Workbook

Sheet PLAN
A1: Self-Reliance Plan
A2: Expanded working version of the Self-Reliance Plan form (PD60007387). Fill in the yellow cells. Steps 2 (income & expenses) are on the Income, Expenses, and Debts tabs; results are on the Summary tab.
A4: Member Information
A5: Name
A6: Phone / email
A7: Address
A8: Date of review
A9: Reviewed with (leader)
A11: Household members
A12: Name | B12: Relationship | C12: Age | D12: Employment / school status | E12: Health or special needs | F12: Notes
A22: Step 1: What are my needs?
A23: Immediate needs (food, clothing, medical/emotional care, housing)
A24: Longer-term needs (education, improved employment)
A26: Step 2: What are my income and expenses? → see Income, Expenses, Debts, and Summary tabs
A28: Step 3: What other resources are available?
A29: Individual resources and skills
A30: Help available from family members
A31: Relevant community resources
A33: Step 4: What is my personal or family plan to become more self-reliant?
A34: Consider participating in a self-reliance group.
A35: Resources and skills needed | C35: Steps to be taken | F35: By when
A43: Step 5: What work or service will I contribute in return for any assistance I may receive?
A44: Ideas to share with the bishop or branch president
A45: Work or service assignment (after consulting with bishop)
A47: Commitment
A48: Member's signature | E48: Date
A49: Spouse's signature | E49: Date

Sheet SUMMARY
A1: Financial Summary
A2: Everything on this tab calculates from the Income, Expenses, and Debts tabs — no entry needed. Use the bottom section to copy totals onto the official Self-Reliance Plan form.
A4: Key Figures | B4: Monthly | C4: Notes
A5: Total monthly income | B5: =INCOME!F42
A6: Total monthly expenses | B6: =EXPENSES!E128
A7: Monthly surplus / (shortfall) | B7: =B5-B6 | C7: Negative = spending more than comes in
A8: Discretionary expenses (could be reduced) | B8: =SUMIFS(EXPENSES!E5:E126,EXPENSES!F5:F126,"Discretionary") | C8: Rows marked Discretionary on Expenses tab
A9: Surplus / (shortfall) if discretionary cut | B9: =B7+B8
A10: Essential expenses only | B10: =SUMIFS(EXPENSES!E5:E126,EXPENSES!F5:F126,"Essential") | C10: Bare-minimum monthly need
A12: Debt & Risk Indicators | B12: Value | C12: Guideline
A13: Total past-due amount (bills + debts) | B13: =EXPENSES!I128 | C13: Urgent — address first
A14: Total debt balance owed | B14: =DEBTS!C21
A15: Housing cost as % of income | B15: =IFERROR(SUMIFS(EXPENSES!E5:E126,EXPENSES!A5:A126,"Housing")/B5,0) | C15: Under 30% is generally considered affordable
A16: Debt payments as % of income | B16: =IFERROR(DEBTS!E21/B5,0) | C16: Over 20% (excl. housing & car) signals strain
A17: Income-to-expense ratio | B17: =IFERROR(B5/B6,0) | C17: Below 1.00 = income doesn't cover expenses
A19: Expenses by Category | B19: Monthly | C19: % of Expenses | D19: Past Due
A20: Tithes & Offerings | B20: =SUMIFS(EXPENSES!$E$5:$E$126,EXPENSES!$A$5:$A$126,A20) | C20: =IFERROR(B20/$B$6,0) | D20: =SUMIFS(EXPENSES!$I$5:$I$126,EXPENSES!$A$5:$A$126,A20)
A21: Housing | B21: =SUMIFS(EXPENSES!$E$5:$E$126,EXPENSES!$A$5:$A$126,A21) | C21: =IFERROR(B21/$B$6,0) | D21: =SUMIFS(EXPENSES!$I$5:$I$126,EXPENSES!$A$5:$A$126,A21)
A22: Utilities | B22: =SUMIFS(EXPENSES!$E$5:$E$126,EXPENSES!$A$5:$A$126,A22) | C22: =IFERROR(B22/$B$6,0) | D22: =SUMIFS(EXPENSES!$I$5:$I$126,EXPENSES!$A$5:$A$126,A22)
A23: Food | B23: =SUMIFS(EXPENSES!$E$5:$E$126,EXPENSES!$A$5:$A$126,A23) | C23: =IFERROR(B23/$B$6,0) | D23: =SUMIFS(EXPENSES!$I$5:$I$126,EXPENSES!$A$5:$A$126,A23)
A24: Household & Personal | B24: =SUMIFS(EXPENSES!$E$5:$E$126,EXPENSES!$A$5:$A$126,A24) | C24: =IFERROR(B24/$B$6,0) | D24: =SUMIFS(EXPENSES!$I$5:$I$126,EXPENSES!$A$5:$A$126,A24)
A25: Clothing | B25: =SUMIFS(EXPENSES!$E$5:$E$126,EXPENSES!$A$5:$A$126,A25) | C25: =IFERROR(B25/$B$6,0) | D25: =SUMIFS(EXPENSES!$I$5:$I$126,EXPENSES!$A$5:$A$126,A25)
A26: Transportation | B26: =SUMIFS(EXPENSES!$E$5:$E$126,EXPENSES!$A$5:$A$126,A26) | C26: =IFERROR(B26/$B$6,0) | D26: =SUMIFS(EXPENSES!$I$5:$I$126,EXPENSES!$A$5:$A$126,A26)
A27: Medical & Health | B27: =SUMIFS(EXPENSES!$E$5:$E$126,EXPENSES!$A$5:$A$126,A27) | C27: =IFERROR(B27/$B$6,0) | D27: =SUMIFS(EXPENSES!$I$5:$I$126,EXPENSES!$A$5:$A$126,A27)
A28: Childcare & Dependents | B28: =SUMIFS(EXPENSES!$E$5:$E$126,EXPENSES!$A$5:$A$126,A28) | C28: =IFERROR(B28/$B$6,0) | D28: =SUMIFS(EXPENSES!$I$5:$I$126,EXPENSES!$A$5:$A$126,A28)
A29: Education | B29: =SUMIFS(EXPENSES!$E$5:$E$126,EXPENSES!$A$5:$A$126,A29) | C29: =IFERROR(B29/$B$6,0) | D29: =SUMIFS(EXPENSES!$I$5:$I$126,EXPENSES!$A$5:$A$126,A29)
A30: Debt Payments | B30: =SUMIFS(EXPENSES!$E$5:$E$126,EXPENSES!$A$5:$A$126,A30) | C30: =IFERROR(B30/$B$6,0) | D30: =SUMIFS(EXPENSES!$I$5:$I$126,EXPENSES!$A$5:$A$126,A30)
A31: Legal & Government | B31: =SUMIFS(EXPENSES!$E$5:$E$126,EXPENSES!$A$5:$A$126,A31) | C31: =IFERROR(B31/$B$6,0) | D31: =SUMIFS(EXPENSES!$I$5:$I$126,EXPENSES!$A$5:$A$126,A31)
... A36: Irregular / Annual Costs | B36: =SUMIFS(EXPENSES!$E$5:$E$126,EXPENSES!$A$5:$A$126,A36) | C36: =IFERROR(B36/$B$6,0) | D36: =SUMIFS(EXPENSES!$I$5:$I$126,EXPENSES!$A$5:$A$126,A36)
A37: Total | B37: =SUM(B20:B36) | C37: =IFERROR(B37/$B$6,0) | D37: =SUM(D20:D36)
A39: Transfer to Official SRP Form — Income | B39: Monthly
A40: Income from all household members | B40: =SUMIFS(INCOME!$F$5:$F$40,INCOME!$G$5:$G$40,A40)
A41: Other financial sources (family, others) | B41: =SUMIFS(INCOME!$F$5:$F$40,INCOME!$G$5:$G$40,A41)
A42: Government assistance | B42: =SUMIFS(INCOME!$F$5:$F$40,INCOME!$G$5:$G$40,A42)
A43: Total | B43: =SUM(B40:B42)
A45: Transfer to Official SRP Form — Expenses | B45: Monthly
A46: Tithes, offerings | B46: =SUMIFS(EXPENSES!$E$5:$E$126,EXPENSES!$J$5:$J$126,A46)
A47: Food | B47: =SUMIFS(EXPENSES!$E$5:$E$126,EXPENSES!$J$5:$J$126,A47)
A48: Housing | B48: =SUMIFS(EXPENSES!$E$5:$E$126,EXPENSES!$J$5:$J$126,A48)
A49: Water | B49: =SUMIFS(EXPENSES!$E$5:$E$126,EXPENSES!$J$5:$J$126,A49)
A50: Medical | B50: =SUMIFS(EXPENSES!$E$5:$E$126,EXPENSES!$J$5:$J$126,A50)
A51: Transportation | B51: =SUMIFS(EXPENSES!$E$5:$E$126,EXPENSES!$J$5:$J$126,A51)
A52: Education | B52: =SUMIFS(EXPENSES!$E$5:$E$126,EXPENSES!$J$5:$J$126,A52)
A53: Debt payments | B53: =SUMIFS(EXPENSES!$E$5:$E$126,EXPENSES!$J$5:$J$126,A53)
A54: Clothing | B54: =SUMIFS(EXPENSES!$E$5:$E$126,EXPENSES!$J$5:$J$126,A54)
A55: Electricity, fuel | B55: =SUMIFS(EXPENSES!$E$5:$E$126,EXPENSES!$J$5:$J$126,A55)
A56: Other | B56: =SUMIFS(EXPENSES!$E$5:$E$126,EXPENSES!$J$5:$J$126,A56)
A57: Total | B57: =SUM(B46:B56)
A58: Expenses that can be reduced or eliminated | B58: =B8
A60: Liquid Funds | B60: Value | C60: Notes
A61: Liquid funds available to use | B61: =INCOME!$F$53 | C61: Cash, checking, savings, 401(k) after est. penalty — Income tab
A62: Months of expenses liquid funds would cover | B62: =INCOME!$F$54 | C62: Below 1.0 = less than one month of cushion

Sheet INCOME
A1: Monthly Income
A2: Fill in the yellow cells only (blue text). Choose Frequency from the dropdown — the Monthly column converts automatically (e.g. Groceries $150 Weekly → $650.00/mo). Rename any 'Other' row to fit. Grey columns calculate on their own. Include every household member's income. Use take-home (net) pay.
A4: Category | B4: Source | C4: Household Member | D4: Amount | E4: Frequency | F4: Monthly | G4: SRP Form Line | H4: Notes
B5: EARNED INCOME | F5: =SUM(F6:F12)
A6: Earned Income | B6: Wages — primary earner | E6: Monthly | F6: =IF(D6="",0,D6*IFERROR(INDEX(LISTS!$B$2:$B$8,MATCH(E6,LISTS!$A$2:$A$8,0)),1)) | G6: Income from all household members
A7: Earned Income | B7: Wages — spouse | E7: Monthly | F7: =IF(D7="",0,D7*IFERROR(INDEX(LISTS!$B$2:$B$8,MATCH(E7,LISTS!$A$2:$A$8,0)),1)) | G7: Income from all household members
A8: Earned Income | B8: Wages — other household members | E8: Monthly | F8: =IF(D8="",0,D8*IFERROR(INDEX(LISTS!$B$2:$B$8,MATCH(E8,LISTS!$A$2:$A$8,0)),1)) | G8: Income from all household members
A9: Earned Income | B9: Tips / commissions / overtime | E9: Monthly | F9: =IF(D9="",0,D9*IFERROR(INDEX(LISTS!$B$2:$B$8,MATCH(E9,LISTS!$A$2:$A$8,0)),1)) | G9: Income from all household members
A10: Earned Income | B10: Self-employment / gig work (net) | E10: Monthly | F10: =IF(D10="",0,D10*IFERROR(INDEX(LISTS!$B$2:$B$8,MATCH(E10,LISTS!$A$2:$A$8,0)),1)) | G10: Income from all household members
A11: Earned Income | B11: Side jobs / odd jobs | E11: Monthly | F11: =IF(D11="",0,D11*IFERROR(INDEX(LISTS!$B$2:$B$8,MATCH(E11,LISTS!$A$2:$A$8,0)),1)) | G11: Income from all household members
A12: Earned Income | B12: Other (specify) | E12: Monthly | F12: =IF(D12="",0,D12*IFERROR(INDEX(LISTS!$B$2:$B$8,MATCH(E12,LISTS!$A$2:$A$8,0)),1)) | G12: Income from all household members
B13: BENEFITS | F13: =SUM(F14:F20)
A14: Benefits | B14: Social Security (retirement / survivor) | E14: Monthly | F14: =IF(D14="",0,D14*IFERROR(INDEX(LISTS!$B$2:$B$8,MATCH(E14,LISTS!$A$2:$A$8,0)),1)) | G14: Income from all household members
A15: Benefits | B15: SSI / SSDI | E15: Monthly | F15: =IF(D15="",0,D15*IFERROR(INDEX(LISTS!$B$2:$B$8,MATCH(E15,LISTS!$A$2:$A$8,0)),1)) | G15: Government assistance
A16: Benefits | B16: Pension / retirement withdrawals | E16: Monthly | F16: =IF(D16="",0,D16*IFERROR(INDEX(LISTS!$B$2:$B$8,MATCH(E16,LISTS!$A$2:$A$8,0)),1)) | G16: Income from all household members
A17: Benefits | B17: Unemployment | E17: Monthly | F17: =IF(D17="",0,D17*IFERROR(INDEX(LISTS!$B$2:$B$8,MATCH(E17,LISTS!$A$2:$A$8,0)),1)) | G17: Government assistance
A18: Benefits | B18: VA benefits | E18: Monthly | F18: =IF(D18="",0,D18*IFERROR(INDEX(LISTS!$B$2:$B$8,MATCH(E18,LISTS!$A$2:$A$8,0)),1)) | G18: Income from all household members
A19: Benefits | B19: Workers' comp / disability | E19: Monthly | F19: =IF(D19="",0,D19*IFERROR(INDEX(LISTS!$B$2:$B$8,MATCH(E19,LISTS!$A$2:$A$8,0)),1)) | G19: Income from all household members
A20: Benefits | B20: Other (specify) | E20: Monthly | F20: =IF(D20="",0,D20*IFERROR(INDEX(LISTS!$B$2:$B$8,MATCH(E20,LISTS!$A$2:$A$8,0)),1)) | G20: Income from all household members
B21: GOVERNMENT ASSISTANCE | F21: =SUM(F22:F28)
A22: Government Assistance | B22: SNAP (food stamps) | E22: Monthly | F22: =IF(D22="",0,D22*IFERROR(INDEX(LISTS!$B$2:$B$8,MATCH(E22,LISTS!$A$2:$A$8,0)),1)) | G22: Government assistance
A23: Government Assistance | B23: WIC | E23: Monthly | F23: =IF(D23="",0,D23*IFERROR(INDEX(LISTS!$B$2:$B$8,MATCH(E23,LISTS!$A$2:$A$8,0)),1)) | G23: Government assistance
A24: Government Assistance | B24: TANF / cash assistance | E24: Monthly | F24: =IF(D24="",0,D24*IFERROR(INDEX(LISTS!$B$2:$B$8,MATCH(E24,LISTS!$A$2:$A$8,0)),1)) | G24: Government assistance
A25: Government Assistance | B25: Housing assistance (Section 8, etc.) | E25: Monthly | F25: =IF(D25="",0,D25*IFERROR(INDEX(LISTS!$B$2:$B$8,MATCH(E25,LISTS!$A$2:$A$8,0)),1)) | G25: Government assistance
A26: Government Assistance | B26: Utility assistance (LIHEAP) | E26: Monthly | F26: =IF(D26="",0,D26*IFERROR(INDEX(LISTS!$B$2:$B$8,MATCH(E26,LISTS!$A$2:$A$8,0)),1)) | G26: Government assistance
A27: Government Assistance | B27: Medicaid / CHIP (value of premiums covered) | E27: Monthly | F27: =IF(D27="",0,D27*IFERROR(INDEX(LISTS!$B$2:$B$8,MATCH(E27,LISTS!$A$2:$A$8,0)),1)) | G27: Government assistance
A28: Government Assistance | B28: Other (specify) | E28: Monthly | F28: =IF(D28="",0,D28*IFERROR(INDEX(LISTS!$B$2:$B$8,MATCH(E28,LISTS!$A$2:$A$8,0)),1)) | G28: Government assistance
B29: SUPPORT RECEIVED | F29: =SUM(F30:F35)
A30: Support Received | B30: Child support received | E30: Monthly | F30: =IF(D30="",0,D30*IFERROR(INDEX(LISTS!$B$2:$B$8,MATCH(E30,LISTS!$A$2:$A$8,0)),1)) | G30: Other financial sources (family, others)
A31: Support Received | B31: Alimony received | E31: Monthly | F31: =IF(D31="",0,D31*IFERROR(INDEX(LISTS!$B$2:$B$8,MATCH(E31,LISTS!$A$2:$A$8,0)),1)) | G31: Other financial sources (family, others)
A32: Support Received | B32: Help from family | E32: Monthly | F32: =IF(D32="",0,D32*IFERROR(INDEX(LISTS!$B$2:$B$8,MATCH(E32,LISTS!$A$2:$A$8,0)),1)) | G32: Other financial sources (family, others)
A33: Support Received | B33: Help from friends / others | E33: Monthly | F33: =IF(D33="",0,D33*IFERROR(INDEX(LISTS!$B$2:$B$8,MATCH(E33,LISTS!$A$2:$A$8,0)),1)) | G33: Other financial sources (family, others)
A34: Support Received | B34: Current Church welfare assistance | E34: Monthly | F34: =IF(D34="",0,D34*IFERROR(INDEX(LISTS!$B$2:$B$8,MATCH(E34,LISTS!$A$2:$A$8,0)),1)) | G34: Other financial sources (family, others)
A35: Support Received | B35: Other (specify) | E35: Monthly | F35: =IF(D35="",0,D35*IFERROR(INDEX(LISTS!$B$2:$B$8,MATCH(E35,LISTS!$A$2:$A$8,0)),1)) | G35: Other financial sources (family, others)
B36: OTHER INCOME | F36: =SUM(F37:F40)
A37: Other Income | B37: Rental income (net) | E37: Monthly | F37: =IF(D37="",0,D37*IFERROR(INDEX(LISTS!$B$2:$B$8,MATCH(E37,LISTS!$A$2:$A$8,0)),1)) | G37: Income from all household members
A38: Other Income | B38: Tax refund (enter annual) | E38: Monthly | F38: =IF(D38="",0,D38*IFERROR(INDEX(LISTS!$B$2:$B$8,MATCH(E38,LISTS!$A$2:$A$8,0)),1)) | G38: Income from all household members
A39: Other Income | B39: Student aid / grants (living portion) | E39: Monthly | F39: =IF(D39="",0,D39*IFERROR(INDEX(LISTS!$B$2:$B$8,MATCH(E39,LISTS!$A$2:$A$8,0)),1)) | G39: Other financial sources (family, others)
A40: Other Income | B40: Other (specify) | E40: Monthly | F40: =IF(D40="",0,D40*IFERROR(INDEX(LISTS!$B$2:$B$8,MATCH(E40,LISTS!$A$2:$A$8,0)),1)) | G40: Other financial sources (family, others)
B42: TOTAL MONTHLY INCOME | F42: =SUMIFS(F5:F40,A5:A40,"<>")
B44: LIQUID FUNDS & SAVINGS (balances on hand — not counted as monthly income)
A45: Category | B45: Account / Source | C45: Household Member | D45: Current Balance | E45: Access | F45: Available to Use | G45: Est. Penalty / Tax % | H45: Notes
A46: Liquid Funds | B46: Cash on hand | E46: Immediate | F46: =IF(D46="",0,IF(E46="Not accessible",0,D46*(1-N(G46))))
A47: Liquid Funds | B47: Checking account balance | E47: Immediate | F47: =IF(D47="",0,IF(E47="Not accessible",0,D47*(1-N(G47))))
A48: Liquid Funds | B48: Savings account balance | E48: Immediate | F48: =IF(D48="",0,IF(E48="Not accessible",0,D48*(1-N(G48))))
A49: Liquid Funds | B49: 401(k) / retirement account (vested balance) | E49: Penalty / tax to withdraw | F49: =IF(D49="",0,IF(E49="Not accessible",0,D49*(1-N(G49)))) | G49: 0.3 | H49: Estimate: 10% early-withdrawal penalty + ~20% tax withholding if under 59½ — adjust. A 401(k) loan may avoid the penalty.
A50: Liquid Funds | B50: Other savings & investments (CDs, brokerage, HSA, etc.) | E50: Within 30 days | F50: =IF(D50="",0,IF(E50="Not accessible",0,D50*(1-N(G50))))
A51: Liquid Funds | B51: Other (specify) | E51: Immediate | F51: =IF(D51="",0,IF(E51="Not accessible",0,D51*(1-N(G51))))
B53: TOTAL LIQUID FUNDS AVAILABLE | D53: =SUM(D46:D51) | F53: =SUM(F46:F51)
B54: Months of expenses these funds would cover | F54: =IFERROR(F53/EXPENSES!$E$128,0)
B55: Available to Use = balance less the estimated penalty/tax %; 'Not accessible' counts as $0. Balances are a snapshot — note the date in Notes.

Sheet EXPENSES
A1: Monthly Expenses
A2: Fill in the yellow cells only (blue text). Choose Frequency from the dropdown — the Monthly column converts automatically (e.g. Groceries $150 Weekly → $650.00/mo). Rename any 'Other' row to fit. Grey columns calculate on their own. Type drives the 'could be reduced' total on the Summary. 'Form line' maps each row to the official Self-Reliance Plan form.
A4: Category | B4: Expense | C4: Amount | D4: Frequency | E4: Monthly | F4: Type | G4: Auto Pay | H4: Due Date | I4: Past Due ($) | J4: SRP Form Line | K4: Notes | L4: Code
B5: TITHES & OFFERINGS | E5: =SUM(E6:E10) | I5: =SUM(I6:I10)
A6: Tithes & Offerings | B6: Tithing | D6: Monthly | E6: =IF(C6="",0,C6*IFERROR(INDEX(LISTS!$B$2:$B$8,MATCH(D6,LISTS!$A$2:$A$8,0)),1)) | F6: Essential | G6: FALSE | J6: Tithes, offerings | L6: TTH-01
A7: Tithes & Offerings | B7: Fast offering | D7: Monthly | E7: =IF(C7="",0,C7*IFERROR(INDEX(LISTS!$B$2:$B$8,MATCH(D7,LISTS!$A$2:$A$8,0)),1)) | F7: Essential | G7: FALSE | J7: Tithes, offerings | L7: TTH-02
A8: Tithes & Offerings | B8: Other donations (missionary, humanitarian, etc.) | D8: Monthly | E8: =IF(C8="",0,C8*IFERROR(INDEX(LISTS!$B$2:$B$8,MATCH(D8,LISTS!$A$2:$A$8,0)),1)) | F8: Important | G8: FALSE | J8: Tithes, offerings | L8: TTH-03
A9: Tithes & Offerings | B9: Other (specify) | D9: Monthly | E9: =IF(C9="",0,C9*IFERROR(INDEX(LISTS!$B$2:$B$8,MATCH(D9,LISTS!$A$2:$A$8,0)),1)) | F9: Important | G9: FALSE | J9: Other | L9: TTH-04
A10: Tithes & Offerings | B10: Other (specify) | D10: Monthly | E10: =IF(C10="",0,C10*IFERROR(INDEX(LISTS!$B$2:$B$8,MATCH(D10,LISTS!$A$2:$A$8,0)),1)) | F10: Important | G10: FALSE | J10: Other | L10: TTH-05
B11: HOUSING | E11: =SUM(E12:E19) | I11: =SUM(I12:I19)
A12: Housing | B12: Rent or mortgage | D12: Monthly | E12: =IF(C12="",0,C12*IFERROR(INDEX(LISTS!$B$2:$B$8,MATCH(D12,LISTS!$A$2:$A$8,0)),1)) | F12: Essential | G12: FALSE | J12: Housing | L12: HOU-01
A13: Housing | B13: Property taxes (if not in mortgage) | D13: Monthly | E13: =IF(C13="",0,C13*IFERROR(INDEX(LISTS!$B$2:$B$8,MATCH(D13,LISTS!$A$2:$A$8,0)),1)) | F13: Essential | G13: FALSE | J13: Housing | L13: HOU-02
A14: Housing | B14: Homeowners / renters insurance | D14: Monthly | E14: =IF(C14="",0,C14*IFERROR(INDEX(LISTS!$B$2:$B$8,MATCH(D14,LISTS!$A$2:$A$8,0)),1)) | F14: Essential | G14: FALSE | J14: Housing | L14: HOU-03
A15: Housing | B15: HOA or lot rent | D15: Monthly | E15: =IF(C15="",0,C15*IFERROR(INDEX(LISTS!$B$2:$B$8,MATCH(D15,LISTS!$A$2:$A$8,0)),1)) | F15: Essential | G15: FALSE | J15: Housing | L15: HOU-04
A16: Housing | B16: Home repairs & maintenance | D16: Monthly | E16: =IF(C16="",0,C16*IFERROR(INDEX(LISTS!$B$2:$B$8,MATCH(D16,LISTS!$A$2:$A$8,0)),1)) | F16: Important | G16: FALSE | J16: Housing | L16: HOU-05
A17: Housing | B17: Storage unit | D17: Monthly | E17: =IF(C17="",0,C17*IFERROR(INDEX(LISTS!$B$2:$B$8,MATCH(D17,LISTS!$A$2:$A$8,0)),1)) | F17: Discretionary | G17: FALSE | J17: Housing | L17: HOU-06
A18: Housing | B18: Other (specify) | D18: Monthly | E18: =IF(C18="",0,C18*IFERROR(INDEX(LISTS!$B$2:$B$8,MATCH(D18,LISTS!$A$2:$A$8,0)),1)) | F18: Important | G18: FALSE | J18: Other | L18: HOU-07
A19: Housing | B19: Other (specify) | D19: Monthly | E19: =IF(C19="",0,C19*IFERROR(INDEX(LISTS!$B$2:$B$8,MATCH(D19,LISTS!$A$2:$A$8,0)),1)) | F19: Important | G19: FALSE | J19: Other | L19: HOU-08
B20: UTILITIES | E20: =SUM(E21:E29) | I20: =SUM(I21:I29)
A21: Utilities | B21: Electricity | D21: Monthly | E21: =IF(C21="",0,C21*IFERROR(INDEX(LISTS!$B$2:$B$8,MATCH(D21,LISTS!$A$2:$A$8,0)),1)) | F21: Essential | G21: FALSE | J21: Electricity, fuel | L21: UTL-01
A22: Utilities | B22: Natural gas / propane / heating oil / wood | D22: Monthly | E22: =IF(C22="",0,C22*IFERROR(INDEX(LISTS!$B$2:$B$8,MATCH(D22,LISTS!$A$2:$A$8,0)),1)) | F22: Essential | G22: FALSE | J22: Electricity, fuel | L22: UTL-02
A23: Utilities | B23: Water & sewer | D23: Monthly | E23: =IF(C23="",0,C23*IFERROR(INDEX(LISTS!$B$2:$B$8,MATCH(D23,LISTS!$A$2:$A$8,0)),1)) | F23: Essential | G23: FALSE | J23: Water | L23: UTL-03
A24: Utilities | B24: Trash | D24: Monthly | E24: =IF(C24="",0,C24*IFERROR(INDEX(LISTS!$B$2:$B$8,MATCH(D24,LISTS!$A$2:$A$8,0)),1)) | F24: Essential | G24: FALSE | J24: Other | L24: UTL-04
A25: Utilities | B25: Phone (cell & landline) | D25: Monthly | E25: =IF(C25="",0,C25*IFERROR(INDEX(LISTS!$B$2:$B$8,MATCH(D25,LISTS!$A$2:$A$8,0)),1)) | F25: Important | G25: FALSE | J25: Other | L25: UTL-05
A26: Utilities | B26: Internet | D26: Monthly | E26: =IF(C26="",0,C26*IFERROR(INDEX(LISTS!$B$2:$B$8,MATCH(D26,LISTS!$A$2:$A$8,0)),1)) | F26: Essential | G26: FALSE | J26: Other | L26: UTL-06
A27: Utilities | B27: Cable / satellite TV | D27: Monthly | E27: =IF(C27="",0,C27*IFERROR(INDEX(LISTS!$B$2:$B$8,MATCH(D27,LISTS!$A$2:$A$8,0)),1)) | F27: Discretionary | G27: FALSE | J27: Other | L27: UTL-07
A28: Utilities | B28: Other (specify) | D28: Monthly | E28: =IF(C28="",0,C28*IFERROR(INDEX(LISTS!$B$2:$B$8,MATCH(D28,LISTS!$A$2:$A$8,0)),1)) | F28: Important | G28: FALSE | J28: Other | L28: UTL-08
A29: Utilities | B29: Other (specify) | D29: Monthly | E29: =IF(C29="",0,C29*IFERROR(INDEX(LISTS!$B$2:$B$8,MATCH(D29,LISTS!$A$2:$A$8,0)),1)) | F29: Important | G29: FALSE | J29: Other | L29: UTL-09
B30: FOOD | E30: =SUM(E31:E36) | I30: =SUM(I31:I36)
A31: Food | B31: Groceries | D31: Monthly | E31: =IF(C31="",0,C31*IFERROR(INDEX(LISTS!$B$2:$B$8,MATCH(D31,LISTS!$A$2:$A$8,0)),1)) | F31: Essential | G31: FALSE | J31: Food | L31: FOD-01
A32: Food | B32: Eating out & fast food | D32: Monthly | E32: =IF(C32="",0,C32*IFERROR(INDEX(LISTS!$B$2:$B$8,MATCH(D32,LISTS!$A$2:$A$8,0)),1)) | F32: Discretionary | G32: FALSE | J32: Food | L32: FOD-02
A33: Food | B33: School lunches | D33: Monthly | E33: =IF(C33="",0,C33*IFERROR(INDEX(LISTS!$B$2:$B$8,MATCH(D33,LISTS!$A$2:$A$8,0)),1)) | F33: Important | G33: FALSE | J33: Food | L33: FOD-03
A34: Food | B34: Baby formula & food | D34: Monthly | E34: =IF(C34="",0,C34*IFERROR(INDEX(LISTS!$B$2:$B$8,MATCH(D34,LISTS!$A$2:$A$8,0)),1)) | F34: Essential | G34: FALSE | J34: Food | L34: FOD-04
A35: Food | B35: Other (specify) | D35: Monthly | E35: =IF(C35="",0,C35*IFERROR(INDEX(LISTS!$B$2:$B$8,MATCH(D35,LISTS!$A$2:$A$8,0)),1)) | F35: Important | G35: FALSE | J35: Other | L35: FOD-05
A36: Food | B36: Other (specify) | D36: Monthly | E36: =IF(C36="",0,C36*IFERROR(INDEX(LISTS!$B$2:$B$8,MATCH(D36,LISTS!$A$2:$A$8,0)),1)) | F36: Important | G36: FALSE | J36: Other | L36: FOD-06
B37: HOUSEHOLD & PERSONAL | E37: =SUM(E38:E44) | I37: =SUM(I38:I44)
A38: Household & Personal | B38: Toiletries & hygiene | D38: Monthly | E38: =IF(C38="",0,C38*IFERROR(INDEX(LISTS!$B$2:$B$8,MATCH(D38,LISTS!$A$2:$A$8,0)),1)) | F38: Essential | G38: FALSE | J38: Other | L38: HHP-01
A39: Household & Personal | B39: Cleaning supplies & paper goods | D39: Monthly | E39: =IF(C39="",0,C39*IFERROR(INDEX(LISTS!$B$2:$B$8,MATCH(D39,LISTS!$A$2:$A$8,0)),1)) | F39: Essential | G39: FALSE | J39: Other | L39: HHP-02
A40: Household & Personal | B40: Laundry / laundromat | D40: Monthly | E40: =IF(C40="",0,C40*IFERROR(INDEX(LISTS!$B$2:$B$8,MATCH(D40,LISTS!$A$2:$A$8,0)),1)) | F40: Essential | G40: FALSE | J40: Other | L40: HHP-03
A41: Household & Personal | B41: Haircuts & grooming | D41: Monthly | E41: =IF(C41="",0,C41*IFERROR(INDEX(LISTS!$B$2:$B$8,MATCH(D41,LISTS!$A$2:$A$8,0)),1)) | F41: Discretionary | G41: FALSE | J41: Other | L41: HHP-04
A42: Household & Personal | B42: Diapers & Wipes | D42: Monthly | E42: =IF(C42="",0,C42*IFERROR(INDEX(LISTS!$B$2:$B$8,MATCH(D42,LISTS!$A$2:$A$8,0)),1)) | F42: Essential | G42: FALSE | J42: Other | L42: HHP-05
A43: Household & Personal | B43: Other (specify) | D43: Monthly | E43: =IF(C43="",0,C43*IFERROR(INDEX(LISTS!$B$2:$B$8,MATCH(D43,LISTS!$A$2:$A$8,0)),1)) | F43: Important | G43: FALSE | J43: Other | L43: HHP-06
A44: Household & Personal | B44: Other (specify) | D44: Monthly | E44: =IF(C44="",0,C44*IFERROR(INDEX(LISTS!$B$2:$B$8,MATCH(D44,LISTS!$A$2:$A$8,0)),1)) | F44: Important | G44: FALSE | J44: Other | L44: HHP-07
B45: CLOTHING | E45: =SUM(E46:E50) | I45: =SUM(I46:I50)
A46: Clothing | B46: Adult clothing & shoes | D46: Monthly | E46: =IF(C46="",0,C46*IFERROR(INDEX(LISTS!$B$2:$B$8,MATCH(D46,LISTS!$A$2:$A$8,0)),1)) | F46: Important | G46: FALSE | J46: Clothing | L46: CLO-01
A47: Clothing | B47: Children's clothing & shoes | D47: Monthly | E47: =IF(C47="",0,C47*IFERROR(INDEX(LISTS!$B$2:$B$8,MATCH(D47,LISTS!$A$2:$A$8,0)),1)) | F47: Important | G47: FALSE | J47: Clothing | L47: CLO-02
A48: Clothing | B48: Work uniforms & boots | D48: Monthly | E48: =IF(C48="",0,C48*IFERROR(INDEX(LISTS!$B$2:$B$8,MATCH(D48,LISTS!$A$2:$A$8,0)),1)) | F48: Essential | G48: FALSE | J48: Clothing | L48: CLO-03
A49: Clothing | B49: Other (specify) | D49: Monthly | E49: =IF(C49="",0,C49*IFERROR(INDEX(LISTS!$B$2:$B$8,MATCH(D49,LISTS!$A$2:$A$8,0)),1)) | F49: Important | G49: FALSE | J49: Other | L49: CLO-04
A50: Clothing | B50: Other (specify) | D50: Monthly | E50: =IF(C50="",0,C50*IFERROR(INDEX(LISTS!$B$2:$B$8,MATCH(D50,LISTS!$A$2:$A$8,0)),1)) | F50: Important | G50: FALSE | J50: Other | L50: CLO-05
B51: TRANSPORTATION | E51: =SUM(E52:E60) | I51: =SUM(I52:I60)
A52: Transportation | B52: Car payment / lease | D52: Monthly | E52: =IF(C52="",0,C52*IFERROR(INDEX(LISTS!$B$2:$B$8,MATCH(D52,LISTS!$A$2:$A$8,0)),1)) | F52: Essential | G52: FALSE | J52: Transportation | L52: TRN-01
A53: Transportation | B53: Auto insurance | D53: Monthly | E53: =IF(C53="",0,C53*IFERROR(INDEX(LISTS!$B$2:$B$8,MATCH(D53,LISTS!$A$2:$A$8,0)),1)) | F53: Essential | G53: FALSE | J53: Transportation | L53: TRN-02
A54: Transportation | B54: Gas / fuel | D54: Monthly | E54: =IF(C54="",0,C54*IFERROR(INDEX(LISTS!$B$2:$B$8,MATCH(D54,LISTS!$A$2:$A$8,0)),1)) | F54: Essential | G54: FALSE | J54: Transportation | L54: TRN-03
A55: Transportation | B55: Maintenance, repairs & tires | D55: Monthly | E55: =IF(C55="",0,C55*IFERROR(INDEX(LISTS!$B$2:$B$8,MATCH(D55,LISTS!$A$2:$A$8,0)),1)) | F55: Important | G55: FALSE | J55: Transportation | L55: TRN-04
A56: Transportation | B56: Registration, license & emissions | D56: Monthly | E56: =IF(C56="",0,C56*IFERROR(INDEX(LISTS!$B$2:$B$8,MATCH(D56,LISTS!$A$2:$A$8,0)),1)) | F56: Essential | G56: FALSE | J56: Transportation | L56: TRN-05
A57: Transportation | B57: Public transit / rideshare | D57: Monthly | E57: =IF(C57="",0,C57*IFERROR(INDEX(LISTS!$B$2:$B$8,MATCH(D57,LISTS!$A$2:$A$8,0)),1)) | F57: Important | G57: FALSE | J57: Transportation | L57: TRN-06
A58: Transportation | B58: Parking & tolls | D58: Monthly | E58: =IF(C58="",0,C58*IFERROR(INDEX(LISTS!$B$2:$B$8,MATCH(D58,LISTS!$A$2:$A$8,0)),1)) | F58: Important | G58: FALSE | J58: Transportation | L58: TRN-07
A59: Transportation | B59: Other (specify) | D59: Monthly | E59: =IF(C59="",0,C59*IFERROR(INDEX(LISTS!$B$2:$B$8,MATCH(D59,LISTS!$A$2:$A$8,0)),1)) | F59: Important | G59: FALSE | J59: Other | L59: TRN-08
A60: Transportation | B60: Other (specify) | D60: Monthly | E60: =IF(C60="",0,C60*IFERROR(INDEX(LISTS!$B$2:$B$8,MATCH(D60,LISTS!$A$2:$A$8,0)),1)) | F60: Important | G60: FALSE | J60: Other | L60: TRN-09
B61: MEDICAL & HEALTH | E61: =SUM(E62:E70) | I61: =SUM(I62:I70)
A62: Medical & Health | B62: Health insurance premiums | D62: Monthly | E62: =IF(C62="",0,C62*IFERROR(INDEX(LISTS!$B$2:$B$8,MATCH(D62,LISTS!$A$2:$A$8,0)),1)) | F62: Essential | G62: FALSE | J62: Medical | L62: MED-01
A63: Medical & Health | B63: Copays & doctor visits | D63: Monthly | E63: =IF(C63="",0,C63*IFERROR(INDEX(LISTS!$B$2:$B$8,MATCH(D63,LISTS!$A$2:$A$8,0)),1)) | F63: Essential | G63: FALSE | J63: Medical | L63: MED-02
A64: Medical & Health | B64: Prescriptions | D64: Monthly | E64: =IF(C64="",0,C64*IFERROR(INDEX(LISTS!$B$2:$B$8,MATCH(D64,LISTS!$A$2:$A$8,0)),1)) | F64: Essential | G64: FALSE | J64: Medical | L64: MED-03
A65: Medical & Health | B65: Dental & vision | D65: Monthly | E65: =IF(C65="",0,C65*IFERROR(INDEX(LISTS!$B$2:$B$8,MATCH(D65,LISTS!$A$2:$A$8,0)),1)) | F65: Important | G65: FALSE | J65: Medical | L65: MED-04
A66: Medical & Health | B66: Counseling | D66: Monthly | E66: =IF(C66="",0,C66*IFERROR(INDEX(LISTS!$B$2:$B$8,MATCH(D66,LISTS!$A$2:$A$8,0)),1)) | F66: Important | G66: FALSE | J66: Medical | L66: MED-05
A67: Medical & Health | B67: Medical equipment & supplies | D67: Monthly | E67: =IF(C67="",0,C67*IFERROR(INDEX(LISTS!$B$2:$B$8,MATCH(D67,LISTS!$A$2:$A$8,0)),1)) | F67: Essential | G67: FALSE | J67: Medical | L67: MED-06
A68: Medical & Health | B68: Life / disability insurance | D68: Monthly | E68: =IF(C68="",0,C68*IFERROR(INDEX(LISTS!$B$2:$B$8,MATCH(D68,LISTS!$A$2:$A$8,0)),1)) | F68: Important | G68: FALSE | J68: Other | L68: MED-07
A69: Medical & Health | B69: Other (specify) | D69: Monthly | E69: =IF(C69="",0,C69*IFERROR(INDEX(LISTS!$B$2:$B$8,MATCH(D69,LISTS!$A$2:$A$8,0)),1)) | F69: Important | G69: FALSE | J69: Other | L69: MED-08
A70: Medical & Health | B70: Other (specify) | D70: Monthly | E70: =IF(C70="",0,C70*IFERROR(INDEX(LISTS!$B$2:$B$8,MATCH(D70,LISTS!$A$2:$A$8,0)),1)) | F70: Important | G70: FALSE | J70: Other | L70: MED-09
B71: CHILDCARE & DEPENDENTS | E71: =SUM(E72:E78) | I71: =SUM(I72:I78)
A72: Childcare & Dependents | B72: Daycare / babysitting | D72: Monthly | E72: =IF(C72="",0,C72*IFERROR(INDEX(LISTS!$B$2:$B$8,MATCH(D72,LISTS!$A$2:$A$8,0)),1)) | F72: Essential | G72: FALSE | J72: Other | L72: CHD-01
A73: Childcare & Dependents | B73: Child support / alimony paid | D73: Monthly | E73: =IF(C73="",0,C73*IFERROR(INDEX(LISTS!$B$2:$B$8,MATCH(D73,LISTS!$A$2:$A$8,0)),1)) | F73: Essential | G73: FALSE | J73: Other | L73: CHD-02
A74: Childcare & Dependents | B74: Support for aging parents / relatives | D74: Monthly | E74: =IF(C74="",0,C74*IFERROR(INDEX(LISTS!$B$2:$B$8,MATCH(D74,LISTS!$A$2:$A$8,0)),1)) | F74: Important | G74: FALSE | J74: Other | L74: CHD-03
A75: Childcare & Dependents | B75: Children's activities & sports | D75: Monthly | E75: =IF(C75="",0,C75*IFERROR(INDEX(LISTS!$B$2:$B$8,MATCH(D75,LISTS!$A$2:$A$8,0)),1)) | F75: Discretionary | G75: FALSE | J75: Other | L75: CHD-04
A76: Childcare & Dependents | B76: Allowances | D76: Monthly | E76: =IF(C76="",0,C76*IFERROR(INDEX(LISTS!$B$2:$B$8,MATCH(D76,LISTS!$A$2:$A$8,0)),1)) | F76: Discretionary | G76: FALSE | J76: Other | L76: CHD-05
A77: Childcare & Dependents | B77: Other (specify) | D77: Monthly | E77: =IF(C77="",0,C77*IFERROR(INDEX(LISTS!$B$2:$B$8,MATCH(D77,LISTS!$A$2:$A$8,0)),1)) | F77: Important | G77: FALSE | J77: Other | L77: CHD-06
A78: Childcare & Dependents | B78: Other (specify) | D78: Monthly | E78: =IF(C78="",0,C78*IFERROR(INDEX(LISTS!$B$2:$B$8,MATCH(D78,LISTS!$A$2:$A$8,0)),1)) | F78: Important | G78: FALSE | J78: Other | L78: CHD-07
B79: EDUCATION | E79: =SUM(E80:E85) | I79: =SUM(I80:I85)
A80: Education | B80: Tuition & fees | D80: Monthly | E80: =IF(C80="",0,C80*IFERROR(INDEX(LISTS!$B$2:$B$8,MATCH(D80,LISTS!$A$2:$A$8,0)),1)) | F80: Important | G80: FALSE | J80: Education | L80: EDU-01
A81: Education | B81: Books & supplies | D81: Monthly | E81: =IF(C81="",0,C81*IFERROR(INDEX(LISTS!$B$2:$B$8,MATCH(D81,LISTS!$A$2:$A$8,0)),1)) | F81: Important | G81: FALSE | J81: Education | L81: EDU-02
A82: Education | B82: School fees & field trips | D82: Monthly | E82: =IF(C82="",0,C82*IFERROR(INDEX(LISTS!$B$2:$B$8,MATCH(D82,LISTS!$A$2:$A$8,0)),1)) | F82: Important | G82: FALSE | J82: Education | L82: EDU-03
A83: Education | B83: Training & certifications | D83: Monthly | E83: =IF(C83="",0,C83*IFERROR(INDEX(LISTS!$B$2:$B$8,MATCH(D83,LISTS!$A$2:$A$8,0)),1)) | F83: Important | G83: FALSE | J83: Education | L83: EDU-04
A84: Education | B84: Other (specify) | D84: Monthly | E84: =IF(C84="",0,C84*IFERROR(INDEX(LISTS!$B$2:$B$8,MATCH(D84,LISTS!$A$2:$A$8,0)),1)) | F84: Important | G84: FALSE | J84: Other | L84: EDU-05
A85: Education | B85: Other (specify) | D85: Monthly | E85: =IF(C85="",0,C85*IFERROR(INDEX(LISTS!$B$2:$B$8,MATCH(D85,LISTS!$A$2:$A$8,0)),1)) | F85: Important | G85: FALSE | J85: Other | L85: EDU-06
B86: DEBT PAYMENTS | E86: =SUM(E87:E87) | I86: =SUM(I87:I87)
A87: Debt Payments | B87: Debt payments — linked from Debts tab | C87: =DEBTS!E21 | D87: Monthly | E87: =IF(C87="",0,C87*IFERROR(INDEX(LISTS!$B$2:$B$8,MATCH(D87,LISTS!$A$2:$A$8,0)),1)) | F87: Essential | I87: =DEBTS!G21 | J87: Debt payments | L87: DBT-01
B88: LEGAL & GOVERNMENT | E88: =SUM(E89:E93) | I88: =SUM(I89:I93)
A89: Legal & Government | B89: Court fines & fees | D89: Monthly | E89: =IF(C89="",0,C89*IFERROR(INDEX(LISTS!$B$2:$B$8,MATCH(D89,LISTS!$A$2:$A$8,0)),1)) | F89: Essential | G89: FALSE | J89: Other | L89: LGL-01
A90: Legal & Government | B90: Legal fees | D90: Monthly | E90: =IF(C90="",0,C90*IFERROR(INDEX(LISTS!$B$2:$B$8,MATCH(D90,LISTS!$A$2:$A$8,0)),1)) | F90: Important | G90: FALSE | J90: Other | L90: LGL-02
A91: Legal & Government | B91: Government payment plans | D91: Monthly | E91: =IF(C91="",0,C91*IFERROR(INDEX(LISTS!$B$2:$B$8,MATCH(D91,LISTS!$A$2:$A$8,0)),1)) | F91: Essential | G91: FALSE | J91: Other | L91: LGL-03
A92: Legal & Government | B92: Other (specify) | D92: Monthly | E92: =IF(C92="",0,C92*IFERROR(INDEX(LISTS!$B$2:$B$8,MATCH(D92,LISTS!$A$2:$A$8,0)),1)) | F92: Important | G92: FALSE | J92: Other | L92: LGL-04
A93: Legal & Government | B93: Other (specify) | D93: Monthly | E93: =IF(C93="",0,C93*IFERROR(INDEX(LISTS!$B$2:$B$8,MATCH(D93,LISTS!$A$2:$A$8,0)),1)) | F93: Important | G93: FALSE | J93: Other | L93: LGL-05
B94: PETS | E94: =SUM(E95:E98) | I94: =SUM(I95:I98)
A95: Pets | B95: Pet food & supplies | D95: Monthly | E95: =IF(C95="",0,C95*IFERROR(INDEX(LISTS!$B$2:$B$8,MATCH(D95,LISTS!$A$2:$A$8,0)),1)) | F95: Discretionary | G95: FALSE | J95: Other | L95: PET-01
A96: Pets | B96: Vet bills | D96: Monthly | E96: =IF(C96="",0,C96*IFERROR(INDEX(LISTS!$B$2:$B$8,MATCH(D96,LISTS!$A$2:$A$8,0)),1)) | F96: Important | G96: FALSE | J96: Other | L96: PET-02
A97: Pets | B97: Other (specify) | D97: Monthly | E97: =IF(C97="",0,C97*IFERROR(INDEX(LISTS!$B$2:$B$8,MATCH(D97,LISTS!$A$2:$A$8,0)),1)) | F97: Important | G97: FALSE | J97: Other | L97: PET-03
A98: Pets | B98: Other (specify) | D98: Monthly | E98: =IF(C98="",0,C98*IFERROR(INDEX(LISTS!$B$2:$B$8,MATCH(D98,LISTS!$A$2:$A$8,0)),1)) | F98: Important | G98: FALSE | J98: Other | L98: PET-04
B99: SUBSCRIPTIONS & MEMBERSHIPS | E99: =SUM(E100:E105) | I99: =SUM(I100:I105)
A100: Subscriptions & Memberships | B100: Streaming services | D100: Monthly | E100: =IF(C100="",0,C100*IFERROR(INDEX(LISTS!$B$2:$B$8,MATCH(D100,LISTS!$A$2:$A$8,0)),1)) | F100: Discretionary | G100: FALSE | J100: Other | L100: SUB-01
A101: Subscriptions & Memberships | B101: Gym | D101: Monthly | E101: =IF(C101="",0,C101*IFERROR(INDEX(LISTS!$B$2:$B$8,MATCH(D101,LISTS!$A$2:$A$8,0)),1)) | F101: Discretionary | G101: FALSE | J101: Other | L101: SUB-02
...

Sheet DEBTS
A1: Debts & Past-Due Accounts
A2: List each debt NOT already counted as rent/mortgage or car payment on the Expenses tab (credit cards, medical bills, personal / payday / title loans, buy-now-pay-later, back taxes, collections, student loans). Monthly payments flow to the Debt Payments line on Expenses.
A4: Creditor | B4: Debt Type | C4: Balance Owed | D4: Interest Rate | E4: Min. Monthly Payment | F4: Months Behind | G4: Past Due ($) | H4: Auto Pay | I4: Due Date | J4: Notes
H5: FALSE
H6: FALSE
H7: FALSE
H8: FALSE
H9: FALSE
H10: FALSE
H11: FALSE
H12: FALSE
H13: FALSE
H14: FALSE
H15: FALSE
H16: FALSE
... H20: FALSE
A21: TOTALS | C21: =SUM(C5:C20) | E21: =SUM(E5:E20) | G21: =SUM(G5:G20)
A22: Enter interest rate as a percent (e.g. 24.99%).

Sheet SUPPORT PLAN
A1: Monthly Support Plan (3 months)
A2: Planned support for each expense line for the next 3 months. Enter amounts in the yellow cells under the source covering it (Member, Family, Church, Social Services, Other). Each month has its own Need column (defaults: Month-1 = Total Due incl. past due, Months 2–3 = Monthly Need — overwrite as needed). Each month's Total turns green when that month's need is covered and orange when it isn't; 3-Month Need and Covered − Need use these month needs. Plan start month (C4) dates the plan for the Expenditure Summary.
A4: Plan start month: | E4: Member: | F4: =IF(PLAN!B5="","",PLAN!B5)
G5: ="Month-1"&IF($C$4="",""," "&UPPER(TEXT(EDATE($C$4,0),"mmm-yyyy"))) | N5: ="Month-2"&IF($C$4="",""," "&UPPER(TEXT(EDATE($C$4,1),"mmm-yyyy"))) | U5: ="Month-3"&IF($C$4="",""," "&UPPER(TEXT(EDATE($C$4,2),"mmm-yyyy"))) | AB5: 3-MONTH TOTALS BY SOURCE
A6: Code | B6: Expense | C6: Monthly Need (Expenses) | D6: Past Due (Expenses) | E6: Total Due (Need + Past Due) | F6: Paid To / Vendor | G6: Member's Month-1 Need | H6: Member Efforts | I6: Family Contribution | J6: Church Assistance | K6: Social Services | L6: Other Support | M6: Month-1 Total | N6: Member's Month-2 Need | O6: Member Efforts | P6: Family Contribution | Q6: Church Assistance | R6: Social Services | S6: Other Support | T6: Month-2 Total | U6: Member's Month-3 Need | V6: Member Efforts | W6: Family Contribution | X6: Church Assistance | Y6: Social Services | Z6: Other Support | AA6: Month-3 Total | AB6: Member | AC6: Family | AD6: Church | AE6: Social Services | AF6: Other | AG6: 3-Month Total Covered | AH6: 3-Month Need (Month-1 + 2 + 3 Need) | AI6: Covered − Need | AJ6: Notes / Conditions
B7: TITHES & OFFERINGS | C7: =SUM(C8:C12) | D7: =SUM(D8:D12) | E7: =SUM(E8:E12) | G7: =SUM(G8:G12) | H7: =SUM(H8:H12) | I7: =SUM(I8:I12) | J7: =SUM(J8:J12) | K7: =SUM(K8:K12) | L7: =SUM(L8:L12) | M7: =SUM(M8:M12) | N7: =SUM(N8:N12) | ... AI7: =SUM(AI8:AI12)
A8: =EXPENSES!L6 | B8: =EXPENSES!B6 | C8: =EXPENSES!E6 | D8: =EXPENSES!I6 | E8: =C8+D8 | M8: =SUM(H8:L8) | T8: =SUM(O8:S8) | AA8: =SUM(V8:Z8) | AB8: =H8+O8+V8 | AC8: =I8+P8+W8 | AD8: =J8+Q8+X8 | AE8: =K8+R8+Y8 | AF8: =L8+S8+Z8 | AG8: =M8+T8+AA8 | AH8: =G8+N8+U8 | AI8: =AG8-AH8
A9: =EXPENSES!L7 | B9: =EXPENSES!B7 | C9: =EXPENSES!E7 | D9: =EXPENSES!I7 | E9: =C9+D9 | M9: =SUM(H9:L9) | T9: =SUM(O9:S9) | AA9: =SUM(V9:Z9) | AB9: =H9+O9+V9 | AC9: =I9+P9+W9 | AD9: =J9+Q9+X9 | AE9: =K9+R9+Y9 | AF9: =L9+S9+Z9 | AG9: =M9+T9+AA9 | AH9: =G9+N9+U9 | AI9: =AG9-AH9
A10: =EXPENSES!L8 | B10: =EXPENSES!B8 | C10: =EXPENSES!E8 | D10: =EXPENSES!I8 | E10: =C10+D10 | M10: =SUM(H10:L10) | T10: =SUM(O10:S10) | AA10: =SUM(V10:Z10) | AB10: =H10+O10+V10 | AC10: =I10+P10+W10 | AD10: =J10+Q10+X10 | AE10: =K10+R10+Y10 | AF10: =L10+S10+Z10 | AG10: =M10+T10+AA10 | AH10: =G10+N10+U10 | AI10: =AG10-AH10
A11: =EXPENSES!L9 | B11: =EXPENSES!B9 | C11: =EXPENSES!E9 | D11: =EXPENSES!I9 | E11: =C11+D11 | M11: =SUM(H11:L11) | T11: =SUM(O11:S11) | AA11: =SUM(V11:Z11) | AB11: =H11+O11+V11 | AC11: =I11+P11+W11 | AD11: =J11+Q11+X11 | AE11: =K11+R11+Y11 | AF11: =L11+S11+Z11 | AG11: =M11+T11+AA11 | AH11: =G11+N11+U11 | AI11: =AG11-AH11
A12: =EXPENSES!L10 | B12: =EXPENSES!B10 | C12: =EXPENSES!E10 | D12: =EXPENSES!I10 | E12: =C12+D12 | M12: =SUM(H12:L12) | T12: =SUM(O12:S12) | AA12: =SUM(V12:Z12) | AB12: =H12+O12+V12 | AC12: =I12+P12+W12 | AD12: =J12+Q12+X12 | AE12: =K12+R12+Y12 | AF12: =L12+S12+Z12 | AG12: =M12+T12+AA12 | AH12: =G12+N12+U12 | AI12: =AG12-AH12
B13: HOUSING | C13: =SUM(C14:C21) | D13: =SUM(D14:D21) | E13: =SUM(E14:E21) | G13: =SUM(G14:G21) | H13: =SUM(H14:H21) | I13: =SUM(I14:I21) | J13: =SUM(J14:J21) | K13: =SUM(K14:K21) | L13: =SUM(L14:L21) | M13: =SUM(M14:M21) | N13: =SUM(N14:N21) | ... AI13: =SUM(AI14:AI21)
A14: =EXPENSES!L12 | B14: =EXPENSES!B12 | C14: =EXPENSES!E12 | D14: =EXPENSES!I12 | E14: =C14+D14 | M14: =SUM(H14:L14) | T14: =SUM(O14:S14) | AA14: =SUM(V14:Z14) | AB14: =H14+O14+V14 | AC14: =I14+P14+W14 | AD14: =J14+Q14+X14 | AE14: =K14+R14+Y14 | AF14: =L14+S14+Z14 | AG14: =M14+T14+AA14 | AH14: =G14+N14+U14 | AI14: =AG14-AH14
A15: =EXPENSES!L13 | B15: =EXPENSES!B13 | C15: =EXPENSES!E13 | D15: =EXPENSES!I13 | E15: =C15+D15 | M15: =SUM(H15:L15) | T15: =SUM(O15:S15) | AA15: =SUM(V15:Z15) | AB15: =H15+O15+V15 | AC15: =I15+P15+W15 | AD15: =J15+Q15+X15 | AE15: =K15+R15+Y15 | AF15: =L15+S15+Z15 | AG15: =M15+T15+AA15 | AH15: =G15+N15+U15 | AI15: =AG15-AH15
A16: =EXPENSES!L14 | B16: =EXPENSES!B14 | C16: =EXPENSES!E14 | D16: =EXPENSES!I14 | E16: =C16+D16 | M16: =SUM(H16:L16) | T16: =SUM(O16:S16) | AA16: =SUM(V16:Z16) | AB16: =H16+O16+V16 | AC16: =I16+P16+W16 | AD16: =J16+Q16+X16 | AE16: =K16+R16+Y16 | AF16: =L16+S16+Z16 | AG16: =M16+T16+AA16 | AH16: =G16+N16+U16 | AI16: =AG16-AH16
A17: =EXPENSES!L15 | B17: =EXPENSES!B15 | C17: =EXPENSES!E15 | D17: =EXPENSES!I15 | E17: =C17+D17 | M17: =SUM(H17:L17) | T17: =SUM(O17:S17) | AA17: =SUM(V17:Z17) | AB17: =H17+O17+V17 | AC17: =I17+P17+W17 | AD17: =J17+Q17+X17 | AE17: =K17+R17+Y17 | AF17: =L17+S17+Z17 | AG17: =M17+T17+AA17 | AH17: =G17+N17+U17 | AI17: =AG17-AH17
A18: =EXPENSES!L16 | B18: =EXPENSES!B16 | C18: =EXPENSES!E16 | D18: =EXPENSES!I16 | E18: =C18+D18 | M18: =SUM(H18:L18) | T18: =SUM(O18:S18) | AA18: =SUM(V18:Z18) | AB18: =H18+O18+V18 | AC18: =I18+P18+W18 | AD18: =J18+Q18+X18 | AE18: =K18+R18+Y18 | AF18: =L18+S18+Z18 | AG18: =M18+T18+AA18 | AH18: =G18+N18+U18 | AI18: =AG18-AH18
A19: =EXPENSES!L17 | B19: =EXPENSES!B17 | C19: =EXPENSES!E17 | D19: =EXPENSES!I17 | E19: =C19+D19 | M19: =SUM(H19:L19) | T19: =SUM(O19:S19) | AA19: =SUM(V19:Z19) | AB19: =H19+O19+V19 | AC19: =I19+P19+W19 | AD19: =J19+Q19+X19 | AE19: =K19+R19+Y19 | AF19: =L19+S19+Z19 | AG19: =M19+T19+AA19 | AH19: =G19+N19+U19 | AI19: =AG19-AH19
A20: =EXPENSES!L18 | B20: =EXPENSES!B18 | C20: =EXPENSES!E18 | D20: =EXPENSES!I18 | E20: =C20+D20 | M20: =SUM(H20:L20) | T20: =SUM(O20:S20) | AA20: =SUM(V20:Z20) | AB20: =H20+O20+V20 | AC20: =I20+P20+W20 | AD20: =J20+Q20+X20 | AE20: =K20+R20+Y20 | AF20: =L20+S20+Z20 | AG20: =M20+T20+AA20 | AH20: =G20+N20+U20 | AI20: =AG20-AH20
A21: =EXPENSES!L19 | B21: =EXPENSES!B19 | C21: =EXPENSES!E19 | D21: =EXPENSES!I19 | E21: =C21+D21 | M21: =SUM(H21:L21) | T21: =SUM(O21:S21) | AA21: =SUM(V21:Z21) | AB21: =H21+O21+V21 | AC21: =I21+P21+W21 | AD21: =J21+Q21+X21 | AE21: =K21+R21+Y21 | AF21: =L21+S21+Z21 | AG21: =M21+T21+AA21 | AH21: =G21+N21+U21 | AI21: =AG21-AH21
B22: UTILITIES | C22: =SUM(C23:C31) | D22: =SUM(D23:D31) | E22: =SUM(E23:E31) | G22: =SUM(G23:G31) | H22: =SUM(H23:H31) | I22: =SUM(I23:I31) | J22: =SUM(J23:J31) | K22: =SUM(K23:K31) | L22: =SUM(L23:L31) | M22: =SUM(M23:M31) | N22: =SUM(N23:N31) | ... AI22: =SUM(AI23:AI31)
A23: =EXPENSES!L21 | B23: =EXPENSES!B21 | C23: =EXPENSES!E21 | D23: =EXPENSES!I21 | E23: =C23+D23 | M23: =SUM(H23:L23) | T23: =SUM(O23:S23) | AA23: =SUM(V23:Z23) | AB23: =H23+O23+V23 | AC23: =I23+P23+W23 | AD23: =J23+Q23+X23 | AE23: =K23+R23+Y23 | AF23: =L23+S23+Z23 | AG23: =M23+T23+AA23 | AH23: =G23+N23+U23 | AI23: =AG23-AH23
A24: =EXPENSES!L22 | B24: =EXPENSES!B22 | C24: =EXPENSES!E22 | D24: =EXPENSES!I22 | E24: =C24+D24 | M24: =SUM(H24:L24) | T24: =SUM(O24:S24) | AA24: =SUM(V24:Z24) | AB24: =H24+O24+V24 | AC24: =I24+P24+W24 | AD24: =J24+Q24+X24 | AE24: =K24+R24+Y24 | AF24: =L24+S24+Z24 | AG24: =M24+T24+AA24 | AH24: =G24+N24+U24 | AI24: =AG24-AH24
A25: =EXPENSES!L23 | B25: =EXPENSES!B23 | C25: =EXPENSES!E23 | D25: =EXPENSES!I23 | E25: =C25+D25 | M25: =SUM(H25:L25) | T25: =SUM(O25:S25) | AA25: =SUM(V25:Z25) | AB25: =H25+O25+V25 | AC25: =I25+P25+W25 | AD25: =J25+Q25+X25 | AE25: =K25+R25+Y25 | AF25: =L25+S25+Z25 | AG25: =M25+T25+AA25 | AH25: =G25+N25+U25 | AI25: =AG25-AH25
A26: =EXPENSES!L24 | B26: =EXPENSES!B24 | C26: =EXPENSES!E24 | D26: =EXPENSES!I24 | E26: =C26+D26 | M26: =SUM(H26:L26) | T26: =SUM(O26:S26) | AA26: =SUM(V26:Z26) | AB26: =H26+O26+V26 | AC26: =I26+P26+W26 | AD26: =J26+Q26+X26 | AE26: =K26+R26+Y26 | AF26: =L26+S26+Z26 | AG26: =M26+T26+AA26 | AH26: =G26+N26+U26 | AI26: =AG26-AH26
A27: =EXPENSES!L25 | B27: =EXPENSES!B25 | C27: =EXPENSES!E25 | D27: =EXPENSES!I25 | E27: =C27+D27 | M27: =SUM(H27:L27) | T27: =SUM(O27:S27) | AA27: =SUM(V27:Z27) | AB27: =H27+O27+V27 | AC27: =I27+P27+W27 | AD27: =J27+Q27+X27 | AE27: =K27+R27+Y27 | AF27: =L27+S27+Z27 | AG27: =M27+T27+AA27 | AH27: =G27+N27+U27 | AI27: =AG27-AH27
A28: =EXPENSES!L26 | B28: =EXPENSES!B26 | C28: =EXPENSES!E26 | D28: =EXPENSES!I26 | E28: =C28+D28 | M28: =SUM(H28:L28) | T28: =SUM(O28:S28) | AA28: =SUM(V28:Z28) | AB28: =H28+O28+V28 | AC28: =I28+P28+W28 | AD28: =J28+Q28+X28 | AE28: =K28+R28+Y28 | AF28: =L28+S28+Z28 | AG28: =M28+T28+AA28 | AH28: =G28+N28+U28 | AI28: =AG28-AH28
A29: =EXPENSES!L27 | B29: =EXPENSES!B27 | C29: =EXPENSES!E27 | D29: =EXPENSES!I27 | E29: =C29+D29 | M29: =SUM(H29:L29) | T29: =SUM(O29:S29) | AA29: =SUM(V29:Z29) | AB29: =H29+O29+V29 | AC29: =I29+P29+W29 | AD29: =J29+Q29+X29 | AE29: =K29+R29+Y29 | AF29: =L29+S29+Z29 | AG29: =M29+T29+AA29 | AH29: =G29+N29+U29 | AI29: =AG29-AH29
A30: =EXPENSES!L28 | B30: =EXPENSES!B28 | C30: =EXPENSES!E28 | D30: =EXPENSES!I28 | E30: =C30+D30 | M30: =SUM(H30:L30) | T30: =SUM(O30:S30) | AA30: =SUM(V30:Z30) | AB30: =H30+O30+V30 | AC30: =I30+P30+W30 | AD30: =J30+Q30+X30 | AE30: =K30+R30+Y30 | AF30: =L30+S30+Z30 | AG30: =M30+T30+AA30 | AH30: =G30+N30+U30 | AI30: =AG30-AH30
A31: =EXPENSES!L29 | B31: =EXPENSES!B29 | C31: =EXPENSES!E29 | D31: =EXPENSES!I29 | E31: =C31+D31 | M31: =SUM(H31:L31) | T31: =SUM(O31:S31) | AA31: =SUM(V31:Z31) | AB31: =H31+O31+V31 | AC31: =I31+P31+W31 | AD31: =J31+Q31+X31 | AE31: =K31+R31+Y31 | AF31: =L31+S31+Z31 | AG31: =M31+T31+AA31 | AH31: =G31+N31+U31 | AI31: =AG31-AH31
B32: FOOD | C32: =SUM(C33:C38) | D32: =SUM(D33:D38) | E32: =SUM(E33:E38) | G32: =SUM(G33:G38) | H32: =SUM(H33:H38) | I32: =SUM(I33:I38) | J32: =SUM(J33:J38) | K32: =SUM(K33:K38) | L32: =SUM(L33:L38) | M32: =SUM(M33:M38) | N32: =SUM(N33:N38) | ... AI32: =SUM(AI33:AI38)
A33: =EXPENSES!L31 | B33: =EXPENSES!B31 | C33: =EXPENSES!E31 | D33: =EXPENSES!I31 | E33: =C33+D33 | M33: =SUM(H33:L33) | T33: =SUM(O33:S33) | AA33: =SUM(V33:Z33) | AB33: =H33+O33+V33 | AC33: =I33+P33+W33 | AD33: =J33+Q33+X33 | AE33: =K33+R33+Y33 | AF33: =L33+S33+Z33 | AG33: =M33+T33+AA33 | AH33: =G33+N33+U33 | AI33: =AG33-AH33
A34: =EXPENSES!L32 | B34: =EXPENSES!B32 | C34: =EXPENSES!E32 | D34: =EXPENSES!I32 | E34: =C34+D34 | M34: =SUM(H34:L34) | T34: =SUM(O34:S34) | AA34: =SUM(V34:Z34) | AB34: =H34+O34+V34 | AC34: =I34+P34+W34 | AD34: =J34+Q34+X34 | AE34: =K34+R34+Y34 | AF34: =L34+S34+Z34 | AG34: =M34+T34+AA34 | AH34: =G34+N34+U34 | AI34: =AG34-AH34
A35: =EXPENSES!L33 | B35: =EXPENSES!B33 | C35: =EXPENSES!E33 | D35: =EXPENSES!I33 | E35: =C35+D35 | M35: =SUM(H35:L35) | T35: =SUM(O35:S35) | AA35: =SUM(V35:Z35) | AB35: =H35+O35+V35 | AC35: =I35+P35+W35 | AD35: =J35+Q35+X35 | AE35: =K35+R35+Y35 | AF35: =L35+S35+Z35 | AG35: =M35+T35+AA35 | AH35: =G35+N35+U35 | AI35: =AG35-AH35
A36: =EXPENSES!L34 | B36: =EXPENSES!B34 | C36: =EXPENSES!E34 | D36: =EXPENSES!I34 | E36: =C36+D36 | M36: =SUM(H36:L36) | T36: =SUM(O36:S36) | AA36: =SUM(V36:Z36) | AB36: =H36+O36+V36 | AC36: =I36+P36+W36 | AD36: =J36+Q36+X36 | AE36: =K36+R36+Y36 | AF36: =L36+S36+Z36 | AG36: =M36+T36+AA36 | AH36: =G36+N36+U36 | AI36: =AG36-AH36
A37: =EXPENSES!L35 | B37: =EXPENSES!B35 | C37: =EXPENSES!E35 | D37: =EXPENSES!I35 | E37: =C37+D37 | M37: =SUM(H37:L37) | T37: =SUM(O37:S37) | AA37: =SUM(V37:Z37) | AB37: =H37+O37+V37 | AC37: =I37+P37+W37 | AD37: =J37+Q37+X37 | AE37: =K37+R37+Y37 | AF37: =L37+S37+Z37 | AG37: =M37+T37+AA37 | AH37: =G37+N37+U37 | AI37: =AG37-AH37
A38: =EXPENSES!L36 | B38: =EXPENSES!B36 | C38: =EXPENSES!E36 | D38: =EXPENSES!I36 | E38: =C38+D38 | M38: =SUM(H38:L38) | T38: =SUM(O38:S38) | AA38: =SUM(V38:Z38) | AB38: =H38+O38+V38 | AC38: =I38+P38+W38 | AD38: =J38+Q38+X38 | AE38: =K38+R38+Y38 | AF38: =L38+S38+Z38 | AG38: =M38+T38+AA38 | AH38: =G38+N38+U38 | AI38: =AG38-AH38
B39: HOUSEHOLD & PERSONAL | C39: =SUM(C40:C46) | D39: =SUM(D40:D46) | E39: =SUM(E40:E46) | G39: =SUM(G40:G46) | H39: =SUM(H40:H46) | I39: =SUM(I40:I46) | J39: =SUM(J40:J46) | K39: =SUM(K40:K46) | L39: =SUM(L40:L46) | M39: =SUM(M40:M46) | N39: =SUM(N40:N46) | ... AI39: =SUM(AI40:AI46)
A40: =EXPENSES!L38 | B40: =EXPENSES!B38 | C40: =EXPENSES!E38 | D40: =EXPENSES!I38 | E40: =C40+D40 | M40: =SUM(H40:L40) | T40: =SUM(O40:S40) | AA40: =SUM(V40:Z40) | AB40: =H40+O40+V40 | AC40: =I40+P40+W40 | AD40: =J40+Q40+X40 | AE40: =K40+R40+Y40 | AF40: =L40+S40+Z40 | AG40: =M40+T40+AA40 | AH40: =G40+N40+U40 | AI40: =AG40-AH40
A41: =EXPENSES!L39 | B41: =EXPENSES!B39 | C41: =EXPENSES!E39 | D41: =EXPENSES!I39 | E41: =C41+D41 | M41: =SUM(H41:L41) | T41: =SUM(O41:S41) | AA41: =SUM(V41:Z41) | AB41: =H41+O41+V41 | AC41: =I41+P41+W41 | AD41: =J41+Q41+X41 | AE41: =K41+R41+Y41 | AF41: =L41+S41+Z41 | AG41: =M41+T41+AA41 | AH41: =G41+N41+U41 | AI41: =AG41-AH41
A42: =EXPENSES!L40 | B42: =EXPENSES!B40 | C42: =EXPENSES!E40 | D42: =EXPENSES!I40 | E42: =C42+D42 | M42: =SUM(H42:L42) | T42: =SUM(O42:S42) | AA42: =SUM(V42:Z42) | AB42: =H42+O42+V42 | AC42: =I42+P42+W42 | AD42: =J42+Q42+X42 | AE42: =K42+R42+Y42 | AF42: =L42+S42+Z42 | AG42: =M42+T42+AA42 | AH42: =G42+N42+U42 | AI42: =AG42-AH42
A43: =EXPENSES!L41 | B43: =EXPENSES!B41 | C43: =EXPENSES!E41 | D43: =EXPENSES!I41 | E43: =C43+D43 | M43: =SUM(H43:L43) | T43: =SUM(O43:S43) | AA43: =SUM(V43:Z43) | AB43: =H43+O43+V43 | AC43: =I43+P43+W43 | AD43: =J43+Q43+X43 | AE43: =K43+R43+Y43 | AF43: =L43+S43+Z43 | AG43: =M43+T43+AA43 | AH43: =G43+N43+U43 | AI43: =AG43-AH43
A44: =EXPENSES!L42 | B44: =EXPENSES!B42 | C44: =EXPENSES!E42 | D44: =EXPENSES!I42 | E44: =C44+D44 | M44: =SUM(H44:L44) | T44: =SUM(O44:S44) | AA44: =SUM(V44:Z44) | AB44: =H44+O44+V44 | AC44: =I44+P44+W44 | AD44: =J44+Q44+X44 | AE44: =K44+R44+Y44 | AF44: =L44+S44+Z44 | AG44: =M44+T44+AA44 | AH44: =G44+N44+U44 | AI44: =AG44-AH44
A45: =EXPENSES!L43 | B45: =EXPENSES!B43 | C45: =EXPENSES!E43 | D45: =EXPENSES!I43 | E45: =C45+D45 | M45: =SUM(H45:L45) | T45: =SUM(O45:S45) | AA45: =SUM(V45:Z45) | AB45: =H45+O45+V45 | AC45: =I45+P45+W45 | AD45: =J45+Q45+X45 | AE45: =K45+R45+Y45 | AF45: =L45+S45+Z45 | AG45: =M45+T45+AA45 | AH45: =G45+N45+U45 | AI45: =AG45-AH45
A46: =EXPENSES!L44 | B46: =EXPENSES!B44 | C46: =EXPENSES!E44 | D46: =EXPENSES!I44 | E46: =C46+D46 | M46: =SUM(H46:L46) | T46: =SUM(O46:S46) | AA46: =SUM(V46:Z46) | AB46: =H46+O46+V46 | AC46: =I46+P46+W46 | AD46: =J46+Q46+X46 | AE46: =K46+R46+Y46 | AF46: =L46+S46+Z46 | AG46: =M46+T46+AA46 | AH46: =G46+N46+U46 | AI46: =AG46-AH46
B47: CLOTHING | C47: =SUM(C48:C52) | D47: =SUM(D48:D52) | E47: =SUM(E48:E52) | G47: =SUM(G48:G52) | H47: =SUM(H48:H52) | I47: =SUM(I48:I52) | J47: =SUM(J48:J52) | K47: =SUM(K48:K52) | L47: =SUM(L48:L52) | M47: =SUM(M48:M52) | N47: =SUM(N48:N52) | ... AI47: =SUM(AI48:AI52)
A48: =EXPENSES!L46 | B48: =EXPENSES!B46 | C48: =EXPENSES!E46 | D48: =EXPENSES!I46 | E48: =C48+D48 | M48: =SUM(H48:L48) | T48: =SUM(O48:S48) | AA48: =SUM(V48:Z48) | AB48: =H48+O48+V48 | AC48: =I48+P48+W48 | AD48: =J48+Q48+X48 | AE48: =K48+R48+Y48 | AF48: =L48+S48+Z48 | AG48: =M48+T48+AA48 | AH48: =G48+N48+U48 | AI48: =AG48-AH48
A49: =EXPENSES!L47 | B49: =EXPENSES!B47 | C49: =EXPENSES!E47 | D49: =EXPENSES!I47 | E49: =C49+D49 | M49: =SUM(H49:L49) | T49: =SUM(O49:S49) | AA49: =SUM(V49:Z49) | AB49: =H49+O49+V49 | AC49: =I49+P49+W49 | AD49: =J49+Q49+X49 | AE49: =K49+R49+Y49 | AF49: =L49+S49+Z49 | AG49: =M49+T49+AA49 | AH49: =G49+N49+U49 | AI49: =AG49-AH49
A50: =EXPENSES!L48 | B50: =EXPENSES!B48 | C50: =EXPENSES!E48 | D50: =EXPENSES!I48 | E50: =C50+D50 | M50: =SUM(H50:L50) | T50: =SUM(O50:S50) | AA50: =SUM(V50:Z50) | AB50: =H50+O50+V50 | AC50: =I50+P50+W50 | AD50: =J50+Q50+X50 | AE50: =K50+R50+Y50 | AF50: =L50+S50+Z50 | AG50: =M50+T50+AA50 | AH50: =G50+N50+U50 | AI50: =AG50-AH50
A51: =EXPENSES!L49 | B51: =EXPENSES!B49 | C51: =EXPENSES!E49 | D51: =EXPENSES!I49 | E51: =C51+D51 | M51: =SUM(H51:L51) | T51: =SUM(O51:S51) | AA51: =SUM(V51:Z51) | AB51: =H51+O51+V51 | AC51: =I51+P51+W51 | AD51: =J51+Q51+X51 | AE51: =K51+R51+Y51 | AF51: =L51+S51+Z51 | AG51: =M51+T51+AA51 | AH51: =G51+N51+U51 | AI51: =AG51-AH51
A52: =EXPENSES!L50 | B52: =EXPENSES!B50 | C52: =EXPENSES!E50 | D52: =EXPENSES!I50 | E52: =C52+D52 | M52: =SUM(H52:L52) | T52: =SUM(O52:S52) | AA52: =SUM(V52:Z52) | AB52: =H52+O52+V52 | AC52: =I52+P52+W52 | AD52: =J52+Q52+X52 | AE52: =K52+R52+Y52 | AF52: =L52+S52+Z52 | AG52: =M52+T52+AA52 | AH52: =G52+N52+U52 | AI52: =AG52-AH52
B53: TRANSPORTATION | C53: =SUM(C54:C62) | D53: =SUM(D54:D62) | E53: =SUM(E54:E62) | G53: =SUM(G54:G62) | H53: =SUM(H54:H62) | I53: =SUM(I54:I62) | J53: =SUM(J54:J62) | K53: =SUM(K54:K62) | L53: =SUM(L54:L62) | M53: =SUM(M54:M62) | N53: =SUM(N54:N62) | ... AI53: =SUM(AI54:AI62)
A54: =EXPENSES!L52 | B54: =EXPENSES!B52 | C54: =EXPENSES!E52 | D54: =EXPENSES!I52 | E54: =C54+D54 | M54: =SUM(H54:L54) | T54: =SUM(O54:S54) | AA54: =SUM(V54:Z54) | AB54: =H54+O54+V54 | AC54: =I54+P54+W54 | AD54: =J54+Q54+X54 | AE54: =K54+R54+Y54 | AF54: =L54+S54+Z54 | AG54: =M54+T54+AA54 | AH54: =G54+N54+U54 | AI54: =AG54-AH54
A55: =EXPENSES!L53 | B55: =EXPENSES!B53 | C55: =EXPENSES!E53 | D55: =EXPENSES!I53 | E55: =C55+D55 | M55: =SUM(H55:L55) | T55: =SUM(O55:S55) | AA55: =SUM(V55:Z55) | AB55: =H55+O55+V55 | AC55: =I55+P55+W55 | AD55: =J55+Q55+X55 | AE55: =K55+R55+Y55 | AF55: =L55+S55+Z55 | AG55: =M55+T55+AA55 | AH55: =G55+N55+U55 | AI55: =AG55-AH55
A56: =EXPENSES!L54 | B56: =EXPENSES!B54 | C56: =EXPENSES!E54 | D56: =EXPENSES!I54 | E56: =C56+D56 | M56: =SUM(H56:L56) | T56: =SUM(O56:S56) | AA56: =SUM(V56:Z56) | AB56: =H56+O56+V56 | AC56: =I56+P56+W56 | AD56: =J56+Q56+X56 | AE56: =K56+R56+Y56 | AF56: =L56+S56+Z56 | AG56: =M56+T56+AA56 | AH56: =G56+N56+U56 | AI56: =AG56-AH56
A57: =EXPENSES!L55 | B57: =EXPENSES!B55 | C57: =EXPENSES!E55 | D57: =EXPENSES!I55 | E57: =C57+D57 | M57: =SUM(H57:L57) | T57: =SUM(O57:S57) | AA57: =SUM(V57:Z57) | AB57: =H57+O57+V57 | AC57: =I57+P57+W57 | AD57: =J57+Q57+X57 | AE57: =K57+R57+Y57 | AF57: =L57+S57+Z57 | AG57: =M57+T57+AA57 | AH57: =G57+N57+U57 | AI57: =AG57-AH57
A58: =EXPENSES!L56 | B58: =EXPENSES!B56 | C58: =EXPENSES!E56 | D58: =EXPENSES!I56 | E58: =C58+D58 | M58: =SUM(H58:L58) | T58: =SUM(O58:S58) | AA58: =SUM(V58:Z58) | AB58: =H58+O58+V58 | AC58: =I58+P58+W58 | AD58: =J58+Q58+X58 | AE58: =K58+R58+Y58 | AF58: =L58+S58+Z58 | AG58: =M58+T58+AA58 | AH58: =G58+N58+U58 | AI58: =AG58-AH58
A59: =EXPENSES!L57 | B59: =EXPENSES!B57 | C59: =EXPENSES!E57 | D59: =EXPENSES!I57 | E59: =C59+D59 | M59: =SUM(H59:L59) | T59: =SUM(O59:S59) | AA59: =SUM(V59:Z59) | AB59: =H59+O59+V59 | AC59: =I59+P59+W59 | AD59: =J59+Q59+X59 | AE59: =K59+R59+Y59 | AF59: =L59+S59+Z59 | AG59: =M59+T59+AA59 | AH59: =G59+N59+U59 | AI59: =AG59-AH59
A60: =EXPENSES!L58 | B60: =EXPENSES!B58 | C60: =EXPENSES!E58 | D60: =EXPENSES!I58 | E60: =C60+D60 | M60: =SUM(H60:L60) | T60: =SUM(O60:S60) | AA60: =SUM(V60:Z60) | AB60: =H60+O60+V60 | AC60: =I60+P60+W60 | AD60: =J60+Q60+X60 | AE60: =K60+R60+Y60 | AF60: =L60+S60+Z60 | AG60: =M60+T60+AA60 | AH60: =G60+N60+U60 | AI60: =AG60-AH60
A61: =EXPENSES!L59 | B61: =EXPENSES!B59 | C61: =EXPENSES!E59 | D61: =EXPENSES!I59 | E61: =C61+D61 | M61: =SUM(H61:L61) | T61: =SUM(O61:S61) | AA61: =SUM(V61:Z61) | AB61: =H61+O61+V61 | AC61: =I61+P61+W61 | AD61: =J61+Q61+X61 | AE61: =K61+R61+Y61 | AF61: =L61+S61+Z61 | AG61: =M61+T61+AA61 | AH61: =G61+N61+U61 | AI61: =AG61-AH61
A62: =EXPENSES!L60 | B62: =EXPENSES!B60 | C62: =EXPENSES!E60 | D62: =EXPENSES!I60 | E62: =C62+D62 | M62: =SUM(H62:L62) | T62: =SUM(O62:S62) | AA62: =SUM(V62:Z62) | AB62: =H62+O62+V62 | AC62: =I62+P62+W62 | AD62: =J62+Q62+X62 | AE62: =K62+R62+Y62 | AF62: =L62+S62+Z62 | AG62: =M62+T62+AA62 | AH62: =G62+N62+U62 | AI62: =AG62-AH62
B63: MEDICAL & HEALTH | C63: =SUM(C64:C72) | D63: =SUM(D64:D72) | E63: =SUM(E64:E72) | G63: =SUM(G64:G72) | H63: =SUM(H64:H72) | I63: =SUM(I64:I72) | J63: =SUM(J64:J72) | K63: =SUM(K64:K72) | L63: =SUM(L64:L72) | M63: =SUM(M64:M72) | N63: =SUM(N64:N72) | ... AI63: =SUM(AI64:AI72)
A64: =EXPENSES!L62 | B64: =EXPENSES!B62 | C64: =EXPENSES!E62 | D64: =EXPENSES!I62 | E64: =C64+D64 | M64: =SUM(H64:L64) | T64: =SUM(O64:S64) | AA64: =SUM(V64:Z64) | AB64: =H64+O64+V64 | AC64: =I64+P64+W64 | AD64: =J64+Q64+X64 | AE64: =K64+R64+Y64 | AF64: =L64+S64+Z64 | AG64: =M64+T64+AA64 | AH64: =G64+N64+U64 | AI64: =AG64-AH64
A65: =EXPENSES!L63 | B65: =EXPENSES!B63 | C65: =EXPENSES!E63 | D65: =EXPENSES!I63 | E65: =C65+D65 | M65: =SUM(H65:L65) | T65: =SUM(O65:S65) | AA65: =SUM(V65:Z65) | AB65: =H65+O65+V65 | AC65: =I65+P65+W65 | AD65: =J65+Q65+X65 | AE65: =K65+R65+Y65 | AF65: =L65+S65+Z65 | AG65: =M65+T65+AA65 | AH65: =G65+N65+U65 | AI65: =AG65-AH65
A66: =EXPENSES!L64 | B66: =EXPENSES!B64 | C66: =EXPENSES!E64 | D66: =EXPENSES!I64 | E66: =C66+D66 | M66: =SUM(H66:L66) | T66: =SUM(O66:S66) | AA66: =SUM(V66:Z66) | AB66: =H66+O66+V66 | AC66: =I66+P66+W66 | AD66: =J66+Q66+X66 | AE66: =K66+R66+Y66 | AF66: =L66+S66+Z66 | AG66: =M66+T66+AA66 | AH66: =G66+N66+U66 | AI66: =AG66-AH66
A67: =EXPENSES!L65 | B67: =EXPENSES!B65 | C67: =EXPENSES!E65 | D67: =EXPENSES!I65 | E67: =C67+D67 | M67: =SUM(H67:L67) | T67: =SUM(O67:S67) | AA67: =SUM(V67:Z67) | AB67: =H67+O67+V67 | AC67: =I67+P67+W67 | AD67: =J67+Q67+X67 | AE67: =K67+R67+Y67 | AF67: =L67+S67+Z67 | AG67: =M67+T67+AA67 | AH67: =G67+N67+U67 | AI67: =AG67-AH67
A68: =EXPENSES!L66 | B68: =EXPENSES!B66 | C68: =EXPENSES!E66 | D68: =EXPENSES!I66 | E68: =C68+D68 | M68: =SUM(H68:L68) | T68: =SUM(O68:S68) | AA68: =SUM(V68:Z68) | AB68: =H68+O68+V68 | AC68: =I68+P68+W68 | AD68: =J68+Q68+X68 | AE68: =K68+R68+Y68 | AF68: =L68+S68+Z68 | AG68: =M68+T68+AA68 | AH68: =G68+N68+U68 | AI68: =AG68-AH68
A69: =EXPENSES!L67 | B69: =EXPENSES!B67 | C69: =EXPENSES!E67 | D69: =EXPENSES!I67 | E69: =C69+D69 | M69: =SUM(H69:L69) | T69: =SUM(O69:S69) | AA69: =SUM(V69:Z69) | AB69: =H69+O69+V69 | AC69: =I69+P69+W69 | AD69: =J69+Q69+X69 | AE69: =K69+R69+Y69 | AF69: =L69+S69+Z69 | AG69: =M69+T69+AA69 | AH69: =G69+N69+U69 | AI69: =AG69-AH69
A70: =EXPENSES!L68 | B70: =EXPENSES!B68 | C70: =EXPENSES!E68 | D70: =EXPENSES!I68 | E70: =C70+D70 | M70: =SUM(H70:L70) | T70: =SUM(O70:S70) | AA70: =SUM(V70:Z70) | AB70: =H70+O70+V70 | AC70: =I70+P70+W70 | AD70: =J70+Q70+X70 | AE70: =K70+R70+Y70 | AF70: =L70+S70+Z70 | AG70: =M70+T70+AA70 | AH70: =G70+N70+U70 | AI70: =AG70-AH70
A71: =EXPENSES!L69 | B71: =EXPENSES!B69 | C71: =EXPENSES!E69 | D71: =EXPENSES!I69 | E71: =C71+D71 | M71: =SUM(H71:L71) | T71: =SUM(O71:S71) | AA71: =SUM(V71:Z71) | AB71: =H71+O71+V71 | AC71: =I71+P71+W71 | AD71: =J71+Q71+X71 | AE71: =K71+R71+Y71 | AF71: =L71+S71+Z71 | AG71: =M71+T71+AA71 | AH71: =G71+N71+U71 | AI71: =AG71-AH71
A72: =EXPENSES!L70 | B72: =EXPENSES!B70 | C72: =EXPENSES!E70 | D72: =EXPENSES!I70 | E72: =C72+D72 | M72: =SUM(H72:L72) | T72: =SUM(O72:S72) | AA72: =SUM(V72:Z72) | AB72: =H72+O72+V72 | AC72: =I72+P72+W72 | AD72: =J72+Q72+X72 | AE72: =K72+R72+Y72 | AF72: =L72+S72+Z72 | AG72: =M72+T72+AA72 | AH72: =G72+N72+U72 | AI72: =AG72-AH72
B73: CHILDCARE & DEPENDENTS | C73: =SUM(C74:C80) | D73: =SUM(D74:D80) | E73: =SUM(E74:E80) | G73: =SUM(G74:G80) | H73: =SUM(H74:H80) | I73: =SUM(I74:I80) | J73: =SUM(J74:J80) | K73: =SUM(K74:K80) | L73: =SUM(L74:L80) | M73: =SUM(M74:M80) | N73: =SUM(N74:N80) | ... AI73: =SUM(AI74:AI80)
A74: =EXPENSES!L72 | B74: =EXPENSES!B72 | C74: =EXPENSES!E72 | D74: =EXPENSES!I72 | E74: =C74+D74 | M74: =SUM(H74:L74) | T74: =SUM(O74:S74) | AA74: =SUM(V74:Z74) | AB74: =H74+O74+V74 | AC74: =I74+P74+W74 | AD74: =J74+Q74+X74 | AE74: =K74+R74+Y74 | AF74: =L74+S74+Z74 | AG74: =M74+T74+AA74 | AH74: =G74+N74+U74 | AI74: =AG74-AH74
A75: =EXPENSES!L73 | B75: =EXPENSES!B73 | C75: =EXPENSES!E73 | D75: =EXPENSES!I73 | E75: =C75+D75 | M75: =SUM(H75:L75) | T75: =SUM(O75:S75) | AA75: =SUM(V75:Z75) | AB75: =H75+O75+V75 | AC75: =I75+P75+W75 | AD75: =J75+Q75+X75 | AE75: =K75+R75+Y75 | AF75: =L75+S75+Z75 | AG75: =M75+T75+AA75 | AH75: =G75+N75+U75 | AI75: =AG75-AH75
A76: =EXPENSES!L74 | B76: =EXPENSES!B74 | C76: =EXPENSES!E74 | D76: =EXPENSES!I74 | E76: =C76+D76 | M76: =SUM(H76:L76) | T76: =SUM(O76:S76) | AA76: =SUM(V76:Z76) | AB76: =H76+O76+V76 | AC76: =I76+P76+W76 | AD76: =J76+Q76+X76 | AE76: =K76+R76+Y76 | AF76: =L76+S76+Z76 | AG76: =M76+T76+AA76 | AH76: =G76+N76+U76 | AI76: =AG76-AH76
A77: =EXPENSES!L75 | B77: =EXPENSES!B75 | C77: =EXPENSES!E75 | D77: =EXPENSES!I75 | E77: =C77+D77 | M77: =SUM(H77:L77) | T77: =SUM(O77:S77) | AA77: =SUM(V77:Z77) | AB77: =H77+O77+V77 | AC77: =I77+P77+W77 | AD77: =J77+Q77+X77 | AE77: =K77+R77+Y77 | AF77: =L77+S77+Z77 | AG77: =M77+T77+AA77 | AH77: =G77+N77+U77 | AI77: =AG77-AH77
A78: =EXPENSES!L76 | B78: =EXPENSES!B76 | C78: =EXPENSES!E76 | D78: =EXPENSES!I76 | E78: =C78+D78 | M78: =SUM(H78:L78) | T78: =SUM(O78:S78) | AA78: =SUM(V78:Z78) | AB78: =H78+O78+V78 | AC78: =I78+P78+W78 | AD78: =J78+Q78+X78 | AE78: =K78+R78+Y78 | AF78: =L78+S78+Z78 | AG78: =M78+T78+AA78 | AH78: =G78+N78+U78 | AI78: =AG78-AH78
A79: =EXPENSES!L77 | B79: =EXPENSES!B77 | C79: =EXPENSES!E77 | D79: =EXPENSES!I77 | E79: =C79+D79 | M79: =SUM(H79:L79) | T79: =SUM(O79:S79) | AA79: =SUM(V79:Z79) | AB79: =H79+O79+V79 | AC79: =I79+P79+W79 | AD79: =J79+Q79+X79 | AE79: =K79+R79+Y79 | AF79: =L79+S79+Z79 | AG79: =M79+T79+AA79 | AH79: =G79+N79+U79 | AI79: =AG79-AH79
A80: =EXPENSES!L78 | B80: =EXPENSES!B78 | C80: =EXPENSES!E78 | D80: =EXPENSES!I78 | E80: =C80+D80 | M80: =SUM(H80:L80) | T80: =SUM(O80:S80) | AA80: =SUM(V80:Z80) | AB80: =H80+O80+V80 | AC80: =I80+P80+W80 | AD80: =J80+Q80+X80 | AE80: =K80+R80+Y80 | AF80: =L80+S80+Z80 | AG80: =M80+T80+AA80 | AH80: =G80+N80+U80 | AI80: =AG80-AH80
B81: EDUCATION | C81: =SUM(C82:C87) | D81: =SUM(D82:D87) | E81: =SUM(E82:E87) | G81: =SUM(G82:G87) | H81: =SUM(H82:H87) | I81: =SUM(I82:I87) | J81: =SUM(J82:J87) | K81: =SUM(K82:K87) | L81: =SUM(L82:L87) | M81: =SUM(M82:M87) | N81: =SUM(N82:N87) | ... AI81: =SUM(AI82:AI87)
A82: =EXPENSES!L80 | B82: =EXPENSES!B80 | C82: =EXPENSES!E80 | D82: =EXPENSES!I80 | E82: =C82+D82 | M82: =SUM(H82:L82) | T82: =SUM(O82:S82) | AA82: =SUM(V82:Z82) | AB82: =H82+O82+V82 | AC82: =I82+P82+W82 | AD82: =J82+Q82+X82 | AE82: =K82+R82+Y82 | AF82: =L82+S82+Z82 | AG82: =M82+T82+AA82 | AH82: =G82+N82+U82 | AI82: =AG82-AH82
A83: =EXPENSES!L81 | B83: =EXPENSES!B81 | C83: =EXPENSES!E81 | D83: =EXPENSES!I81 | E83: =C83+D83 | M83: =SUM(H83:L83) | T83: =SUM(O83:S83) | AA83: =SUM(V83:Z83) | AB83: =H83+O83+V83 | AC83: =I83+P83+W83 | AD83: =J83+Q83+X83 | AE83: =K83+R83+Y83 | AF83: =L83+S83+Z83 | AG83: =M83+T83+AA83 | AH83: =G83+N83+U83 | AI83: =AG83-AH83
A84: =EXPENSES!L82 | B84: =EXPENSES!B82 | C84: =EXPENSES!E82 | D84: =EXPENSES!I82 | E84: =C84+D84 | M84: =SUM(H84:L84) | T84: =SUM(O84:S84) | AA84: =SUM(V84:Z84) | AB84: =H84+O84+V84 | AC84: =I84+P84+W84 | AD84: =J84+Q84+X84 | AE84: =K84+R84+Y84 | AF84: =L84+S84+Z84 | AG84: =M84+T84+AA84 | AH84: =G84+N84+U84 | AI84: =AG84-AH84
A85: =EXPENSES!L83 | B85: =EXPENSES!B83 | C85: =EXPENSES!E83 | D85: =EXPENSES!I83 | E85: =C85+D85 | M85: =SUM(H85:L85) | T85: =SUM(O85:S85) | AA85: =SUM(V85:Z85) | AB85: =H85+O85+V85 | AC85: =I85+P85+W85 | AD85: =J85+Q85+X85 | AE85: =K85+R85+Y85 | AF85: =L85+S85+Z85 | AG85: =M85+T85+AA85 | AH85: =G85+N85+U85 | AI85: =AG85-AH85
A86: =EXPENSES!L84 | B86: =EXPENSES!B84 | C86: =EXPENSES!E84 | D86: =EXPENSES!I84 | E86: =C86+D86 | M86: =SUM(H86:L86) | T86: =SUM(O86:S86) | AA86: =SUM(V86:Z86) | AB86: =H86+O86+V86 | AC86: =I86+P86+W86 | AD86: =J86+Q86+X86 | AE86: =K86+R86+Y86 | AF86: =L86+S86+Z86 | AG86: =M86+T86+AA86 | AH86: =G86+N86+U86 | AI86: =AG86-AH86
A87: =EXPENSES!L85 | B87: =EXPENSES!B85 | C87: =EXPENSES!E85 | D87: =EXPENSES!I85 | E87: =C87+D87 | M87: =SUM(H87:L87) | T87: =SUM(O87:S87) | AA87: =SUM(V87:Z87) | AB87: =H87+O87+V87 | AC87: =I87+P87+W87 | AD87: =J87+Q87+X87 | AE87: =K87+R87+Y87 | AF87: =L87+S87+Z87 | AG87: =M87+T87+AA87 | AH87: =G87+N87+U87 | AI87: =AG87-AH87
B88: DEBT PAYMENTS | C88: =SUM(C89:C89) | D88: =SUM(D89:D89) | E88: =SUM(E89:E89) | G88: =SUM(G89:G89) | H88: =SUM(H89:H89) | I88: =SUM(I89:I89) | J88: =SUM(J89:J89) | K88: =SUM(K89:K89) | L88: =SUM(L89:L89) | M88: =SUM(M89:M89) | N88: =SUM(N89:N89) | ... AI88: =SUM(AI89:AI89)
A89: =EXPENSES!L87 | B89: =EXPENSES!B87 | C89: =EXPENSES!E87 | D89: =EXPENSES!I87 | E89: =C89+D89 | M89: =SUM(H89:L89) | T89: =SUM(O89:S89) | AA89: =SUM(V89:Z89) | AB89: =H89+O89+V89 | AC89: =I89+P89+W89 | AD89: =J89+Q89+X89 | AE89: =K89+R89+Y89 | AF89: =L89+S89+Z89 | AG89: =M89+T89+AA89 | AH89: =G89+N89+U89 | AI89: =AG89-AH89
B90: LEGAL & GOVERNMENT | C90: =SUM(C91:C95) | D90: =SUM(D91:D95) | E90: =SUM(E91:E95) | G90: =SUM(G91:G95) | H90: =SUM(H91:H95) | I90: =SUM(I91:I95) | J90: =SUM(J91:J95) | K90: =SUM(K91:K95) | L90: =SUM(L91:L95) | M90: =SUM(M91:M95) | N90: =SUM(N91:N95) | ... AI90: =SUM(AI91:AI95)
A91: =EXPENSES!L89 | B91: =EXPENSES!B89 | C91: =EXPENSES!E89 | D91: =EXPENSES!I89 | E91: =C91+D91 | M91: =SUM(H91:L91) | T91: =SUM(O91:S91) | AA91: =SUM(V91:Z91) | AB91: =H91+O91+V91 | AC91: =I91+P91+W91 | AD91: =J91+Q91+X91 | AE91: =K91+R91+Y91 | AF91: =L91+S91+Z91 | AG91: =M91+T91+AA91 | AH91: =G91+N91+U91 | AI91: =AG91-AH91
A92: =EXPENSES!L90 | B92: =EXPENSES!B90 | C92: =EXPENSES!E90 | D92: =EXPENSES!I90 | E92: =C92+D92 | M92: =SUM(H92:L92) | T92: =SUM(O92:S92) | AA92: =SUM(V92:Z92) | AB92: =H92+O92+V92 | AC92: =I92+P92+W92 | AD92: =J92+Q92+X92 | AE92: =K92+R92+Y92 | AF92: =L92+S92+Z92 | AG92: =M92+T92+AA92 | AH92: =G92+N92+U92 | AI92: =AG92-AH92
A93: =EXPENSES!L91 | B93: =EXPENSES!B91 | C93: =EXPENSES!E91 | D93: =EXPENSES!I91 | E93: =C93+D93 | M93: =SUM(H93:L93) | T93: =SUM(O93:S93) | AA93: =SUM(V93:Z93) | AB93: =H93+O93+V93 | AC93: =I93+P93+W93 | AD93: =J93+Q93+X93 | AE93: =K93+R93+Y93 | AF93: =L93+S93+Z93 | AG93: =M93+T93+AA93 | AH93: =G93+N93+U93 | AI93: =AG93-AH93
A94: =EXPENSES!L92 | B94: =EXPENSES!B92 | C94: =EXPENSES!E92 | D94: =EXPENSES!I92 | E94: =C94+D94 | M94: =SUM(H94:L94) | T94: =SUM(O94:S94) | AA94: =SUM(V94:Z94) | AB94: =H94+O94+V94 | AC94: =I94+P94+W94 | AD94: =J94+Q94+X94 | AE94: =K94+R94+Y94 | AF94: =L94+S94+Z94 | AG94: =M94+T94+AA94 | AH94: =G94+N94+U94 | AI94: =AG94-AH94
A95: =EXPENSES!L93 | B95: =EXPENSES!B93 | C95: =EXPENSES!E93 | D95: =EXPENSES!I93 | E95: =C95+D95 | M95: =SUM(H95:L95) | T95: =SUM(O95:S95) | AA95: =SUM(V95:Z95) | AB95: =H95+O95+V95 | AC95: =I95+P95+W95 | AD95: =J95+Q95+X95 | AE95: =K95+R95+Y95 | AF95: =L95+S95+Z95 | AG95: =M95+T95+AA95 | AH95: =G95+N95+U95 | AI95: =AG95-AH95
B96: PETS | C96: =SUM(C97:C100) | D96: =SUM(D97:D100) | E96: =SUM(E97:E100) | G96: =SUM(G97:G100) | H96: =SUM(H97:H100) | I96: =SUM(I97:I100) | J96: =SUM(J97:J100) | K96: =SUM(K97:K100) | L96: =SUM(L97:L100) | M96: =SUM(M97:M100) | N96: =SUM(N97:N100) | ... AI96: =SUM(AI97:AI100)
A97: =EXPENSES!L95 | B97: =EXPENSES!B95 | C97: =EXPENSES!E95 | D97: =EXPENSES!I95 | E97: =C97+D97 | M97: =SUM(H97:L97) | T97: =SUM(O97:S97) | AA97: =SUM(V97:Z97) | AB97: =H97+O97+V97 | AC97: =I97+P97+W97 | AD97: =J97+Q97+X97 | AE97: =K97+R97+Y97 | AF97: =L97+S97+Z97 | AG97: =M97+T97+AA97 | AH97: =G97+N97+U97 | AI97: =AG97-AH97
A98: =EXPENSES!L96 | B98: =EXPENSES!B96 | C98: =EXPENSES!E96 | D98: =EXPENSES!I96 | E98: =C98+D98 | M98: =SUM(H98:L98) | T98: =SUM(O98:S98) | AA98: =SUM(V98:Z98) | AB98: =H98+O98+V98 | AC98: =I98+P98+W98 | AD98: =J98+Q98+X98 | AE98: =K98+R98+Y98 | AF98: =L98+S98+Z98 | AG98: =M98+T98+AA98 | AH98: =G98+N98+U98 | AI98: =AG98-AH98
A99: =EXPENSES!L97 | B99: =EXPENSES!B97 | C99: =EXPENSES!E97 | D99: =EXPENSES!I97 | E99: =C99+D99 | M99: =SUM(H99:L99) | T99: =SUM(O99:S99) | AA99: =SUM(V99:Z99) | AB99: =H99+O99+V99 | AC99: =I99+P99+W99 | AD99: =J99+Q99+X99 | AE99: =K99+R99+Y99 | AF99: =L99+S99+Z99 | AG99: =M99+T99+AA99 | AH99: =G99+N99+U99 | AI99: =AG99-AH99
A100: =EXPENSES!L98 | B100: =EXPENSES!B98 | C100: =EXPENSES!E98 | D100: =EXPENSES!I98 | E100: =C100+D100 | M100: =SUM(H100:L100) | T100: =SUM(O100:S100) | AA100: =SUM(V100:Z100) | AB100: =H100+O100+V100 | AC100: =I100+P100+W100 | AD100: =J100+Q100+X100 | AE100: =K100+R100+Y100 | AF100: =L100+S100+Z100 | AG100: =M100+T100+AA100 | AH100: =G100+N100+U100 | AI100: =AG100-AH100
B101: SUBSCRIPTIONS & MEMBERSHIPS | C101: =SUM(C102:C107) | D101: =SUM(D102:D107) | E101: =SUM(E102:E107) | G101: =SUM(G102:G107) | H101: =SUM(H102:H107) | I101: =SUM(I102:I107) | J101: =SUM(J102:J107) | K101: =SUM(K102:K107) | L101: =SUM(L102:L107) | M101: =SUM(M102:M107) | N101: =SUM(N102:N107) | ... AI101: =SUM(AI102:AI107)
...

Sheet EXPENDITURE LOG
A1: Expenditure Log
A2: Record every purchase or payment, one per row (yellow cells). Pick the Expense Line from the dropdown — it matches the Expenses tab — and Code and Category fill in automatically. Example: 11/04/2026 | Weekly groceries | Walmart | $142.67 | FOD-01 - Groceries | Member | Debit card. A row with an amount but no Expense Line turns orange.
A4: Date | B4: Description | C4: Payee / Vendor | D4: Amount | E4: Expense Line | F4: Paid By | G4: Payment Method | H4: Receipt? | I4: Notes | J4: Code | K4: Category | M4: Total recorded: | N4: =SUM(D5:D504)
J5: =IF(E5="","",LEFT(E5,6)) | K5: =IF(J5="","",IFERROR(INDEX(EXPENSES!$A$5:$A$126,MATCH(J5,EXPENSES!$L$5:$L$126,0)),"")) | M5: Entries: | N5: =COUNT(D5:D504)
J6: =IF(E6="","",LEFT(E6,6)) | K6: =IF(J6="","",IFERROR(INDEX(EXPENSES!$A$5:$A$126,MATCH(J6,EXPENSES!$L$5:$L$126,0)),"")) | M6: Uncoded entries: | N6: =COUNTIFS(D5:D504,"<>",E5:E504,"")
J7: =IF(E7="","",LEFT(E7,6)) | K7: =IF(J7="","",IFERROR(INDEX(EXPENSES!$A$5:$A$126,MATCH(J7,EXPENSES!$L$5:$L$126,0)),""))
J8: =IF(E8="","",LEFT(E8,6)) | K8: =IF(J8="","",IFERROR(INDEX(EXPENSES!$A$5:$A$126,MATCH(J8,EXPENSES!$L$5:$L$126,0)),""))
J9: =IF(E9="","",LEFT(E9,6)) | K9: =IF(J9="","",IFERROR(INDEX(EXPENSES!$A$5:$A$126,MATCH(J9,EXPENSES!$L$5:$L$126,0)),""))
J10: =IF(E10="","",LEFT(E10,6)) | K10: =IF(J10="","",IFERROR(INDEX(EXPENSES!$A$5:$A$126,MATCH(J10,EXPENSES!$L$5:$L$126,0)),""))
J11: =IF(E11="","",LEFT(E11,6)) | K11: =IF(J11="","",IFERROR(INDEX(EXPENSES!$A$5:$A$126,MATCH(J11,EXPENSES!$L$5:$L$126,0)),""))
J12: =IF(E12="","",LEFT(E12,6)) | K12: =IF(J12="","",IFERROR(INDEX(EXPENSES!$A$5:$A$126,MATCH(J12,EXPENSES!$L$5:$L$126,0)),""))
J13: =IF(E13="","",LEFT(E13,6)) | K13: =IF(J13="","",IFERROR(INDEX(EXPENSES!$A$5:$A$126,MATCH(J13,EXPENSES!$L$5:$L$126,0)),""))
J14: =IF(E14="","",LEFT(E14,6)) | K14: =IF(J14="","",IFERROR(INDEX(EXPENSES!$A$5:$A$126,MATCH(J14,EXPENSES!$L$5:$L$126,0)),""))
J15: =IF(E15="","",LEFT(E15,6)) | K15: =IF(J15="","",IFERROR(INDEX(EXPENSES!$A$5:$A$126,MATCH(J15,EXPENSES!$L$5:$L$126,0)),""))
J16: =IF(E16="","",LEFT(E16,6)) | K16: =IF(J16="","",IFERROR(INDEX(EXPENSES!$A$5:$A$126,MATCH(J16,EXPENSES!$L$5:$L$126,0)),""))
J17: =IF(E17="","",LEFT(E17,6)) | K17: =IF(J17="","",IFERROR(INDEX(EXPENSES!$A$5:$A$126,MATCH(J17,EXPENSES!$L$5:$L$126,0)),""))
J18: =IF(E18="","",LEFT(E18,6)) | K18: =IF(J18="","",IFERROR(INDEX(EXPENSES!$A$5:$A$126,MATCH(J18,EXPENSES!$L$5:$L$126,0)),""))
... J504: =IF(E504="","",LEFT(E504,6)) | K504: =IF(J504="","",IFERROR(INDEX(EXPENSES!$A$5:$A$126,MATCH(J504,EXPENSES!$L$5:$L$126,0)),""))
C505: TOTAL | D505: =SUM(D5:D504)

Sheet EXPENDITURE SUMMARY
A1: Expenditure Summary
A2: Totals from the Expenditure Log for each expense line. Pick a month in C4 to see that month's spending against the budget and the support plan, and cumulative spending from the plan start month through the selected month. Nothing else to enter on this tab.
A4: Select month: | E4: Month # of plan: | F4: =(YEAR($C$4)-YEAR('SUPPORT PLAN'!$C$4))*12+MONTH($C$4)-MONTH('SUPPORT PLAN'!$C$4)+1 | G4: Plan start: | H4: ='SUPPORT PLAN'!$C$4
A6: Code | B6: Expense | C6: Monthly Budget | D6: Planned Support — All Sources (Selected Month) | E6: Spent in Selected Month | F6: Church-Paid in Selected Month | G6: Over / (Under) Budget — Month | H6: Cumulative Spent (Plan Start → Selected Month) | I6: Cumulative Budget (Plan Start → Selected Month) | J6: Cumulative Over / (Under) | K6: Total Recorded (All Dates)
B7: TITHES & OFFERINGS | C7: =SUM(C8:C12) | D7: =SUM(D8:D12) | E7: =SUM(E8:E12) | F7: =SUM(F8:F12) | G7: =SUM(G8:G12) | H7: =SUM(H8:H12) | I7: =SUM(I8:I12) | J7: =SUM(J8:J12) | K7: =SUM(K8:K12)
A8: =EXPENSES!L6 | B8: =EXPENSES!B6 | C8: =EXPENSES!E6 | D8: =IF(AND($F$4>=1,$F$4<=3),CHOOSE($F$4,'SUPPORT PLAN'!$M8,'SUPPORT PLAN'!$T8,'SUPPORT PLAN'!$AA8),0) | E8: =SUMIFS('EXPENDITURE LOG'!$D$5:$D$504,'EXPENDITURE LOG'!$J$5:$J$504,$A8,'EXPENDITURE LOG'!$A$5:$A$504,">="&$C$4,'EXPENDITURE LOG'!$A$5:$A$504,"<"&EDATE($C$4,1)) | F8: =SUMIFS('EXPENDITURE LOG'!$D$5:$D$504,'EXPENDITURE LOG'!$J$5:$J$504,$A8,'EXPENDITURE LOG'!$A$5:$A$504,">="&$C$4,'EXPENDITURE LOG'!$A$5:$A$504,"<"&EDATE($C$4,1),'EXPENDITURE LOG'!$F$5:$F$504,"Church*") | G8: =E8-C8 | H8: =SUMIFS('EXPENDITURE LOG'!$D$5:$D$504,'EXPENDITURE LOG'!$J$5:$J$504,$A8,'EXPENDITURE LOG'!$A$5:$A$504,">="&'SUPPORT PLAN'!$C$4,'EXPENDITURE LOG'!$A$5:$A$504,"<"&EDATE($C$4,1)) | I8: =C8*MAX(0,$F$4) | J8: =H8-I8 | K8: =SUMIFS('EXPENDITURE LOG'!$D$5:$D$504,'EXPENDITURE LOG'!$J$5:$J$504,$A8)
A9: =EXPENSES!L7 | B9: =EXPENSES!B7 | C9: =EXPENSES!E7 | D9: =IF(AND($F$4>=1,$F$4<=3),CHOOSE($F$4,'SUPPORT PLAN'!$M9,'SUPPORT PLAN'!$T9,'SUPPORT PLAN'!$AA9),0) | E9: =SUMIFS('EXPENDITURE LOG'!$D$5:$D$504,'EXPENDITURE LOG'!$J$5:$J$504,$A9,'EXPENDITURE LOG'!$A$5:$A$504,">="&$C$4,'EXPENDITURE LOG'!$A$5:$A$504,"<"&EDATE($C$4,1)) | F9: =SUMIFS('EXPENDITURE LOG'!$D$5:$D$504,'EXPENDITURE LOG'!$J$5:$J$504,$A9,'EXPENDITURE LOG'!$A$5:$A$504,">="&$C$4,'EXPENDITURE LOG'!$A$5:$A$504,"<"&EDATE($C$4,1),'EXPENDITURE LOG'!$F$5:$F$504,"Church*") | G9: =E9-C9 | H9: =SUMIFS('EXPENDITURE LOG'!$D$5:$D$504,'EXPENDITURE LOG'!$J$5:$J$504,$A9,'EXPENDITURE LOG'!$A$5:$A$504,">="&'SUPPORT PLAN'!$C$4,'EXPENDITURE LOG'!$A$5:$A$504,"<"&EDATE($C$4,1)) | I9: =C9*MAX(0,$F$4) | J9: =H9-I9 | K9: =SUMIFS('EXPENDITURE LOG'!$D$5:$D$504,'EXPENDITURE LOG'!$J$5:$J$504,$A9)
A10: =EXPENSES!L8 | B10: =EXPENSES!B8 | C10: =EXPENSES!E8 | D10: =IF(AND($F$4>=1,$F$4<=3),CHOOSE($F$4,'SUPPORT PLAN'!$M10,'SUPPORT PLAN'!$T10,'SUPPORT PLAN'!$AA10),0) | E10: =SUMIFS('EXPENDITURE LOG'!$D$5:$D$504,'EXPENDITURE LOG'!$J$5:$J$504,$A10,'EXPENDITURE LOG'!$A$5:$A$504,">="&$C$4,'EXPENDITURE LOG'!$A$5:$A$504,"<"&EDATE($C$4,1)) | F10: =SUMIFS('EXPENDITURE LOG'!$D$5:$D$504,'EXPENDITURE LOG'!$J$5:$J$504,$A10,'EXPENDITURE LOG'!$A$5:$A$504,">="&$C$4,'EXPENDITURE LOG'!$A$5:$A$504,"<"&EDATE($C$4,1),'EXPENDITURE LOG'!$F$5:$F$504,"Church*") | G10: =E10-C10 | H10: =SUMIFS('EXPENDITURE LOG'!$D$5:$D$504,'EXPENDITURE LOG'!$J$5:$J$504,$A10,'EXPENDITURE LOG'!$A$5:$A$504,">="&'SUPPORT PLAN'!$C$4,'EXPENDITURE LOG'!$A$5:$A$504,"<"&EDATE($C$4,1)) | I10: =C10*MAX(0,$F$4) | J10: =H10-I10 | K10: =SUMIFS('EXPENDITURE LOG'!$D$5:$D$504,'EXPENDITURE LOG'!$J$5:$J$504,$A10)
A11: =EXPENSES!L9 | B11: =EXPENSES!B9 | C11: =EXPENSES!E9 | D11: =IF(AND($F$4>=1,$F$4<=3),CHOOSE($F$4,'SUPPORT PLAN'!$M11,'SUPPORT PLAN'!$T11,'SUPPORT PLAN'!$AA11),0) | E11: =SUMIFS('EXPENDITURE LOG'!$D$5:$D$504,'EXPENDITURE LOG'!$J$5:$J$504,$A11,'EXPENDITURE LOG'!$A$5:$A$504,">="&$C$4,'EXPENDITURE LOG'!$A$5:$A$504,"<"&EDATE($C$4,1)) | F11: =SUMIFS('EXPENDITURE LOG'!$D$5:$D$504,'EXPENDITURE LOG'!$J$5:$J$504,$A11,'EXPENDITURE LOG'!$A$5:$A$504,">="&$C$4,'EXPENDITURE LOG'!$A$5:$A$504,"<"&EDATE($C$4,1),'EXPENDITURE LOG'!$F$5:$F$504,"Church*") | G11: =E11-C11 | H11: =SUMIFS('EXPENDITURE LOG'!$D$5:$D$504,'EXPENDITURE LOG'!$J$5:$J$504,$A11,'EXPENDITURE LOG'!$A$5:$A$504,">="&'SUPPORT PLAN'!$C$4,'EXPENDITURE LOG'!$A$5:$A$504,"<"&EDATE($C$4,1)) | I11: =C11*MAX(0,$F$4) | J11: =H11-I11 | K11: =SUMIFS('EXPENDITURE LOG'!$D$5:$D$504,'EXPENDITURE LOG'!$J$5:$J$504,$A11)
A12: =EXPENSES!L10 | B12: =EXPENSES!B10 | C12: =EXPENSES!E10 | D12: =IF(AND($F$4>=1,$F$4<=3),CHOOSE($F$4,'SUPPORT PLAN'!$M12,'SUPPORT PLAN'!$T12,'SUPPORT PLAN'!$AA12),0) | E12: =SUMIFS('EXPENDITURE LOG'!$D$5:$D$504,'EXPENDITURE LOG'!$J$5:$J$504,$A12,'EXPENDITURE LOG'!$A$5:$A$504,">="&$C$4,'EXPENDITURE LOG'!$A$5:$A$504,"<"&EDATE($C$4,1)) | F12: =SUMIFS('EXPENDITURE LOG'!$D$5:$D$504,'EXPENDITURE LOG'!$J$5:$J$504,$A12,'EXPENDITURE LOG'!$A$5:$A$504,">="&$C$4,'EXPENDITURE LOG'!$A$5:$A$504,"<"&EDATE($C$4,1),'EXPENDITURE LOG'!$F$5:$F$504,"Church*") | G12: =E12-C12 | H12: =SUMIFS('EXPENDITURE LOG'!$D$5:$D$504,'EXPENDITURE LOG'!$J$5:$J$504,$A12,'EXPENDITURE LOG'!$A$5:$A$504,">="&'SUPPORT PLAN'!$C$4,'EXPENDITURE LOG'!$A$5:$A$504,"<"&EDATE($C$4,1)) | I12: =C12*MAX(0,$F$4) | J12: =H12-I12 | K12: =SUMIFS('EXPENDITURE LOG'!$D$5:$D$504,'EXPENDITURE LOG'!$J$5:$J$504,$A12)
B13: HOUSING | C13: =SUM(C14:C21) | D13: =SUM(D14:D21) | E13: =SUM(E14:E21) | F13: =SUM(F14:F21) | G13: =SUM(G14:G21) | H13: =SUM(H14:H21) | I13: =SUM(I14:I21) | J13: =SUM(J14:J21) | K13: =SUM(K14:K21)
A14: =EXPENSES!L12 | B14: =EXPENSES!B12 | C14: =EXPENSES!E12 | D14: =IF(AND($F$4>=1,$F$4<=3),CHOOSE($F$4,'SUPPORT PLAN'!$M14,'SUPPORT PLAN'!$T14,'SUPPORT PLAN'!$AA14),0) | E14: =SUMIFS('EXPENDITURE LOG'!$D$5:$D$504,'EXPENDITURE LOG'!$J$5:$J$504,$A14,'EXPENDITURE LOG'!$A$5:$A$504,">="&$C$4,'EXPENDITURE LOG'!$A$5:$A$504,"<"&EDATE($C$4,1)) | F14: =SUMIFS('EXPENDITURE LOG'!$D$5:$D$504,'EXPENDITURE LOG'!$J$5:$J$504,$A14,'EXPENDITURE LOG'!$A$5:$A$504,">="&$C$4,'EXPENDITURE LOG'!$A$5:$A$504,"<"&EDATE($C$4,1),'EXPENDITURE LOG'!$F$5:$F$504,"Church*") | G14: =E14-C14 | H14: =SUMIFS('EXPENDITURE LOG'!$D$5:$D$504,'EXPENDITURE LOG'!$J$5:$J$504,$A14,'EXPENDITURE LOG'!$A$5:$A$504,">="&'SUPPORT PLAN'!$C$4,'EXPENDITURE LOG'!$A$5:$A$504,"<"&EDATE($C$4,1)) | I14: =C14*MAX(0,$F$4) | J14: =H14-I14 | K14: =SUMIFS('EXPENDITURE LOG'!$D$5:$D$504,'EXPENDITURE LOG'!$J$5:$J$504,$A14)
A15: =EXPENSES!L13 | B15: =EXPENSES!B13 | C15: =EXPENSES!E13 | D15: =IF(AND($F$4>=1,$F$4<=3),CHOOSE($F$4,'SUPPORT PLAN'!$M15,'SUPPORT PLAN'!$T15,'SUPPORT PLAN'!$AA15),0) | E15: =SUMIFS('EXPENDITURE LOG'!$D$5:$D$504,'EXPENDITURE LOG'!$J$5:$J$504,$A15,'EXPENDITURE LOG'!$A$5:$A$504,">="&$C$4,'EXPENDITURE LOG'!$A$5:$A$504,"<"&EDATE($C$4,1)) | F15: =SUMIFS('EXPENDITURE LOG'!$D$5:$D$504,'EXPENDITURE LOG'!$J$5:$J$504,$A15,'EXPENDITURE LOG'!$A$5:$A$504,">="&$C$4,'EXPENDITURE LOG'!$A$5:$A$504,"<"&EDATE($C$4,1),'EXPENDITURE LOG'!$F$5:$F$504,"Church*") | G15: =E15-C15 | H15: =SUMIFS('EXPENDITURE LOG'!$D$5:$D$504,'EXPENDITURE LOG'!$J$5:$J$504,$A15,'EXPENDITURE LOG'!$A$5:$A$504,">="&'SUPPORT PLAN'!$C$4,'EXPENDITURE LOG'!$A$5:$A$504,"<"&EDATE($C$4,1)) | I15: =C15*MAX(0,$F$4) | J15: =H15-I15 | K15: =SUMIFS('EXPENDITURE LOG'!$D$5:$D$504,'EXPENDITURE LOG'!$J$5:$J$504,$A15)
A16: =EXPENSES!L14 | B16: =EXPENSES!B14 | C16: =EXPENSES!E14 | D16: =IF(AND($F$4>=1,$F$4<=3),CHOOSE($F$4,'SUPPORT PLAN'!$M16,'SUPPORT PLAN'!$T16,'SUPPORT PLAN'!$AA16),0) | E16: =SUMIFS('EXPENDITURE LOG'!$D$5:$D$504,'EXPENDITURE LOG'!$J$5:$J$504,$A16,'EXPENDITURE LOG'!$A$5:$A$504,">="&$C$4,'EXPENDITURE LOG'!$A$5:$A$504,"<"&EDATE($C$4,1)) | F16: =SUMIFS('EXPENDITURE LOG'!$D$5:$D$504,'EXPENDITURE LOG'!$J$5:$J$504,$A16,'EXPENDITURE LOG'!$A$5:$A$504,">="&$C$4,'EXPENDITURE LOG'!$A$5:$A$504,"<"&EDATE($C$4,1),'EXPENDITURE LOG'!$F$5:$F$504,"Church*") | G16: =E16-C16 | H16: =SUMIFS('EXPENDITURE LOG'!$D$5:$D$504,'EXPENDITURE LOG'!$J$5:$J$504,$A16,'EXPENDITURE LOG'!$A$5:$A$504,">="&'SUPPORT PLAN'!$C$4,'EXPENDITURE LOG'!$A$5:$A$504,"<"&EDATE($C$4,1)) | I16: =C16*MAX(0,$F$4) | J16: =H16-I16 | K16: =SUMIFS('EXPENDITURE LOG'!$D$5:$D$504,'EXPENDITURE LOG'!$J$5:$J$504,$A16)
A17: =EXPENSES!L15 | B17: =EXPENSES!B15 | C17: =EXPENSES!E15 | D17: =IF(AND($F$4>=1,$F$4<=3),CHOOSE($F$4,'SUPPORT PLAN'!$M17,'SUPPORT PLAN'!$T17,'SUPPORT PLAN'!$AA17),0) | E17: =SUMIFS('EXPENDITURE LOG'!$D$5:$D$504,'EXPENDITURE LOG'!$J$5:$J$504,$A17,'EXPENDITURE LOG'!$A$5:$A$504,">="&$C$4,'EXPENDITURE LOG'!$A$5:$A$504,"<"&EDATE($C$4,1)) | F17: =SUMIFS('EXPENDITURE LOG'!$D$5:$D$504,'EXPENDITURE LOG'!$J$5:$J$504,$A17,'EXPENDITURE LOG'!$A$5:$A$504,">="&$C$4,'EXPENDITURE LOG'!$A$5:$A$504,"<"&EDATE($C$4,1),'EXPENDITURE LOG'!$F$5:$F$504,"Church*") | G17: =E17-C17 | H17: =SUMIFS('EXPENDITURE LOG'!$D$5:$D$504,'EXPENDITURE LOG'!$J$5:$J$504,$A17,'EXPENDITURE LOG'!$A$5:$A$504,">="&'SUPPORT PLAN'!$C$4,'EXPENDITURE LOG'!$A$5:$A$504,"<"&EDATE($C$4,1)) | I17: =C17*MAX(0,$F$4) | J17: =H17-I17 | K17: =SUMIFS('EXPENDITURE LOG'!$D$5:$D$504,'EXPENDITURE LOG'!$J$5:$J$504,$A17)
A18: =EXPENSES!L16 | B18: =EXPENSES!B16 | C18: =EXPENSES!E16 | D18: =IF(AND($F$4>=1,$F$4<=3),CHOOSE($F$4,'SUPPORT PLAN'!$M18,'SUPPORT PLAN'!$T18,'SUPPORT PLAN'!$AA18),0) | E18: =SUMIFS('EXPENDITURE LOG'!$D$5:$D$504,'EXPENDITURE LOG'!$J$5:$J$504,$A18,'EXPENDITURE LOG'!$A$5:$A$504,">="&$C$4,'EXPENDITURE LOG'!$A$5:$A$504,"<"&EDATE($C$4,1)) | F18: =SUMIFS('EXPENDITURE LOG'!$D$5:$D$504,'EXPENDITURE LOG'!$J$5:$J$504,$A18,'EXPENDITURE LOG'!$A$5:$A$504,">="&$C$4,'EXPENDITURE LOG'!$A$5:$A$504,"<"&EDATE($C$4,1),'EXPENDITURE LOG'!$F$5:$F$504,"Church*") | G18: =E18-C18 | H18: =SUMIFS('EXPENDITURE LOG'!$D$5:$D$504,'EXPENDITURE LOG'!$J$5:$J$504,$A18,'EXPENDITURE LOG'!$A$5:$A$504,">="&'SUPPORT PLAN'!$C$4,'EXPENDITURE LOG'!$A$5:$A$504,"<"&EDATE($C$4,1)) | I18: =C18*MAX(0,$F$4) | J18: =H18-I18 | K18: =SUMIFS('EXPENDITURE LOG'!$D$5:$D$504,'EXPENDITURE LOG'!$J$5:$J$504,$A18)
A19: =EXPENSES!L17 | B19: =EXPENSES!B17 | C19: =EXPENSES!E17 | D19: =IF(AND($F$4>=1,$F$4<=3),CHOOSE($F$4,'SUPPORT PLAN'!$M19,'SUPPORT PLAN'!$T19,'SUPPORT PLAN'!$AA19),0) | E19: =SUMIFS('EXPENDITURE LOG'!$D$5:$D$504,'EXPENDITURE LOG'!$J$5:$J$504,$A19,'EXPENDITURE LOG'!$A$5:$A$504,">="&$C$4,'EXPENDITURE LOG'!$A$5:$A$504,"<"&EDATE($C$4,1)) | F19: =SUMIFS('EXPENDITURE LOG'!$D$5:$D$504,'EXPENDITURE LOG'!$J$5:$J$504,$A19,'EXPENDITURE LOG'!$A$5:$A$504,">="&$C$4,'EXPENDITURE LOG'!$A$5:$A$504,"<"&EDATE($C$4,1),'EXPENDITURE LOG'!$F$5:$F$504,"Church*") | G19: =E19-C19 | H19: =SUMIFS('EXPENDITURE LOG'!$D$5:$D$504,'EXPENDITURE LOG'!$J$5:$J$504,$A19,'EXPENDITURE LOG'!$A$5:$A$504,">="&'SUPPORT PLAN'!$C$4,'EXPENDITURE LOG'!$A$5:$A$504,"<"&EDATE($C$4,1)) | I19: =C19*MAX(0,$F$4) | J19: =H19-I19 | K19: =SUMIFS('EXPENDITURE LOG'!$D$5:$D$504,'EXPENDITURE LOG'!$J$5:$J$504,$A19)
A20: =EXPENSES!L18 | B20: =EXPENSES!B18 | C20: =EXPENSES!E18 | D20: =IF(AND($F$4>=1,$F$4<=3),CHOOSE($F$4,'SUPPORT PLAN'!$M20,'SUPPORT PLAN'!$T20,'SUPPORT PLAN'!$AA20),0) | E20: =SUMIFS('EXPENDITURE LOG'!$D$5:$D$504,'EXPENDITURE LOG'!$J$5:$J$504,$A20,'EXPENDITURE LOG'!$A$5:$A$504,">="&$C$4,'EXPENDITURE LOG'!$A$5:$A$504,"<"&EDATE($C$4,1)) | F20: =SUMIFS('EXPENDITURE LOG'!$D$5:$D$504,'EXPENDITURE LOG'!$J$5:$J$504,$A20,'EXPENDITURE LOG'!$A$5:$A$504,">="&$C$4,'EXPENDITURE LOG'!$A$5:$A$504,"<"&EDATE($C$4,1),'EXPENDITURE LOG'!$F$5:$F$504,"Church*") | G20: =E20-C20 | H20: =SUMIFS('EXPENDITURE LOG'!$D$5:$D$504,'EXPENDITURE LOG'!$J$5:$J$504,$A20,'EXPENDITURE LOG'!$A$5:$A$504,">="&'SUPPORT PLAN'!$C$4,'EXPENDITURE LOG'!$A$5:$A$504,"<"&EDATE($C$4,1)) | I20: =C20*MAX(0,$F$4) | J20: =H20-I20 | K20: =SUMIFS('EXPENDITURE LOG'!$D$5:$D$504,'EXPENDITURE LOG'!$J$5:$J$504,$A20)
A21: =EXPENSES!L19 | B21: =EXPENSES!B19 | C21: =EXPENSES!E19 | D21: =IF(AND($F$4>=1,$F$4<=3),CHOOSE($F$4,'SUPPORT PLAN'!$M21,'SUPPORT PLAN'!$T21,'SUPPORT PLAN'!$AA21),0) | E21: =SUMIFS('EXPENDITURE LOG'!$D$5:$D$504,'EXPENDITURE LOG'!$J$5:$J$504,$A21,'EXPENDITURE LOG'!$A$5:$A$504,">="&$C$4,'EXPENDITURE LOG'!$A$5:$A$504,"<"&EDATE($C$4,1)) | F21: =SUMIFS('EXPENDITURE LOG'!$D$5:$D$504,'EXPENDITURE LOG'!$J$5:$J$504,$A21,'EXPENDITURE LOG'!$A$5:$A$504,">="&$C$4,'EXPENDITURE LOG'!$A$5:$A$504,"<"&EDATE($C$4,1),'EXPENDITURE LOG'!$F$5:$F$504,"Church*") | G21: =E21-C21 | H21: =SUMIFS('EXPENDITURE LOG'!$D$5:$D$504,'EXPENDITURE LOG'!$J$5:$J$504,$A21,'EXPENDITURE LOG'!$A$5:$A$504,">="&'SUPPORT PLAN'!$C$4,'EXPENDITURE LOG'!$A$5:$A$504,"<"&EDATE($C$4,1)) | I21: =C21*MAX(0,$F$4) | J21: =H21-I21 | K21: =SUMIFS('EXPENDITURE LOG'!$D$5:$D$504,'EXPENDITURE LOG'!$J$5:$J$504,$A21)
B22: UTILITIES | C22: =SUM(C23:C31) | D22: =SUM(D23:D31) | E22: =SUM(E23:E31) | F22: =SUM(F23:F31) | G22: =SUM(G23:G31) | H22: =SUM(H23:H31) | I22: =SUM(I23:I31) | J22: =SUM(J23:J31) | K22: =SUM(K23:K31)
A23: =EXPENSES!L21 | B23: =EXPENSES!B21 | C23: =EXPENSES!E21 | D23: =IF(AND($F$4>=1,$F$4<=3),CHOOSE($F$4,'SUPPORT PLAN'!$M23,'SUPPORT PLAN'!$T23,'SUPPORT PLAN'!$AA23),0) | E23: =SUMIFS('EXPENDITURE LOG'!$D$5:$D$504,'EXPENDITURE LOG'!$J$5:$J$504,$A23,'EXPENDITURE LOG'!$A$5:$A$504,">="&$C$4,'EXPENDITURE LOG'!$A$5:$A$504,"<"&EDATE($C$4,1)) | F23: =SUMIFS('EXPENDITURE LOG'!$D$5:$D$504,'EXPENDITURE LOG'!$J$5:$J$504,$A23,'EXPENDITURE LOG'!$A$5:$A$504,">="&$C$4,'EXPENDITURE LOG'!$A$5:$A$504,"<"&EDATE($C$4,1),'EXPENDITURE LOG'!$F$5:$F$504,"Church*") | G23: =E23-C23 | H23: =SUMIFS('EXPENDITURE LOG'!$D$5:$D$504,'EXPENDITURE LOG'!$J$5:$J$504,$A23,'EXPENDITURE LOG'!$A$5:$A$504,">="&'SUPPORT PLAN'!$C$4,'EXPENDITURE LOG'!$A$5:$A$504,"<"&EDATE($C$4,1)) | I23: =C23*MAX(0,$F$4) | J23: =H23-I23 | K23: =SUMIFS('EXPENDITURE LOG'!$D$5:$D$504,'EXPENDITURE LOG'!$J$5:$J$504,$A23)
A24: =EXPENSES!L22 | B24: =EXPENSES!B22 | C24: =EXPENSES!E22 | D24: =IF(AND($F$4>=1,$F$4<=3),CHOOSE($F$4,'SUPPORT PLAN'!$M24,'SUPPORT PLAN'!$T24,'SUPPORT PLAN'!$AA24),0) | E24: =SUMIFS('EXPENDITURE LOG'!$D$5:$D$504,'EXPENDITURE LOG'!$J$5:$J$504,$A24,'EXPENDITURE LOG'!$A$5:$A$504,">="&$C$4,'EXPENDITURE LOG'!$A$5:$A$504,"<"&EDATE($C$4,1)) | F24: =SUMIFS('EXPENDITURE LOG'!$D$5:$D$504,'EXPENDITURE LOG'!$J$5:$J$504,$A24,'EXPENDITURE LOG'!$A$5:$A$504,">="&$C$4,'EXPENDITURE LOG'!$A$5:$A$504,"<"&EDATE($C$4,1),'EXPENDITURE LOG'!$F$5:$F$504,"Church*") | G24: =E24-C24 | H24: =SUMIFS('EXPENDITURE LOG'!$D$5:$D$504,'EXPENDITURE LOG'!$J$5:$J$504,$A24,'EXPENDITURE LOG'!$A$5:$A$504,">="&'SUPPORT PLAN'!$C$4,'EXPENDITURE LOG'!$A$5:$A$504,"<"&EDATE($C$4,1)) | I24: =C24*MAX(0,$F$4) | J24: =H24-I24 | K24: =SUMIFS('EXPENDITURE LOG'!$D$5:$D$504,'EXPENDITURE LOG'!$J$5:$J$504,$A24)
A25: =EXPENSES!L23 | B25: =EXPENSES!B23 | C25: =EXPENSES!E23 | D25: =IF(AND($F$4>=1,$F$4<=3),CHOOSE($F$4,'SUPPORT PLAN'!$M25,'SUPPORT PLAN'!$T25,'SUPPORT PLAN'!$AA25),0) | E25: =SUMIFS('EXPENDITURE LOG'!$D$5:$D$504,'EXPENDITURE LOG'!$J$5:$J$504,$A25,'EXPENDITURE LOG'!$A$5:$A$504,">="&$C$4,'EXPENDITURE LOG'!$A$5:$A$504,"<"&EDATE($C$4,1)) | F25: =SUMIFS('EXPENDITURE LOG'!$D$5:$D$504,'EXPENDITURE LOG'!$J$5:$J$504,$A25,'EXPENDITURE LOG'!$A$5:$A$504,">="&$C$4,'EXPENDITURE LOG'!$A$5:$A$504,"<"&EDATE($C$4,1),'EXPENDITURE LOG'!$F$5:$F$504,"Church*") | G25: =E25-C25 | H25: =SUMIFS('EXPENDITURE LOG'!$D$5:$D$504,'EXPENDITURE LOG'!$J$5:$J$504,$A25,'EXPENDITURE LOG'!$A$5:$A$504,">="&'SUPPORT PLAN'!$C$4,'EXPENDITURE LOG'!$A$5:$A$504,"<"&EDATE($C$4,1)) | I25: =C25*MAX(0,$F$4) | J25: =H25-I25 | K25: =SUMIFS('EXPENDITURE LOG'!$D$5:$D$504,'EXPENDITURE LOG'!$J$5:$J$504,$A25)
A26: =EXPENSES!L24 | B26: =EXPENSES!B24 | C26: =EXPENSES!E24 | D26: =IF(AND($F$4>=1,$F$4<=3),CHOOSE($F$4,'SUPPORT PLAN'!$M26,'SUPPORT PLAN'!$T26,'SUPPORT PLAN'!$AA26),0) | E26: =SUMIFS('EXPENDITURE LOG'!$D$5:$D$504,'EXPENDITURE LOG'!$J$5:$J$504,$A26,'EXPENDITURE LOG'!$A$5:$A$504,">="&$C$4,'EXPENDITURE LOG'!$A$5:$A$504,"<"&EDATE($C$4,1)) | F26: =SUMIFS('EXPENDITURE LOG'!$D$5:$D$504,'EXPENDITURE LOG'!$J$5:$J$504,$A26,'EXPENDITURE LOG'!$A$5:$A$504,">="&$C$4,'EXPENDITURE LOG'!$A$5:$A$504,"<"&EDATE($C$4,1),'EXPENDITURE LOG'!$F$5:$F$504,"Church*") | G26: =E26-C26 | H26: =SUMIFS('EXPENDITURE LOG'!$D$5:$D$504,'EXPENDITURE LOG'!$J$5:$J$504,$A26,'EXPENDITURE LOG'!$A$5:$A$504,">="&'SUPPORT PLAN'!$C$4,'EXPENDITURE LOG'!$A$5:$A$504,"<"&EDATE($C$4,1)) | I26: =C26*MAX(0,$F$4) | J26: =H26-I26 | K26: =SUMIFS('EXPENDITURE LOG'!$D$5:$D$504,'EXPENDITURE LOG'!$J$5:$J$504,$A26)
A27: =EXPENSES!L25 | B27: =EXPENSES!B25 | C27: =EXPENSES!E25 | D27: =IF(AND($F$4>=1,$F$4<=3),CHOOSE($F$4,'SUPPORT PLAN'!$M27,'SUPPORT PLAN'!$T27,'SUPPORT PLAN'!$AA27),0) | E27: =SUMIFS('EXPENDITURE LOG'!$D$5:$D$504,'EXPENDITURE LOG'!$J$5:$J$504,$A27,'EXPENDITURE LOG'!$A$5:$A$504,">="&$C$4,'EXPENDITURE LOG'!$A$5:$A$504,"<"&EDATE($C$4,1)) | F27: =SUMIFS('EXPENDITURE LOG'!$D$5:$D$504,'EXPENDITURE LOG'!$J$5:$J$504,$A27,'EXPENDITURE LOG'!$A$5:$A$504,">="&$C$4,'EXPENDITURE LOG'!$A$5:$A$504,"<"&EDATE($C$4,1),'EXPENDITURE LOG'!$F$5:$F$504,"Church*") | G27: =E27-C27 | H27: =SUMIFS('EXPENDITURE LOG'!$D$5:$D$504,'EXPENDITURE LOG'!$J$5:$J$504,$A27,'EXPENDITURE LOG'!$A$5:$A$504,">="&'SUPPORT PLAN'!$C$4,'EXPENDITURE LOG'!$A$5:$A$504,"<"&EDATE($C$4,1)) | I27: =C27*MAX(0,$F$4) | J27: =H27-I27 | K27: =SUMIFS('EXPENDITURE LOG'!$D$5:$D$504,'EXPENDITURE LOG'!$J$5:$J$504,$A27)
A28: =EXPENSES!L26 | B28: =EXPENSES!B26 | C28: =EXPENSES!E26 | D28: =IF(AND($F$4>=1,$F$4<=3),CHOOSE($F$4,'SUPPORT PLAN'!$M28,'SUPPORT PLAN'!$T28,'SUPPORT PLAN'!$AA28),0) | E28: =SUMIFS('EXPENDITURE LOG'!$D$5:$D$504,'EXPENDITURE LOG'!$J$5:$J$504,$A28,'EXPENDITURE LOG'!$A$5:$A$504,">="&$C$4,'EXPENDITURE LOG'!$A$5:$A$504,"<"&EDATE($C$4,1)) | F28: =SUMIFS('EXPENDITURE LOG'!$D$5:$D$504,'EXPENDITURE LOG'!$J$5:$J$504,$A28,'EXPENDITURE LOG'!$A$5:$A$504,">="&$C$4,'EXPENDITURE LOG'!$A$5:$A$504,"<"&EDATE($C$4,1),'EXPENDITURE LOG'!$F$5:$F$504,"Church*") | G28: =E28-C28 | H28: =SUMIFS('EXPENDITURE LOG'!$D$5:$D$504,'EXPENDITURE LOG'!$J$5:$J$504,$A28,'EXPENDITURE LOG'!$A$5:$A$504,">="&'SUPPORT PLAN'!$C$4,'EXPENDITURE LOG'!$A$5:$A$504,"<"&EDATE($C$4,1)) | I28: =C28*MAX(0,$F$4) | J28: =H28-I28 | K28: =SUMIFS('EXPENDITURE LOG'!$D$5:$D$504,'EXPENDITURE LOG'!$J$5:$J$504,$A28)
A29: =EXPENSES!L27 | B29: =EXPENSES!B27 | C29: =EXPENSES!E27 | D29: =IF(AND($F$4>=1,$F$4<=3),CHOOSE($F$4,'SUPPORT PLAN'!$M29,'SUPPORT PLAN'!$T29,'SUPPORT PLAN'!$AA29),0) | E29: =SUMIFS('EXPENDITURE LOG'!$D$5:$D$504,'EXPENDITURE LOG'!$J$5:$J$504,$A29,'EXPENDITURE LOG'!$A$5:$A$504,">="&$C$4,'EXPENDITURE LOG'!$A$5:$A$504,"<"&EDATE($C$4,1)) | F29: =SUMIFS('EXPENDITURE LOG'!$D$5:$D$504,'EXPENDITURE LOG'!$J$5:$J$504,$A29,'EXPENDITURE LOG'!$A$5:$A$504,">="&$C$4,'EXPENDITURE LOG'!$A$5:$A$504,"<"&EDATE($C$4,1),'EXPENDITURE LOG'!$F$5:$F$504,"Church*") | G29: =E29-C29 | H29: =SUMIFS('EXPENDITURE LOG'!$D$5:$D$504,'EXPENDITURE LOG'!$J$5:$J$504,$A29,'EXPENDITURE LOG'!$A$5:$A$504,">="&'SUPPORT PLAN'!$C$4,'EXPENDITURE LOG'!$A$5:$A$504,"<"&EDATE($C$4,1)) | I29: =C29*MAX(0,$F$4) | J29: =H29-I29 | K29: =SUMIFS('EXPENDITURE LOG'!$D$5:$D$504,'EXPENDITURE LOG'!$J$5:$J$504,$A29)
A30: =EXPENSES!L28 | B30: =EXPENSES!B28 | C30: =EXPENSES!E28 | D30: =IF(AND($F$4>=1,$F$4<=3),CHOOSE($F$4,'SUPPORT PLAN'!$M30,'SUPPORT PLAN'!$T30,'SUPPORT PLAN'!$AA30),0) | E30: =SUMIFS('EXPENDITURE LOG'!$D$5:$D$504,'EXPENDITURE LOG'!$J$5:$J$504,$A30,'EXPENDITURE LOG'!$A$5:$A$504,">="&$C$4,'EXPENDITURE LOG'!$A$5:$A$504,"<"&EDATE($C$4,1)) | F30: =SUMIFS('EXPENDITURE LOG'!$D$5:$D$504,'EXPENDITURE LOG'!$J$5:$J$504,$A30,'EXPENDITURE LOG'!$A$5:$A$504,">="&$C$4,'EXPENDITURE LOG'!$A$5:$A$504,"<"&EDATE($C$4,1),'EXPENDITURE LOG'!$F$5:$F$504,"Church*") | G30: =E30-C30 | H30: =SUMIFS('EXPENDITURE LOG'!$D$5:$D$504,'EXPENDITURE LOG'!$J$5:$J$504,$A30,'EXPENDITURE LOG'!$A$5:$A$504,">="&'SUPPORT PLAN'!$C$4,'EXPENDITURE LOG'!$A$5:$A$504,"<"&EDATE($C$4,1)) | I30: =C30*MAX(0,$F$4) | J30: =H30-I30 | K30: =SUMIFS('EXPENDITURE LOG'!$D$5:$D$504,'EXPENDITURE LOG'!$J$5:$J$504,$A30)
A31: =EXPENSES!L29 | B31: =EXPENSES!B29 | C31: =EXPENSES!E29 | D31: =IF(AND($F$4>=1,$F$4<=3),CHOOSE($F$4,'SUPPORT PLAN'!$M31,'SUPPORT PLAN'!$T31,'SUPPORT PLAN'!$AA31),0) | E31: =SUMIFS('EXPENDITURE LOG'!$D$5:$D$504,'EXPENDITURE LOG'!$J$5:$J$504,$A31,'EXPENDITURE LOG'!$A$5:$A$504,">="&$C$4,'EXPENDITURE LOG'!$A$5:$A$504,"<"&EDATE($C$4,1)) | F31: =SUMIFS('EXPENDITURE LOG'!$D$5:$D$504,'EXPENDITURE LOG'!$J$5:$J$504,$A31,'EXPENDITURE LOG'!$A$5:$A$504,">="&$C$4,'EXPENDITURE LOG'!$A$5:$A$504,"<"&EDATE($C$4,1),'EXPENDITURE LOG'!$F$5:$F$504,"Church*") | G31: =E31-C31 | H31: =SUMIFS('EXPENDITURE LOG'!$D$5:$D$504,'EXPENDITURE LOG'!$J$5:$J$504,$A31,'EXPENDITURE LOG'!$A$5:$A$504,">="&'SUPPORT PLAN'!$C$4,'EXPENDITURE LOG'!$A$5:$A$504,"<"&EDATE($C$4,1)) | I31: =C31*MAX(0,$F$4) | J31: =H31-I31 | K31: =SUMIFS('EXPENDITURE LOG'!$D$5:$D$504,'EXPENDITURE LOG'!$J$5:$J$504,$A31)
B32: FOOD | C32: =SUM(C33:C38) | D32: =SUM(D33:D38) | E32: =SUM(E33:E38) | F32: =SUM(F33:F38) | G32: =SUM(G33:G38) | H32: =SUM(H33:H38) | I32: =SUM(I33:I38) | J32: =SUM(J33:J38) | K32: =SUM(K33:K38)
A33: =EXPENSES!L31 | B33: =EXPENSES!B31 | C33: =EXPENSES!E31 | D33: =IF(AND($F$4>=1,$F$4<=3),CHOOSE($F$4,'SUPPORT PLAN'!$M33,'SUPPORT PLAN'!$T33,'SUPPORT PLAN'!$AA33),0) | E33: =SUMIFS('EXPENDITURE LOG'!$D$5:$D$504,'EXPENDITURE LOG'!$J$5:$J$504,$A33,'EXPENDITURE LOG'!$A$5:$A$504,">="&$C$4,'EXPENDITURE LOG'!$A$5:$A$504,"<"&EDATE($C$4,1)) | F33: =SUMIFS('EXPENDITURE LOG'!$D$5:$D$504,'EXPENDITURE LOG'!$J$5:$J$504,$A33,'EXPENDITURE LOG'!$A$5:$A$504,">="&$C$4,'EXPENDITURE LOG'!$A$5:$A$504,"<"&EDATE($C$4,1),'EXPENDITURE LOG'!$F$5:$F$504,"Church*") | G33: =E33-C33 | H33: =SUMIFS('EXPENDITURE LOG'!$D$5:$D$504,'EXPENDITURE LOG'!$J$5:$J$504,$A33,'EXPENDITURE LOG'!$A$5:$A$504,">="&'SUPPORT PLAN'!$C$4,'EXPENDITURE LOG'!$A$5:$A$504,"<"&EDATE($C$4,1)) | I33: =C33*MAX(0,$F$4) | J33: =H33-I33 | K33: =SUMIFS('EXPENDITURE LOG'!$D$5:$D$504,'EXPENDITURE LOG'!$J$5:$J$504,$A33)
A34: =EXPENSES!L32 | B34: =EXPENSES!B32 | C34: =EXPENSES!E32 | D34: =IF(AND($F$4>=1,$F$4<=3),CHOOSE($F$4,'SUPPORT PLAN'!$M34,'SUPPORT PLAN'!$T34,'SUPPORT PLAN'!$AA34),0) | E34: =SUMIFS('EXPENDITURE LOG'!$D$5:$D$504,'EXPENDITURE LOG'!$J$5:$J$504,$A34,'EXPENDITURE LOG'!$A$5:$A$504,">="&$C$4,'EXPENDITURE LOG'!$A$5:$A$504,"<"&EDATE($C$4,1)) | F34: =SUMIFS('EXPENDITURE LOG'!$D$5:$D$504,'EXPENDITURE LOG'!$J$5:$J$504,$A34,'EXPENDITURE LOG'!$A$5:$A$504,">="&$C$4,'EXPENDITURE LOG'!$A$5:$A$504,"<"&EDATE($C$4,1),'EXPENDITURE LOG'!$F$5:$F$504,"Church*") | G34: =E34-C34 | H34: =SUMIFS('EXPENDITURE LOG'!$D$5:$D$504,'EXPENDITURE LOG'!$J$5:$J$504,$A34,'EXPENDITURE LOG'!$A$5:$A$504,">="&'SUPPORT PLAN'!$C$4,'EXPENDITURE LOG'!$A$5:$A$504,"<"&EDATE($C$4,1)) | I34: =C34*MAX(0,$F$4) | J34: =H34-I34 | K34: =SUMIFS('EXPENDITURE LOG'!$D$5:$D$504,'EXPENDITURE LOG'!$J$5:$J$504,$A34)
A35: =EXPENSES!L33 | B35: =EXPENSES!B33 | C35: =EXPENSES!E33 | D35: =IF(AND($F$4>=1,$F$4<=3),CHOOSE($F$4,'SUPPORT PLAN'!$M35,'SUPPORT PLAN'!$T35,'SUPPORT PLAN'!$AA35),0) | E35: =SUMIFS('EXPENDITURE LOG'!$D$5:$D$504,'EXPENDITURE LOG'!$J$5:$J$504,$A35,'EXPENDITURE LOG'!$A$5:$A$504,">="&$C$4,'EXPENDITURE LOG'!$A$5:$A$504,"<"&EDATE($C$4,1)) | F35: =SUMIFS('EXPENDITURE LOG'!$D$5:$D$504,'EXPENDITURE LOG'!$J$5:$J$504,$A35,'EXPENDITURE LOG'!$A$5:$A$504,">="&$C$4,'EXPENDITURE LOG'!$A$5:$A$504,"<"&EDATE($C$4,1),'EXPENDITURE LOG'!$F$5:$F$504,"Church*") | G35: =E35-C35 | H35: =SUMIFS('EXPENDITURE LOG'!$D$5:$D$504,'EXPENDITURE LOG'!$J$5:$J$504,$A35,'EXPENDITURE LOG'!$A$5:$A$504,">="&'SUPPORT PLAN'!$C$4,'EXPENDITURE LOG'!$A$5:$A$504,"<"&EDATE($C$4,1)) | I35: =C35*MAX(0,$F$4) | J35: =H35-I35 | K35: =SUMIFS('EXPENDITURE LOG'!$D$5:$D$504,'EXPENDITURE LOG'!$J$5:$J$504,$A35)
A36: =EXPENSES!L34 | B36: =EXPENSES!B34 | C36: =EXPENSES!E34 | D36: =IF(AND($F$4>=1,$F$4<=3),CHOOSE($F$4,'SUPPORT PLAN'!$M36,'SUPPORT PLAN'!$T36,'SUPPORT PLAN'!$AA36),0) | E36: =SUMIFS('EXPENDITURE LOG'!$D$5:$D$504,'EXPENDITURE LOG'!$J$5:$J$504,$A36,'EXPENDITURE LOG'!$A$5:$A$504,">="&$C$4,'EXPENDITURE LOG'!$A$5:$A$504,"<"&EDATE($C$4,1)) | F36: =SUMIFS('EXPENDITURE LOG'!$D$5:$D$504,'EXPENDITURE LOG'!$J$5:$J$504,$A36,'EXPENDITURE LOG'!$A$5:$A$504,">="&$C$4,'EXPENDITURE LOG'!$A$5:$A$504,"<"&EDATE($C$4,1),'EXPENDITURE LOG'!$F$5:$F$504,"Church*") | G36: =E36-C36 | H36: =SUMIFS('EXPENDITURE LOG'!$D$5:$D$504,'EXPENDITURE LOG'!$J$5:$J$504,$A36,'EXPENDITURE LOG'!$A$5:$A$504,">="&'SUPPORT PLAN'!$C$4,'EXPENDITURE LOG'!$A$5:$A$504,"<"&EDATE($C$4,1)) | I36: =C36*MAX(0,$F$4) | J36: =H36-I36 | K36: =SUMIFS('EXPENDITURE LOG'!$D$5:$D$504,'EXPENDITURE LOG'!$J$5:$J$504,$A36)
A37: =EXPENSES!L35 | B37: =EXPENSES!B35 | C37: =EXPENSES!E35 | D37: =IF(AND($F$4>=1,$F$4<=3),CHOOSE($F$4,'SUPPORT PLAN'!$M37,'SUPPORT PLAN'!$T37,'SUPPORT PLAN'!$AA37),0) | E37: =SUMIFS('EXPENDITURE LOG'!$D$5:$D$504,'EXPENDITURE LOG'!$J$5:$J$504,$A37,'EXPENDITURE LOG'!$A$5:$A$504,">="&$C$4,'EXPENDITURE LOG'!$A$5:$A$504,"<"&EDATE($C$4,1)) | F37: =SUMIFS('EXPENDITURE LOG'!$D$5:$D$504,'EXPENDITURE LOG'!$J$5:$J$504,$A37,'EXPENDITURE LOG'!$A$5:$A$504,">="&$C$4,'EXPENDITURE LOG'!$A$5:$A$504,"<"&EDATE($C$4,1),'EXPENDITURE LOG'!$F$5:$F$504,"Church*") | G37: =E37-C37 | H37: =SUMIFS('EXPENDITURE LOG'!$D$5:$D$504,'EXPENDITURE LOG'!$J$5:$J$504,$A37,'EXPENDITURE LOG'!$A$5:$A$504,">="&'SUPPORT PLAN'!$C$4,'EXPENDITURE LOG'!$A$5:$A$504,"<"&EDATE($C$4,1)) | I37: =C37*MAX(0,$F$4) | J37: =H37-I37 | K37: =SUMIFS('EXPENDITURE LOG'!$D$5:$D$504,'EXPENDITURE LOG'!$J$5:$J$504,$A37)
A38: =EXPENSES!L36 | B38: =EXPENSES!B36 | C38: =EXPENSES!E36 | D38: =IF(AND($F$4>=1,$F$4<=3),CHOOSE($F$4,'SUPPORT PLAN'!$M38,'SUPPORT PLAN'!$T38,'SUPPORT PLAN'!$AA38),0) | E38: =SUMIFS('EXPENDITURE LOG'!$D$5:$D$504,'EXPENDITURE LOG'!$J$5:$J$504,$A38,'EXPENDITURE LOG'!$A$5:$A$504,">="&$C$4,'EXPENDITURE LOG'!$A$5:$A$504,"<"&EDATE($C$4,1)) | F38: =SUMIFS('EXPENDITURE LOG'!$D$5:$D$504,'EXPENDITURE LOG'!$J$5:$J$504,$A38,'EXPENDITURE LOG'!$A$5:$A$504,">="&$C$4,'EXPENDITURE LOG'!$A$5:$A$504,"<"&EDATE($C$4,1),'EXPENDITURE LOG'!$F$5:$F$504,"Church*") | G38: =E38-C38 | H38: =SUMIFS('EXPENDITURE LOG'!$D$5:$D$504,'EXPENDITURE LOG'!$J$5:$J$504,$A38,'EXPENDITURE LOG'!$A$5:$A$504,">="&'SUPPORT PLAN'!$C$4,'EXPENDITURE LOG'!$A$5:$A$504,"<"&EDATE($C$4,1)) | I38: =C38*MAX(0,$F$4) | J38: =H38-I38 | K38: =SUMIFS('EXPENDITURE LOG'!$D$5:$D$504,'EXPENDITURE LOG'!$J$5:$J$504,$A38)
B39: HOUSEHOLD & PERSONAL | C39: =SUM(C40:C46) | D39: =SUM(D40:D46) | E39: =SUM(E40:E46) | F39: =SUM(F40:F46) | G39: =SUM(G40:G46) | H39: =SUM(H40:H46) | I39: =SUM(I40:I46) | J39: =SUM(J40:J46) | K39: =SUM(K40:K46)
A40: =EXPENSES!L38 | B40: =EXPENSES!B38 | C40: =EXPENSES!E38 | D40: =IF(AND($F$4>=1,$F$4<=3),CHOOSE($F$4,'SUPPORT PLAN'!$M40,'SUPPORT PLAN'!$T40,'SUPPORT PLAN'!$AA40),0) | E40: =SUMIFS('EXPENDITURE LOG'!$D$5:$D$504,'EXPENDITURE LOG'!$J$5:$J$504,$A40,'EXPENDITURE LOG'!$A$5:$A$504,">="&$C$4,'EXPENDITURE LOG'!$A$5:$A$504,"<"&EDATE($C$4,1)) | F40: =SUMIFS('EXPENDITURE LOG'!$D$5:$D$504,'EXPENDITURE LOG'!$J$5:$J$504,$A40,'EXPENDITURE LOG'!$A$5:$A$504,">="&$C$4,'EXPENDITURE LOG'!$A$5:$A$504,"<"&EDATE($C$4,1),'EXPENDITURE LOG'!$F$5:$F$504,"Church*") | G40: =E40-C40 | H40: =SUMIFS('EXPENDITURE LOG'!$D$5:$D$504,'EXPENDITURE LOG'!$J$5:$J$504,$A40,'EXPENDITURE LOG'!$A$5:$A$504,">="&'SUPPORT PLAN'!$C$4,'EXPENDITURE LOG'!$A$5:$A$504,"<"&EDATE($C$4,1)) | I40: =C40*MAX(0,$F$4) | J40: =H40-I40 | K40: =SUMIFS('EXPENDITURE LOG'!$D$5:$D$504,'EXPENDITURE LOG'!$J$5:$J$504,$A40)
A41: =EXPENSES!L39 | B41: =EXPENSES!B39 | C41: =EXPENSES!E39 | D41: =IF(AND($F$4>=1,$F$4<=3),CHOOSE($F$4,'SUPPORT PLAN'!$M41,'SUPPORT PLAN'!$T41,'SUPPORT PLAN'!$AA41),0) | E41: =SUMIFS('EXPENDITURE LOG'!$D$5:$D$504,'EXPENDITURE LOG'!$J$5:$J$504,$A41,'EXPENDITURE LOG'!$A$5:$A$504,">="&$C$4,'EXPENDITURE LOG'!$A$5:$A$504,"<"&EDATE($C$4,1)) | F41: =SUMIFS('EXPENDITURE LOG'!$D$5:$D$504,'EXPENDITURE LOG'!$J$5:$J$504,$A41,'EXPENDITURE LOG'!$A$5:$A$504,">="&$C$4,'EXPENDITURE LOG'!$A$5:$A$504,"<"&EDATE($C$4,1),'EXPENDITURE LOG'!$F$5:$F$504,"Church*") | G41: =E41-C41 | H41: =SUMIFS('EXPENDITURE LOG'!$D$5:$D$504,'EXPENDITURE LOG'!$J$5:$J$504,$A41,'EXPENDITURE LOG'!$A$5:$A$504,">="&'SUPPORT PLAN'!$C$4,'EXPENDITURE LOG'!$A$5:$A$504,"<"&EDATE($C$4,1)) | I41: =C41*MAX(0,$F$4) | J41: =H41-I41 | K41: =SUMIFS('EXPENDITURE LOG'!$D$5:$D$504,'EXPENDITURE LOG'!$J$5:$J$504,$A41)
A42: =EXPENSES!L40 | B42: =EXPENSES!B40 | C42: =EXPENSES!E40 | D42: =IF(AND($F$4>=1,$F$4<=3),CHOOSE($F$4,'SUPPORT PLAN'!$M42,'SUPPORT PLAN'!$T42,'SUPPORT PLAN'!$AA42),0) | E42: =SUMIFS('EXPENDITURE LOG'!$D$5:$D$504,'EXPENDITURE LOG'!$J$5:$J$504,$A42,'EXPENDITURE LOG'!$A$5:$A$504,">="&$C$4,'EXPENDITURE LOG'!$A$5:$A$504,"<"&EDATE($C$4,1)) | F42: =SUMIFS('EXPENDITURE LOG'!$D$5:$D$504,'EXPENDITURE LOG'!$J$5:$J$504,$A42,'EXPENDITURE LOG'!$A$5:$A$504,">="&$C$4,'EXPENDITURE LOG'!$A$5:$A$504,"<"&EDATE($C$4,1),'EXPENDITURE LOG'!$F$5:$F$504,"Church*") | G42: =E42-C42 | H42: =SUMIFS('EXPENDITURE LOG'!$D$5:$D$504,'EXPENDITURE LOG'!$J$5:$J$504,$A42,'EXPENDITURE LOG'!$A$5:$A$504,">="&'SUPPORT PLAN'!$C$4,'EXPENDITURE LOG'!$A$5:$A$504,"<"&EDATE($C$4,1)) | I42: =C42*MAX(0,$F$4) | J42: =H42-I42 | K42: =SUMIFS('EXPENDITURE LOG'!$D$5:$D$504,'EXPENDITURE LOG'!$J$5:$J$504,$A42)
A43: =EXPENSES!L41 | B43: =EXPENSES!B41 | C43: =EXPENSES!E41 | D43: =IF(AND($F$4>=1,$F$4<=3),CHOOSE($F$4,'SUPPORT PLAN'!$M43,'SUPPORT PLAN'!$T43,'SUPPORT PLAN'!$AA43),0) | E43: =SUMIFS('EXPENDITURE LOG'!$D$5:$D$504,'EXPENDITURE LOG'!$J$5:$J$504,$A43,'EXPENDITURE LOG'!$A$5:$A$504,">="&$C$4,'EXPENDITURE LOG'!$A$5:$A$504,"<"&EDATE($C$4,1)) | F43: =SUMIFS('EXPENDITURE LOG'!$D$5:$D$504,'EXPENDITURE LOG'!$J$5:$J$504,$A43,'EXPENDITURE LOG'!$A$5:$A$504,">="&$C$4,'EXPENDITURE LOG'!$A$5:$A$504,"<"&EDATE($C$4,1),'EXPENDITURE LOG'!$F$5:$F$504,"Church*") | G43: =E43-C43 | H43: =SUMIFS('EXPENDITURE LOG'!$D$5:$D$504,'EXPENDITURE LOG'!$J$5:$J$504,$A43,'EXPENDITURE LOG'!$A$5:$A$504,">="&'SUPPORT PLAN'!$C$4,'EXPENDITURE LOG'!$A$5:$A$504,"<"&EDATE($C$4,1)) | I43: =C43*MAX(0,$F$4) | J43: =H43-I43 | K43: =SUMIFS('EXPENDITURE LOG'!$D$5:$D$504,'EXPENDITURE LOG'!$J$5:$J$504,$A43)
A44: =EXPENSES!L42 | B44: =EXPENSES!B42 | C44: =EXPENSES!E42 | D44: =IF(AND($F$4>=1,$F$4<=3),CHOOSE($F$4,'SUPPORT PLAN'!$M44,'SUPPORT PLAN'!$T44,'SUPPORT PLAN'!$AA44),0) | E44: =SUMIFS('EXPENDITURE LOG'!$D$5:$D$504,'EXPENDITURE LOG'!$J$5:$J$504,$A44,'EXPENDITURE LOG'!$A$5:$A$504,">="&$C$4,'EXPENDITURE LOG'!$A$5:$A$504,"<"&EDATE($C$4,1)) | F44: =SUMIFS('EXPENDITURE LOG'!$D$5:$D$504,'EXPENDITURE LOG'!$J$5:$J$504,$A44,'EXPENDITURE LOG'!$A$5:$A$504,">="&$C$4,'EXPENDITURE LOG'!$A$5:$A$504,"<"&EDATE($C$4,1),'EXPENDITURE LOG'!$F$5:$F$504,"Church*") | G44: =E44-C44 | H44: =SUMIFS('EXPENDITURE LOG'!$D$5:$D$504,'EXPENDITURE LOG'!$J$5:$J$504,$A44,'EXPENDITURE LOG'!$A$5:$A$504,">="&'SUPPORT PLAN'!$C$4,'EXPENDITURE LOG'!$A$5:$A$504,"<"&EDATE($C$4,1)) | I44: =C44*MAX(0,$F$4) | J44: =H44-I44 | K44: =SUMIFS('EXPENDITURE LOG'!$D$5:$D$504,'EXPENDITURE LOG'!$J$5:$J$504,$A44)
A45: =EXPENSES!L43 | B45: =EXPENSES!B43 | C45: =EXPENSES!E43 | D45: =IF(AND($F$4>=1,$F$4<=3),CHOOSE($F$4,'SUPPORT PLAN'!$M45,'SUPPORT PLAN'!$T45,'SUPPORT PLAN'!$AA45),0) | E45: =SUMIFS('EXPENDITURE LOG'!$D$5:$D$504,'EXPENDITURE LOG'!$J$5:$J$504,$A45,'EXPENDITURE LOG'!$A$5:$A$504,">="&$C$4,'EXPENDITURE LOG'!$A$5:$A$504,"<"&EDATE($C$4,1)) | F45: =SUMIFS('EXPENDITURE LOG'!$D$5:$D$504,'EXPENDITURE LOG'!$J$5:$J$504,$A45,'EXPENDITURE LOG'!$A$5:$A$504,">="&$C$4,'EXPENDITURE LOG'!$A$5:$A$504,"<"&EDATE($C$4,1),'EXPENDITURE LOG'!$F$5:$F$504,"Church*") | G45: =E45-C45 | H45: =SUMIFS('EXPENDITURE LOG'!$D$5:$D$504,'EXPENDITURE LOG'!$J$5:$J$504,$A45,'EXPENDITURE LOG'!$A$5:$A$504,">="&'SUPPORT PLAN'!$C$4,'EXPENDITURE LOG'!$A$5:$A$504,"<"&EDATE($C$4,1)) | I45: =C45*MAX(0,$F$4) | J45: =H45-I45 | K45: =SUMIFS('EXPENDITURE LOG'!$D$5:$D$504,'EXPENDITURE LOG'!$J$5:$J$504,$A45)
A46: =EXPENSES!L44 | B46: =EXPENSES!B44 | C46: =EXPENSES!E44 | D46: =IF(AND($F$4>=1,$F$4<=3),CHOOSE($F$4,'SUPPORT PLAN'!$M46,'SUPPORT PLAN'!$T46,'SUPPORT PLAN'!$AA46),0) | E46: =SUMIFS('EXPENDITURE LOG'!$D$5:$D$504,'EXPENDITURE LOG'!$J$5:$J$504,$A46,'EXPENDITURE LOG'!$A$5:$A$504,">="&$C$4,'EXPENDITURE LOG'!$A$5:$A$504,"<"&EDATE($C$4,1)) | F46: =SUMIFS('EXPENDITURE LOG'!$D$5:$D$504,'EXPENDITURE LOG'!$J$5:$J$504,$A46,'EXPENDITURE LOG'!$A$5:$A$504,">="&$C$4,'EXPENDITURE LOG'!$A$5:$A$504,"<"&EDATE($C$4,1),'EXPENDITURE LOG'!$F$5:$F$504,"Church*") | G46: =E46-C46 | H46: =SUMIFS('EXPENDITURE LOG'!$D$5:$D$504,'EXPENDITURE LOG'!$J$5:$J$504,$A46,'EXPENDITURE LOG'!$A$5:$A$504,">="&'SUPPORT PLAN'!$C$4,'EXPENDITURE LOG'!$A$5:$A$504,"<"&EDATE($C$4,1)) | I46: =C46*MAX(0,$F$4) | J46: =H46-I46 | K46: =SUMIFS('EXPENDITURE LOG'!$D$5:$D$504,'EXPENDITURE LOG'!$J$5:$J$504,$A46)
B47: CLOTHING | C47: =SUM(C48:C52) | D47: =SUM(D48:D52) | E47: =SUM(E48:E52) | F47: =SUM(F48:F52) | G47: =SUM(G48:G52) | H47: =SUM(H48:H52) | I47: =SUM(I48:I52) | J47: =SUM(J48:J52) | K47: =SUM(K48:K52)
A48: =EXPENSES!L46 | B48: =EXPENSES!B46 | C48: =EXPENSES!E46 | D48: =IF(AND($F$4>=1,$F$4<=3),CHOOSE($F$4,'SUPPORT PLAN'!$M48,'SUPPORT PLAN'!$T48,'SUPPORT PLAN'!$AA48),0) | E48: =SUMIFS('EXPENDITURE LOG'!$D$5:$D$504,'EXPENDITURE LOG'!$J$5:$J$504,$A48,'EXPENDITURE LOG'!$A$5:$A$504,">="&$C$4,'EXPENDITURE LOG'!$A$5:$A$504,"<"&EDATE($C$4,1)) | F48: =SUMIFS('EXPENDITURE LOG'!$D$5:$D$504,'EXPENDITURE LOG'!$J$5:$J$504,$A48,'EXPENDITURE LOG'!$A$5:$A$504,">="&$C$4,'EXPENDITURE LOG'!$A$5:$A$504,"<"&EDATE($C$4,1),'EXPENDITURE LOG'!$F$5:$F$504,"Church*") | G48: =E48-C48 | H48: =SUMIFS('EXPENDITURE LOG'!$D$5:$D$504,'EXPENDITURE LOG'!$J$5:$J$504,$A48,'EXPENDITURE LOG'!$A$5:$A$504,">="&'SUPPORT PLAN'!$C$4,'EXPENDITURE LOG'!$A$5:$A$504,"<"&EDATE($C$4,1)) | I48: =C48*MAX(0,$F$4) | J48: =H48-I48 | K48: =SUMIFS('EXPENDITURE LOG'!$D$5:$D$504,'EXPENDITURE LOG'!$J$5:$J$504,$A48)
A49: =EXPENSES!L47 | B49: =EXPENSES!B47 | C49: =EXPENSES!E47 | D49: =IF(AND($F$4>=1,$F$4<=3),CHOOSE($F$4,'SUPPORT PLAN'!$M49,'SUPPORT PLAN'!$T49,'SUPPORT PLAN'!$AA49),0) | E49: =SUMIFS('EXPENDITURE LOG'!$D$5:$D$504,'EXPENDITURE LOG'!$J$5:$J$504,$A49,'EXPENDITURE LOG'!$A$5:$A$504,">="&$C$4,'EXPENDITURE LOG'!$A$5:$A$504,"<"&EDATE($C$4,1)) | F49: =SUMIFS('EXPENDITURE LOG'!$D$5:$D$504,'EXPENDITURE LOG'!$J$5:$J$504,$A49,'EXPENDITURE LOG'!$A$5:$A$504,">="&$C$4,'EXPENDITURE LOG'!$A$5:$A$504,"<"&EDATE($C$4,1),'EXPENDITURE LOG'!$F$5:$F$504,"Church*") | G49: =E49-C49 | H49: =SUMIFS('EXPENDITURE LOG'!$D$5:$D$504,'EXPENDITURE LOG'!$J$5:$J$504,$A49,'EXPENDITURE LOG'!$A$5:$A$504,">="&'SUPPORT PLAN'!$C$4,'EXPENDITURE LOG'!$A$5:$A$504,"<"&EDATE($C$4,1)) | I49: =C49*MAX(0,$F$4) | J49: =H49-I49 | K49: =SUMIFS('EXPENDITURE LOG'!$D$5:$D$504,'EXPENDITURE LOG'!$J$5:$J$504,$A49)
A50: =EXPENSES!L48 | B50: =EXPENSES!B48 | C50: =EXPENSES!E48 | D50: =IF(AND($F$4>=1,$F$4<=3),CHOOSE($F$4,'SUPPORT PLAN'!$M50,'SUPPORT PLAN'!$T50,'SUPPORT PLAN'!$AA50),0) | E50: =SUMIFS('EXPENDITURE LOG'!$D$5:$D$504,'EXPENDITURE LOG'!$J$5:$J$504,$A50,'EXPENDITURE LOG'!$A$5:$A$504,">="&$C$4,'EXPENDITURE LOG'!$A$5:$A$504,"<"&EDATE($C$4,1)) | F50: =SUMIFS('EXPENDITURE LOG'!$D$5:$D$504,'EXPENDITURE LOG'!$J$5:$J$504,$A50,'EXPENDITURE LOG'!$A$5:$A$504,">="&$C$4,'EXPENDITURE LOG'!$A$5:$A$504,"<"&EDATE($C$4,1),'EXPENDITURE LOG'!$F$5:$F$504,"Church*") | G50: =E50-C50 | H50: =SUMIFS('EXPENDITURE LOG'!$D$5:$D$504,'EXPENDITURE LOG'!$J$5:$J$504,$A50,'EXPENDITURE LOG'!$A$5:$A$504,">="&'SUPPORT PLAN'!$C$4,'EXPENDITURE LOG'!$A$5:$A$504,"<"&EDATE($C$4,1)) | I50: =C50*MAX(0,$F$4) | J50: =H50-I50 | K50: =SUMIFS('EXPENDITURE LOG'!$D$5:$D$504,'EXPENDITURE LOG'!$J$5:$J$504,$A50)
A51: =EXPENSES!L49 | B51: =EXPENSES!B49 | C51: =EXPENSES!E49 | D51: =IF(AND($F$4>=1,$F$4<=3),CHOOSE($F$4,'SUPPORT PLAN'!$M51,'SUPPORT PLAN'!$T51,'SUPPORT PLAN'!$AA51),0) | E51: =SUMIFS('EXPENDITURE LOG'!$D$5:$D$504,'EXPENDITURE LOG'!$J$5:$J$504,$A51,'EXPENDITURE LOG'!$A$5:$A$504,">="&$C$4,'EXPENDITURE LOG'!$A$5:$A$504,"<"&EDATE($C$4,1)) | F51: =SUMIFS('EXPENDITURE LOG'!$D$5:$D$504,'EXPENDITURE LOG'!$J$5:$J$504,$A51,'EXPENDITURE LOG'!$A$5:$A$504,">="&$C$4,'EXPENDITURE LOG'!$A$5:$A$504,"<"&EDATE($C$4,1),'EXPENDITURE LOG'!$F$5:$F$504,"Church*") | G51: =E51-C51 | H51: =SUMIFS('EXPENDITURE LOG'!$D$5:$D$504,'EXPENDITURE LOG'!$J$5:$J$504,$A51,'EXPENDITURE LOG'!$A$5:$A$504,">="&'SUPPORT PLAN'!$C$4,'EXPENDITURE LOG'!$A$5:$A$504,"<"&EDATE($C$4,1)) | I51: =C51*MAX(0,$F$4) | J51: =H51-I51 | K51: =SUMIFS('EXPENDITURE LOG'!$D$5:$D$504,'EXPENDITURE LOG'!$J$5:$J$504,$A51)
A52: =EXPENSES!L50 | B52: =EXPENSES!B50 | C52: =EXPENSES!E50 | D52: =IF(AND($F$4>=1,$F$4<=3),CHOOSE($F$4,'SUPPORT PLAN'!$M52,'SUPPORT PLAN'!$T52,'SUPPORT PLAN'!$AA52),0) | E52: =SUMIFS('EXPENDITURE LOG'!$D$5:$D$504,'EXPENDITURE LOG'!$J$5:$J$504,$A52,'EXPENDITURE LOG'!$A$5:$A$504,">="&$C$4,'EXPENDITURE LOG'!$A$5:$A$504,"<"&EDATE($C$4,1)) | F52: =SUMIFS('EXPENDITURE LOG'!$D$5:$D$504,'EXPENDITURE LOG'!$J$5:$J$504,$A52,'EXPENDITURE LOG'!$A$5:$A$504,">="&$C$4,'EXPENDITURE LOG'!$A$5:$A$504,"<"&EDATE($C$4,1),'EXPENDITURE LOG'!$F$5:$F$504,"Church*") | G52: =E52-C52 | H52: =SUMIFS('EXPENDITURE LOG'!$D$5:$D$504,'EXPENDITURE LOG'!$J$5:$J$504,$A52,'EXPENDITURE LOG'!$A$5:$A$504,">="&'SUPPORT PLAN'!$C$4,'EXPENDITURE LOG'!$A$5:$A$504,"<"&EDATE($C$4,1)) | I52: =C52*MAX(0,$F$4) | J52: =H52-I52 | K52: =SUMIFS('EXPENDITURE LOG'!$D$5:$D$504,'EXPENDITURE LOG'!$J$5:$J$504,$A52)
B53: TRANSPORTATION | C53: =SUM(C54:C62) | D53: =SUM(D54:D62) | E53: =SUM(E54:E62) | F53: =SUM(F54:F62) | G53: =SUM(G54:G62) | H53: =SUM(H54:H62) | I53: =SUM(I54:I62) | J53: =SUM(J54:J62) | K53: =SUM(K54:K62)
A54: =EXPENSES!L52 | B54: =EXPENSES!B52 | C54: =EXPENSES!E52 | D54: =IF(AND($F$4>=1,$F$4<=3),CHOOSE($F$4,'SUPPORT PLAN'!$M54,'SUPPORT PLAN'!$T54,'SUPPORT PLAN'!$AA54),0) | E54: =SUMIFS('EXPENDITURE LOG'!$D$5:$D$504,'EXPENDITURE LOG'!$J$5:$J$504,$A54,'EXPENDITURE LOG'!$A$5:$A$504,">="&$C$4,'EXPENDITURE LOG'!$A$5:$A$504,"<"&EDATE($C$4,1)) | F54: =SUMIFS('EXPENDITURE LOG'!$D$5:$D$504,'EXPENDITURE LOG'!$J$5:$J$504,$A54,'EXPENDITURE LOG'!$A$5:$A$504,">="&$C$4,'EXPENDITURE LOG'!$A$5:$A$504,"<"&EDATE($C$4,1),'EXPENDITURE LOG'!$F$5:$F$504,"Church*") | G54: =E54-C54 | H54: =SUMIFS('EXPENDITURE LOG'!$D$5:$D$504,'EXPENDITURE LOG'!$J$5:$J$504,$A54,'EXPENDITURE LOG'!$A$5:$A$504,">="&'SUPPORT PLAN'!$C$4,'EXPENDITURE LOG'!$A$5:$A$504,"<"&EDATE($C$4,1)) | I54: =C54*MAX(0,$F$4) | J54: =H54-I54 | K54: =SUMIFS('EXPENDITURE LOG'!$D$5:$D$504,'EXPENDITURE LOG'!$J$5:$J$504,$A54)
A55: =EXPENSES!L53 | B55: =EXPENSES!B53 | C55: =EXPENSES!E53 | D55: =IF(AND($F$4>=1,$F$4<=3),CHOOSE($F$4,'SUPPORT PLAN'!$M55,'SUPPORT PLAN'!$T55,'SUPPORT PLAN'!$AA55),0) | E55: =SUMIFS('EXPENDITURE LOG'!$D$5:$D$504,'EXPENDITURE LOG'!$J$5:$J$504,$A55,'EXPENDITURE LOG'!$A$5:$A$504,">="&$C$4,'EXPENDITURE LOG'!$A$5:$A$504,"<"&EDATE($C$4,1)) | F55: =SUMIFS('EXPENDITURE LOG'!$D$5:$D$504,'EXPENDITURE LOG'!$J$5:$J$504,$A55,'EXPENDITURE LOG'!$A$5:$A$504,">="&$C$4,'EXPENDITURE LOG'!$A$5:$A$504,"<"&EDATE($C$4,1),'EXPENDITURE LOG'!$F$5:$F$504,"Church*") | G55: =E55-C55 | H55: =SUMIFS('EXPENDITURE LOG'!$D$5:$D$504,'EXPENDITURE LOG'!$J$5:$J$504,$A55,'EXPENDITURE LOG'!$A$5:$A$504,">="&'SUPPORT PLAN'!$C$4,'EXPENDITURE LOG'!$A$5:$A$504,"<"&EDATE($C$4,1)) | I55: =C55*MAX(0,$F$4) | J55: =H55-I55 | K55: =SUMIFS('EXPENDITURE LOG'!$D$5:$D$504,'EXPENDITURE LOG'!$J$5:$J$504,$A55)
A56: =EXPENSES!L54 | B56: =EXPENSES!B54 | C56: =EXPENSES!E54 | D56: =IF(AND($F$4>=1,$F$4<=3),CHOOSE($F$4,'SUPPORT PLAN'!$M56,'SUPPORT PLAN'!$T56,'SUPPORT PLAN'!$AA56),0) | E56: =SUMIFS('EXPENDITURE LOG'!$D$5:$D$504,'EXPENDITURE LOG'!$J$5:$J$504,$A56,'EXPENDITURE LOG'!$A$5:$A$504,">="&$C$4,'EXPENDITURE LOG'!$A$5:$A$504,"<"&EDATE($C$4,1)) | F56: =SUMIFS('EXPENDITURE LOG'!$D$5:$D$504,'EXPENDITURE LOG'!$J$5:$J$504,$A56,'EXPENDITURE LOG'!$A$5:$A$504,">="&$C$4,'EXPENDITURE LOG'!$A$5:$A$504,"<"&EDATE($C$4,1),'EXPENDITURE LOG'!$F$5:$F$504,"Church*") | G56: =E56-C56 | H56: =SUMIFS('EXPENDITURE LOG'!$D$5:$D$504,'EXPENDITURE LOG'!$J$5:$J$504,$A56,'EXPENDITURE LOG'!$A$5:$A$504,">="&'SUPPORT PLAN'!$C$4,'EXPENDITURE LOG'!$A$5:$A$504,"<"&EDATE($C$4,1)) | I56: =C56*MAX(0,$F$4) | J56: =H56-I56 | K56: =SUMIFS('EXPENDITURE LOG'!$D$5:$D$504,'EXPENDITURE LOG'!$J$5:$J$504,$A56)
A57: =EXPENSES!L55 | B57: =EXPENSES!B55 | C57: =EXPENSES!E55 | D57: =IF(AND($F$4>=1,$F$4<=3),CHOOSE($F$4,'SUPPORT PLAN'!$M57,'SUPPORT PLAN'!$T57,'SUPPORT PLAN'!$AA57),0) | E57: =SUMIFS('EXPENDITURE LOG'!$D$5:$D$504,'EXPENDITURE LOG'!$J$5:$J$504,$A57,'EXPENDITURE LOG'!$A$5:$A$504,">="&$C$4,'EXPENDITURE LOG'!$A$5:$A$504,"<"&EDATE($C$4,1)) | F57: =SUMIFS('EXPENDITURE LOG'!$D$5:$D$504,'EXPENDITURE LOG'!$J$5:$J$504,$A57,'EXPENDITURE LOG'!$A$5:$A$504,">="&$C$4,'EXPENDITURE LOG'!$A$5:$A$504,"<"&EDATE($C$4,1),'EXPENDITURE LOG'!$F$5:$F$504,"Church*") | G57: =E57-C57 | H57: =SUMIFS('EXPENDITURE LOG'!$D$5:$D$504,'EXPENDITURE LOG'!$J$5:$J$504,$A57,'EXPENDITURE LOG'!$A$5:$A$504,">="&'SUPPORT PLAN'!$C$4,'EXPENDITURE LOG'!$A$5:$A$504,"<"&EDATE($C$4,1)) | I57: =C57*MAX(0,$F$4) | J57: =H57-I57 | K57: =SUMIFS('EXPENDITURE LOG'!$D$5:$D$504,'EXPENDITURE LOG'!$J$5:$J$504,$A57)
A58: =EXPENSES!L56 | B58: =EXPENSES!B56 | C58: =EXPENSES!E56 | D58: =IF(AND($F$4>=1,$F$4<=3),CHOOSE($F$4,'SUPPORT PLAN'!$M58,'SUPPORT PLAN'!$T58,'SUPPORT PLAN'!$AA58),0) | E58: =SUMIFS('EXPENDITURE LOG'!$D$5:$D$504,'EXPENDITURE LOG'!$J$5:$J$504,$A58,'EXPENDITURE LOG'!$A$5:$A$504,">="&$C$4,'EXPENDITURE LOG'!$A$5:$A$504,"<"&EDATE($C$4,1)) | F58: =SUMIFS('EXPENDITURE LOG'!$D$5:$D$504,'EXPENDITURE LOG'!$J$5:$J$504,$A58,'EXPENDITURE LOG'!$A$5:$A$504,">="&$C$4,'EXPENDITURE LOG'!$A$5:$A$504,"<"&EDATE($C$4,1),'EXPENDITURE LOG'!$F$5:$F$504,"Church*") | G58: =E58-C58 | H58: =SUMIFS('EXPENDITURE LOG'!$D$5:$D$504,'EXPENDITURE LOG'!$J$5:$J$504,$A58,'EXPENDITURE LOG'!$A$5:$A$504,">="&'SUPPORT PLAN'!$C$4,'EXPENDITURE LOG'!$A$5:$A$504,"<"&EDATE($C$4,1)) | I58: =C58*MAX(0,$F$4) | J58: =H58-I58 | K58: =SUMIFS('EXPENDITURE LOG'!$D$5:$D$504,'EXPENDITURE LOG'!$J$5:$J$504,$A58)
A59: =EXPENSES!L57 | B59: =EXPENSES!B57 | C59: =EXPENSES!E57 | D59: =IF(AND($F$4>=1,$F$4<=3),CHOOSE($F$4,'SUPPORT PLAN'!$M59,'SUPPORT PLAN'!$T59,'SUPPORT PLAN'!$AA59),0) | E59: =SUMIFS('EXPENDITURE LOG'!$D$5:$D$504,'EXPENDITURE LOG'!$J$5:$J$504,$A59,'EXPENDITURE LOG'!$A$5:$A$504,">="&$C$4,'EXPENDITURE LOG'!$A$5:$A$504,"<"&EDATE($C$4,1)) | F59: =SUMIFS('EXPENDITURE LOG'!$D$5:$D$504,'EXPENDITURE LOG'!$J$5:$J$504,$A59,'EXPENDITURE LOG'!$A$5:$A$504,">="&$C$4,'EXPENDITURE LOG'!$A$5:$A$504,"<"&EDATE($C$4,1),'EXPENDITURE LOG'!$F$5:$F$504,"Church*") | G59: =E59-C59 | H59: =SUMIFS('EXPENDITURE LOG'!$D$5:$D$504,'EXPENDITURE LOG'!$J$5:$J$504,$A59,'EXPENDITURE LOG'!$A$5:$A$504,">="&'SUPPORT PLAN'!$C$4,'EXPENDITURE LOG'!$A$5:$A$504,"<"&EDATE($C$4,1)) | I59: =C59*MAX(0,$F$4) | J59: =H59-I59 | K59: =SUMIFS('EXPENDITURE LOG'!$D$5:$D$504,'EXPENDITURE LOG'!$J$5:$J$504,$A59)
A60: =EXPENSES!L58 | B60: =EXPENSES!B58 | C60: =EXPENSES!E58 | D60: =IF(AND($F$4>=1,$F$4<=3),CHOOSE($F$4,'SUPPORT PLAN'!$M60,'SUPPORT PLAN'!$T60,'SUPPORT PLAN'!$AA60),0) | E60: =SUMIFS('EXPENDITURE LOG'!$D$5:$D$504,'EXPENDITURE LOG'!$J$5:$J$504,$A60,'EXPENDITURE LOG'!$A$5:$A$504,">="&$C$4,'EXPENDITURE LOG'!$A$5:$A$504,"<"&EDATE($C$4,1)) | F60: =SUMIFS('EXPENDITURE LOG'!$D$5:$D$504,'EXPENDITURE LOG'!$J$5:$J$504,$A60,'EXPENDITURE LOG'!$A$5:$A$504,">="&$C$4,'EXPENDITURE LOG'!$A$5:$A$504,"<"&EDATE($C$4,1),'EXPENDITURE LOG'!$F$5:$F$504,"Church*") | G60: =E60-C60 | H60: =SUMIFS('EXPENDITURE LOG'!$D$5:$D$504,'EXPENDITURE LOG'!$J$5:$J$504,$A60,'EXPENDITURE LOG'!$A$5:$A$504,">="&'SUPPORT PLAN'!$C$4,'EXPENDITURE LOG'!$A$5:$A$504,"<"&EDATE($C$4,1)) | I60: =C60*MAX(0,$F$4) | J60: =H60-I60 | K60: =SUMIFS('EXPENDITURE LOG'!$D$5:$D$504,'EXPENDITURE LOG'!$J$5:$J$504,$A60)
A61: =EXPENSES!L59 | B61: =EXPENSES!B59 | C61: =EXPENSES!E59 | D61: =IF(AND($F$4>=1,$F$4<=3),CHOOSE($F$4,'SUPPORT PLAN'!$M61,'SUPPORT PLAN'!$T61,'SUPPORT PLAN'!$AA61),0) | E61: =SUMIFS('EXPENDITURE LOG'!$D$5:$D$504,'EXPENDITURE LOG'!$J$5:$J$504,$A61,'EXPENDITURE LOG'!$A$5:$A$504,">="&$C$4,'EXPENDITURE LOG'!$A$5:$A$504,"<"&EDATE($C$4,1)) | F61: =SUMIFS('EXPENDITURE LOG'!$D$5:$D$504,'EXPENDITURE LOG'!$J$5:$J$504,$A61,'EXPENDITURE LOG'!$A$5:$A$504,">="&$C$4,'EXPENDITURE LOG'!$A$5:$A$504,"<"&EDATE($C$4,1),'EXPENDITURE LOG'!$F$5:$F$504,"Church*") | G61: =E61-C61 | H61: =SUMIFS('EXPENDITURE LOG'!$D$5:$D$504,'EXPENDITURE LOG'!$J$5:$J$504,$A61,'EXPENDITURE LOG'!$A$5:$A$504,">="&'SUPPORT PLAN'!$C$4,'EXPENDITURE LOG'!$A$5:$A$504,"<"&EDATE($C$4,1)) | I61: =C61*MAX(0,$F$4) | J61: =H61-I61 | K61: =SUMIFS('EXPENDITURE LOG'!$D$5:$D$504,'EXPENDITURE LOG'!$J$5:$J$504,$A61)
A62: =EXPENSES!L60 | B62: =EXPENSES!B60 | C62: =EXPENSES!E60 | D62: =IF(AND($F$4>=1,$F$4<=3),CHOOSE($F$4,'SUPPORT PLAN'!$M62,'SUPPORT PLAN'!$T62,'SUPPORT PLAN'!$AA62),0) | E62: =SUMIFS('EXPENDITURE LOG'!$D$5:$D$504,'EXPENDITURE LOG'!$J$5:$J$504,$A62,'EXPENDITURE LOG'!$A$5:$A$504,">="&$C$4,'EXPENDITURE LOG'!$A$5:$A$504,"<"&EDATE($C$4,1)) | F62: =SUMIFS('EXPENDITURE LOG'!$D$5:$D$504,'EXPENDITURE LOG'!$J$5:$J$504,$A62,'EXPENDITURE LOG'!$A$5:$A$504,">="&$C$4,'EXPENDITURE LOG'!$A$5:$A$504,"<"&EDATE($C$4,1),'EXPENDITURE LOG'!$F$5:$F$504,"Church*") | G62: =E62-C62 | H62: =SUMIFS('EXPENDITURE LOG'!$D$5:$D$504,'EXPENDITURE LOG'!$J$5:$J$504,$A62,'EXPENDITURE LOG'!$A$5:$A$504,">="&'SUPPORT PLAN'!$C$4,'EXPENDITURE LOG'!$A$5:$A$504,"<"&EDATE($C$4,1)) | I62: =C62*MAX(0,$F$4) | J62: =H62-I62 | K62: =SUMIFS('EXPENDITURE LOG'!$D$5:$D$504,'EXPENDITURE LOG'!$J$5:$J$504,$A62)
B63: MEDICAL & HEALTH | C63: =SUM(C64:C72) | D63: =SUM(D64:D72) | E63: =SUM(E64:E72) | F63: =SUM(F64:F72) | G63: =SUM(G64:G72) | H63: =SUM(H64:H72) | I63: =SUM(I64:I72) | J63: =SUM(J64:J72) | K63: =SUM(K64:K72)
A64: =EXPENSES!L62 | B64: =EXPENSES!B62 | C64: =EXPENSES!E62 | D64: =IF(AND($F$4>=1,$F$4<=3),CHOOSE($F$4,'SUPPORT PLAN'!$M64,'SUPPORT PLAN'!$T64,'SUPPORT PLAN'!$AA64),0) | E64: =SUMIFS('EXPENDITURE LOG'!$D$5:$D$504,'EXPENDITURE LOG'!$J$5:$J$504,$A64,'EXPENDITURE LOG'!$A$5:$A$504,">="&$C$4,'EXPENDITURE LOG'!$A$5:$A$504,"<"&EDATE($C$4,1)) | F64: =SUMIFS('EXPENDITURE LOG'!$D$5:$D$504,'EXPENDITURE LOG'!$J$5:$J$504,$A64,'EXPENDITURE LOG'!$A$5:$A$504,">="&$C$4,'EXPENDITURE LOG'!$A$5:$A$504,"<"&EDATE($C$4,1),'EXPENDITURE LOG'!$F$5:$F$504,"Church*") | G64: =E64-C64 | H64: =SUMIFS('EXPENDITURE LOG'!$D$5:$D$504,'EXPENDITURE LOG'!$J$5:$J$504,$A64,'EXPENDITURE LOG'!$A$5:$A$504,">="&'SUPPORT PLAN'!$C$4,'EXPENDITURE LOG'!$A$5:$A$504,"<"&EDATE($C$4,1)) | I64: =C64*MAX(0,$F$4) | J64: =H64-I64 | K64: =SUMIFS('EXPENDITURE LOG'!$D$5:$D$504,'EXPENDITURE LOG'!$J$5:$J$504,$A64)
A65: =EXPENSES!L63 | B65: =EXPENSES!B63 | C65: =EXPENSES!E63 | D65: =IF(AND($F$4>=1,$F$4<=3),CHOOSE($F$4,'SUPPORT PLAN'!$M65,'SUPPORT PLAN'!$T65,'SUPPORT PLAN'!$AA65),0) | E65: =SUMIFS('EXPENDITURE LOG'!$D$5:$D$504,'EXPENDITURE LOG'!$J$5:$J$504,$A65,'EXPENDITURE LOG'!$A$5:$A$504,">="&$C$4,'EXPENDITURE LOG'!$A$5:$A$504,"<"&EDATE($C$4,1)) | F65: =SUMIFS('EXPENDITURE LOG'!$D$5:$D$504,'EXPENDITURE LOG'!$J$5:$J$504,$A65,'EXPENDITURE LOG'!$A$5:$A$504,">="&$C$4,'EXPENDITURE LOG'!$A$5:$A$504,"<"&EDATE($C$4,1),'EXPENDITURE LOG'!$F$5:$F$504,"Church*") | G65: =E65-C65 | H65: =SUMIFS('EXPENDITURE LOG'!$D$5:$D$504,'EXPENDITURE LOG'!$J$5:$J$504,$A65,'EXPENDITURE LOG'!$A$5:$A$504,">="&'SUPPORT PLAN'!$C$4,'EXPENDITURE LOG'!$A$5:$A$504,"<"&EDATE($C$4,1)) | I65: =C65*MAX(0,$F$4) | J65: =H65-I65 | K65: =SUMIFS('EXPENDITURE LOG'!$D$5:$D$504,'EXPENDITURE LOG'!$J$5:$J$504,$A65)
A66: =EXPENSES!L64 | B66: =EXPENSES!B64 | C66: =EXPENSES!E64 | D66: =IF(AND($F$4>=1,$F$4<=3),CHOOSE($F$4,'SUPPORT PLAN'!$M66,'SUPPORT PLAN'!$T66,'SUPPORT PLAN'!$AA66),0) | E66: =SUMIFS('EXPENDITURE LOG'!$D$5:$D$504,'EXPENDITURE LOG'!$J$5:$J$504,$A66,'EXPENDITURE LOG'!$A$5:$A$504,">="&$C$4,'EXPENDITURE LOG'!$A$5:$A$504,"<"&EDATE($C$4,1)) | F66: =SUMIFS('EXPENDITURE LOG'!$D$5:$D$504,'EXPENDITURE LOG'!$J$5:$J$504,$A66,'EXPENDITURE LOG'!$A$5:$A$504,">="&$C$4,'EXPENDITURE LOG'!$A$5:$A$504,"<"&EDATE($C$4,1),'EXPENDITURE LOG'!$F$5:$F$504,"Church*") | G66: =E66-C66 | H66: =SUMIFS('EXPENDITURE LOG'!$D$5:$D$504,'EXPENDITURE LOG'!$J$5:$J$504,$A66,'EXPENDITURE LOG'!$A$5:$A$504,">="&'SUPPORT PLAN'!$C$4,'EXPENDITURE LOG'!$A$5:$A$504,"<"&EDATE($C$4,1)) | I66: =C66*MAX(0,$F$4) | J66: =H66-I66 | K66: =SUMIFS('EXPENDITURE LOG'!$D$5:$D$504,'EXPENDITURE LOG'!$J$5:$J$504,$A66)
A67: =EXPENSES!L65 | B67: =EXPENSES!B65 | C67: =EXPENSES!E65 | D67: =IF(AND($F$4>=1,$F$4<=3),CHOOSE($F$4,'SUPPORT PLAN'!$M67,'SUPPORT PLAN'!$T67,'SUPPORT PLAN'!$AA67),0) | E67: =SUMIFS('EXPENDITURE LOG'!$D$5:$D$504,'EXPENDITURE LOG'!$J$5:$J$504,$A67,'EXPENDITURE LOG'!$A$5:$A$504,">="&$C$4,'EXPENDITURE LOG'!$A$5:$A$504,"<"&EDATE($C$4,1)) | F67: =SUMIFS('EXPENDITURE LOG'!$D$5:$D$504,'EXPENDITURE LOG'!$J$5:$J$504,$A67,'EXPENDITURE LOG'!$A$5:$A$504,">="&$C$4,'EXPENDITURE LOG'!$A$5:$A$504,"<"&EDATE($C$4,1),'EXPENDITURE LOG'!$F$5:$F$504,"Church*") | G67: =E67-C67 | H67: =SUMIFS('EXPENDITURE LOG'!$D$5:$D$504,'EXPENDITURE LOG'!$J$5:$J$504,$A67,'EXPENDITURE LOG'!$A$5:$A$504,">="&'SUPPORT PLAN'!$C$4,'EXPENDITURE LOG'!$A$5:$A$504,"<"&EDATE($C$4,1)) | I67: =C67*MAX(0,$F$4) | J67: =H67-I67 | K67: =SUMIFS('EXPENDITURE LOG'!$D$5:$D$504,'EXPENDITURE LOG'!$J$5:$J$504,$A67)
A68: =EXPENSES!L66 | B68: =EXPENSES!B66 | C68: =EXPENSES!E66 | D68: =IF(AND($F$4>=1,$F$4<=3),CHOOSE($F$4,'SUPPORT PLAN'!$M68,'SUPPORT PLAN'!$T68,'SUPPORT PLAN'!$AA68),0) | E68: =SUMIFS('EXPENDITURE LOG'!$D$5:$D$504,'EXPENDITURE LOG'!$J$5:$J$504,$A68,'EXPENDITURE LOG'!$A$5:$A$504,">="&$C$4,'EXPENDITURE LOG'!$A$5:$A$504,"<"&EDATE($C$4,1)) | F68: =SUMIFS('EXPENDITURE LOG'!$D$5:$D$504,'EXPENDITURE LOG'!$J$5:$J$504,$A68,'EXPENDITURE LOG'!$A$5:$A$504,">="&$C$4,'EXPENDITURE LOG'!$A$5:$A$504,"<"&EDATE($C$4,1),'EXPENDITURE LOG'!$F$5:$F$504,"Church*") | G68: =E68-C68 | H68: =SUMIFS('EXPENDITURE LOG'!$D$5:$D$504,'EXPENDITURE LOG'!$J$5:$J$504,$A68,'EXPENDITURE LOG'!$A$5:$A$504,">="&'SUPPORT PLAN'!$C$4,'EXPENDITURE LOG'!$A$5:$A$504,"<"&EDATE($C$4,1)) | I68: =C68*MAX(0,$F$4) | J68: =H68-I68 | K68: =SUMIFS('EXPENDITURE LOG'!$D$5:$D$504,'EXPENDITURE LOG'!$J$5:$J$504,$A68)
A69: =EXPENSES!L67 | B69: =EXPENSES!B67 | C69: =EXPENSES!E67 | D69: =IF(AND($F$4>=1,$F$4<=3),CHOOSE($F$4,'SUPPORT PLAN'!$M69,'SUPPORT PLAN'!$T69,'SUPPORT PLAN'!$AA69),0) | E69: =SUMIFS('EXPENDITURE LOG'!$D$5:$D$504,'EXPENDITURE LOG'!$J$5:$J$504,$A69,'EXPENDITURE LOG'!$A$5:$A$504,">="&$C$4,'EXPENDITURE LOG'!$A$5:$A$504,"<"&EDATE($C$4,1)) | F69: =SUMIFS('EXPENDITURE LOG'!$D$5:$D$504,'EXPENDITURE LOG'!$J$5:$J$504,$A69,'EXPENDITURE LOG'!$A$5:$A$504,">="&$C$4,'EXPENDITURE LOG'!$A$5:$A$504,"<"&EDATE($C$4,1),'EXPENDITURE LOG'!$F$5:$F$504,"Church*") | G69: =E69-C69 | H69: =SUMIFS('EXPENDITURE LOG'!$D$5:$D$504,'EXPENDITURE LOG'!$J$5:$J$504,$A69,'EXPENDITURE LOG'!$A$5:$A$504,">="&'SUPPORT PLAN'!$C$4,'EXPENDITURE LOG'!$A$5:$A$504,"<"&EDATE($C$4,1)) | I69: =C69*MAX(0,$F$4) | J69: =H69-I69 | K69: =SUMIFS('EXPENDITURE LOG'!$D$5:$D$504,'EXPENDITURE LOG'!$J$5:$J$504,$A69)
A70: =EXPENSES!L68 | B70: =EXPENSES!B68 | C70: =EXPENSES!E68 | D70: =IF(AND($F$4>=1,$F$4<=3),CHOOSE($F$4,'SUPPORT PLAN'!$M70,'SUPPORT PLAN'!$T70,'SUPPORT PLAN'!$AA70),0) | E70: =SUMIFS('EXPENDITURE LOG'!$D$5:$D$504,'EXPENDITURE LOG'!$J$5:$J$504,$A70,'EXPENDITURE LOG'!$A$5:$A$504,">="&$C$4,'EXPENDITURE LOG'!$A$5:$A$504,"<"&EDATE($C$4,1)) | F70: =SUMIFS('EXPENDITURE LOG'!$D$5:$D$504,'EXPENDITURE LOG'!$J$5:$J$504,$A70,'EXPENDITURE LOG'!$A$5:$A$504,">="&$C$4,'EXPENDITURE LOG'!$A$5:$A$504,"<"&EDATE($C$4,1),'EXPENDITURE LOG'!$F$5:$F$504,"Church*") | G70: =E70-C70 | H70: =SUMIFS('EXPENDITURE LOG'!$D$5:$D$504,'EXPENDITURE LOG'!$J$5:$J$504,$A70,'EXPENDITURE LOG'!$A$5:$A$504,">="&'SUPPORT PLAN'!$C$4,'EXPENDITURE LOG'!$A$5:$A$504,"<"&EDATE($C$4,1)) | I70: =C70*MAX(0,$F$4) | J70: =H70-I70 | K70: =SUMIFS('EXPENDITURE LOG'!$D$5:$D$504,'EXPENDITURE LOG'!$J$5:$J$504,$A70)
A71: =EXPENSES!L69 | B71: =EXPENSES!B69 | C71: =EXPENSES!E69 | D71: =IF(AND($F$4>=1,$F$4<=3),CHOOSE($F$4,'SUPPORT PLAN'!$M71,'SUPPORT PLAN'!$T71,'SUPPORT PLAN'!$AA71),0) | E71: =SUMIFS('EXPENDITURE LOG'!$D$5:$D$504,'EXPENDITURE LOG'!$J$5:$J$504,$A71,'EXPENDITURE LOG'!$A$5:$A$504,">="&$C$4,'EXPENDITURE LOG'!$A$5:$A$504,"<"&EDATE($C$4,1)) | F71: =SUMIFS('EXPENDITURE LOG'!$D$5:$D$504,'EXPENDITURE LOG'!$J$5:$J$504,$A71,'EXPENDITURE LOG'!$A$5:$A$504,">="&$C$4,'EXPENDITURE LOG'!$A$5:$A$504,"<"&EDATE($C$4,1),'EXPENDITURE LOG'!$F$5:$F$504,"Church*") | G71: =E71-C71 | H71: =SUMIFS('EXPENDITURE LOG'!$D$5:$D$504,'EXPENDITURE LOG'!$J$5:$J$504,$A71,'EXPENDITURE LOG'!$A$5:$A$504,">="&'SUPPORT PLAN'!$C$4,'EXPENDITURE LOG'!$A$5:$A$504,"<"&EDATE($C$4,1)) | I71: =C71*MAX(0,$F$4) | J71: =H71-I71 | K71: =SUMIFS('EXPENDITURE LOG'!$D$5:$D$504,'EXPENDITURE LOG'!$J$5:$J$504,$A71)
A72: =EXPENSES!L70 | B72: =EXPENSES!B70 | C72: =EXPENSES!E70 | D72: =IF(AND($F$4>=1,$F$4<=3),CHOOSE($F$4,'SUPPORT PLAN'!$M72,'SUPPORT PLAN'!$T72,'SUPPORT PLAN'!$AA72),0) | E72: =SUMIFS('EXPENDITURE LOG'!$D$5:$D$504,'EXPENDITURE LOG'!$J$5:$J$504,$A72,'EXPENDITURE LOG'!$A$5:$A$504,">="&$C$4,'EXPENDITURE LOG'!$A$5:$A$504,"<"&EDATE($C$4,1)) | F72: =SUMIFS('EXPENDITURE LOG'!$D$5:$D$504,'EXPENDITURE LOG'!$J$5:$J$504,$A72,'EXPENDITURE LOG'!$A$5:$A$504,">="&$C$4,'EXPENDITURE LOG'!$A$5:$A$504,"<"&EDATE($C$4,1),'EXPENDITURE LOG'!$F$5:$F$504,"Church*") | G72: =E72-C72 | H72: =SUMIFS('EXPENDITURE LOG'!$D$5:$D$504,'EXPENDITURE LOG'!$J$5:$J$504,$A72,'EXPENDITURE LOG'!$A$5:$A$504,">="&'SUPPORT PLAN'!$C$4,'EXPENDITURE LOG'!$A$5:$A$504,"<"&EDATE($C$4,1)) | I72: =C72*MAX(0,$F$4) | J72: =H72-I72 | K72: =SUMIFS('EXPENDITURE LOG'!$D$5:$D$504,'EXPENDITURE LOG'!$J$5:$J$504,$A72)
B73: CHILDCARE & DEPENDENTS | C73: =SUM(C74:C80) | D73: =SUM(D74:D80) | E73: =SUM(E74:E80) | F73: =SUM(F74:F80) | G73: =SUM(G74:G80) | H73: =SUM(H74:H80) | I73: =SUM(I74:I80) | J73: =SUM(J74:J80) | K73: =SUM(K74:K80)
A74: =EXPENSES!L72 | B74: =EXPENSES!B72 | C74: =EXPENSES!E72 | D74: =IF(AND($F$4>=1,$F$4<=3),CHOOSE($F$4,'SUPPORT PLAN'!$M74,'SUPPORT PLAN'!$T74,'SUPPORT PLAN'!$AA74),0) | E74: =SUMIFS('EXPENDITURE LOG'!$D$5:$D$504,'EXPENDITURE LOG'!$J$5:$J$504,$A74,'EXPENDITURE LOG'!$A$5:$A$504,">="&$C$4,'EXPENDITURE LOG'!$A$5:$A$504,"<"&EDATE($C$4,1)) | F74: =SUMIFS('EXPENDITURE LOG'!$D$5:$D$504,'EXPENDITURE LOG'!$J$5:$J$504,$A74,'EXPENDITURE LOG'!$A$5:$A$504,">="&$C$4,'EXPENDITURE LOG'!$A$5:$A$504,"<"&EDATE($C$4,1),'EXPENDITURE LOG'!$F$5:$F$504,"Church*") | G74: =E74-C74 | H74: =SUMIFS('EXPENDITURE LOG'!$D$5:$D$504,'EXPENDITURE LOG'!$J$5:$J$504,$A74,'EXPENDITURE LOG'!$A$5:$A$504,">="&'SUPPORT PLAN'!$C$4,'EXPENDITURE LOG'!$A$5:$A$504,"<"&EDATE($C$4,1)) | I74: =C74*MAX(0,$F$4) | J74: =H74-I74 | K74: =SUMIFS('EXPENDITURE LOG'!$D$5:$D$504,'EXPENDITURE LOG'!$J$5:$J$504,$A74)
A75: =EXPENSES!L73 | B75: =EXPENSES!B73 | C75: =EXPENSES!E73 | D75: =IF(AND($F$4>=1,$F$4<=3),CHOOSE($F$4,'SUPPORT PLAN'!$M75,'SUPPORT PLAN'!$T75,'SUPPORT PLAN'!$AA75),0) | E75: =SUMIFS('EXPENDITURE LOG'!$D$5:$D$504,'EXPENDITURE LOG'!$J$5:$J$504,$A75,'EXPENDITURE LOG'!$A$5:$A$504,">="&$C$4,'EXPENDITURE LOG'!$A$5:$A$504,"<"&EDATE($C$4,1)) | F75: =SUMIFS('EXPENDITURE LOG'!$D$5:$D$504,'EXPENDITURE LOG'!$J$5:$J$504,$A75,'EXPENDITURE LOG'!$A$5:$A$504,">="&$C$4,'EXPENDITURE LOG'!$A$5:$A$504,"<"&EDATE($C$4,1),'EXPENDITURE LOG'!$F$5:$F$504,"Church*") | G75: =E75-C75 | H75: =SUMIFS('EXPENDITURE LOG'!$D$5:$D$504,'EXPENDITURE LOG'!$J$5:$J$504,$A75,'EXPENDITURE LOG'!$A$5:$A$504,">="&'SUPPORT PLAN'!$C$4,'EXPENDITURE LOG'!$A$5:$A$504,"<"&EDATE($C$4,1)) | I75: =C75*MAX(0,$F$4) | J75: =H75-I75 | K75: =SUMIFS('EXPENDITURE LOG'!$D$5:$D$504,'EXPENDITURE LOG'!$J$5:$J$504,$A75)
A76: =EXPENSES!L74 | B76: =EXPENSES!B74 | C76: =EXPENSES!E74 | D76: =IF(AND($F$4>=1,$F$4<=3),CHOOSE($F$4,'SUPPORT PLAN'!$M76,'SUPPORT PLAN'!$T76,'SUPPORT PLAN'!$AA76),0) | E76: =SUMIFS('EXPENDITURE LOG'!$D$5:$D$504,'EXPENDITURE LOG'!$J$5:$J$504,$A76,'EXPENDITURE LOG'!$A$5:$A$504,">="&$C$4,'EXPENDITURE LOG'!$A$5:$A$504,"<"&EDATE($C$4,1)) | F76: =SUMIFS('EXPENDITURE LOG'!$D$5:$D$504,'EXPENDITURE LOG'!$J$5:$J$504,$A76,'EXPENDITURE LOG'!$A$5:$A$504,">="&$C$4,'EXPENDITURE LOG'!$A$5:$A$504,"<"&EDATE($C$4,1),'EXPENDITURE LOG'!$F$5:$F$504,"Church*") | G76: =E76-C76 | H76: =SUMIFS('EXPENDITURE LOG'!$D$5:$D$504,'EXPENDITURE LOG'!$J$5:$J$504,$A76,'EXPENDITURE LOG'!$A$5:$A$504,">="&'SUPPORT PLAN'!$C$4,'EXPENDITURE LOG'!$A$5:$A$504,"<"&EDATE($C$4,1)) | I76: =C76*MAX(0,$F$4) | J76: =H76-I76 | K76: =SUMIFS('EXPENDITURE LOG'!$D$5:$D$504,'EXPENDITURE LOG'!$J$5:$J$504,$A76)
A77: =EXPENSES!L75 | B77: =EXPENSES!B75 | C77: =EXPENSES!E75 | D77: =IF(AND($F$4>=1,$F$4<=3),CHOOSE($F$4,'SUPPORT PLAN'!$M77,'SUPPORT PLAN'!$T77,'SUPPORT PLAN'!$AA77),0) | E77: =SUMIFS('EXPENDITURE LOG'!$D$5:$D$504,'EXPENDITURE LOG'!$J$5:$J$504,$A77,'EXPENDITURE LOG'!$A$5:$A$504,">="&$C$4,'EXPENDITURE LOG'!$A$5:$A$504,"<"&EDATE($C$4,1)) | F77: =SUMIFS('EXPENDITURE LOG'!$D$5:$D$504,'EXPENDITURE LOG'!$J$5:$J$504,$A77,'EXPENDITURE LOG'!$A$5:$A$504,">="&$C$4,'EXPENDITURE LOG'!$A$5:$A$504,"<"&EDATE($C$4,1),'EXPENDITURE LOG'!$F$5:$F$504,"Church*") | G77: =E77-C77 | H77: =SUMIFS('EXPENDITURE LOG'!$D$5:$D$504,'EXPENDITURE LOG'!$J$5:$J$504,$A77,'EXPENDITURE LOG'!$A$5:$A$504,">="&'SUPPORT PLAN'!$C$4,'EXPENDITURE LOG'!$A$5:$A$504,"<"&EDATE($C$4,1)) | I77: =C77*MAX(0,$F$4) | J77: =H77-I77 | K77: =SUMIFS('EXPENDITURE LOG'!$D$5:$D$504,'EXPENDITURE LOG'!$J$5:$J$504,$A77)
A78: =EXPENSES!L76 | B78: =EXPENSES!B76 | C78: =EXPENSES!E76 | D78: =IF(AND($F$4>=1,$F$4<=3),CHOOSE($F$4,'SUPPORT PLAN'!$M78,'SUPPORT PLAN'!$T78,'SUPPORT PLAN'!$AA78),0) | E78: =SUMIFS('EXPENDITURE LOG'!$D$5:$D$504,'EXPENDITURE LOG'!$J$5:$J$504,$A78,'EXPENDITURE LOG'!$A$5:$A$504,">="&$C$4,'EXPENDITURE LOG'!$A$5:$A$504,"<"&EDATE($C$4,1)) | F78: =SUMIFS('EXPENDITURE LOG'!$D$5:$D$504,'EXPENDITURE LOG'!$J$5:$J$504,$A78,'EXPENDITURE LOG'!$A$5:$A$504,">="&$C$4,'EXPENDITURE LOG'!$A$5:$A$504,"<"&EDATE($C$4,1),'EXPENDITURE LOG'!$F$5:$F$504,"Church*") | G78: =E78-C78 | H78: =SUMIFS('EXPENDITURE LOG'!$D$5:$D$504,'EXPENDITURE LOG'!$J$5:$J$504,$A78,'EXPENDITURE LOG'!$A$5:$A$504,">="&'SUPPORT PLAN'!$C$4,'EXPENDITURE LOG'!$A$5:$A$504,"<"&EDATE($C$4,1)) | I78: =C78*MAX(0,$F$4) | J78: =H78-I78 | K78: =SUMIFS('EXPENDITURE LOG'!$D$5:$D$504,'EXPENDITURE LOG'!$J$5:$J$504,$A78)
A79: =EXPENSES!L77 | B79: =EXPENSES!B77 | C79: =EXPENSES!E77 | D79: =IF(AND($F$4>=1,$F$4<=3),CHOOSE($F$4,'SUPPORT PLAN'!$M79,'SUPPORT PLAN'!$T79,'SUPPORT PLAN'!$AA79),0) | E79: =SUMIFS('EXPENDITURE LOG'!$D$5:$D$504,'EXPENDITURE LOG'!$J$5:$J$504,$A79,'EXPENDITURE LOG'!$A$5:$A$504,">="&$C$4,'EXPENDITURE LOG'!$A$5:$A$504,"<"&EDATE($C$4,1)) | F79: =SUMIFS('EXPENDITURE LOG'!$D$5:$D$504,'EXPENDITURE LOG'!$J$5:$J$504,$A79,'EXPENDITURE LOG'!$A$5:$A$504,">="&$C$4,'EXPENDITURE LOG'!$A$5:$A$504,"<"&EDATE($C$4,1),'EXPENDITURE LOG'!$F$5:$F$504,"Church*") | G79: =E79-C79 | H79: =SUMIFS('EXPENDITURE LOG'!$D$5:$D$504,'EXPENDITURE LOG'!$J$5:$J$504,$A79,'EXPENDITURE LOG'!$A$5:$A$504,">="&'SUPPORT PLAN'!$C$4,'EXPENDITURE LOG'!$A$5:$A$504,"<"&EDATE($C$4,1)) | I79: =C79*MAX(0,$F$4) | J79: =H79-I79 | K79: =SUMIFS('EXPENDITURE LOG'!$D$5:$D$504,'EXPENDITURE LOG'!$J$5:$J$504,$A79)
A80: =EXPENSES!L78 | B80: =EXPENSES!B78 | C80: =EXPENSES!E78 | D80: =IF(AND($F$4>=1,$F$4<=3),CHOOSE($F$4,'SUPPORT PLAN'!$M80,'SUPPORT PLAN'!$T80,'SUPPORT PLAN'!$AA80),0) | E80: =SUMIFS('EXPENDITURE LOG'!$D$5:$D$504,'EXPENDITURE LOG'!$J$5:$J$504,$A80,'EXPENDITURE LOG'!$A$5:$A$504,">="&$C$4,'EXPENDITURE LOG'!$A$5:$A$504,"<"&EDATE($C$4,1)) | F80: =SUMIFS('EXPENDITURE LOG'!$D$5:$D$504,'EXPENDITURE LOG'!$J$5:$J$504,$A80,'EXPENDITURE LOG'!$A$5:$A$504,">="&$C$4,'EXPENDITURE LOG'!$A$5:$A$504,"<"&EDATE($C$4,1),'EXPENDITURE LOG'!$F$5:$F$504,"Church*") | G80: =E80-C80 | H80: =SUMIFS('EXPENDITURE LOG'!$D$5:$D$504,'EXPENDITURE LOG'!$J$5:$J$504,$A80,'EXPENDITURE LOG'!$A$5:$A$504,">="&'SUPPORT PLAN'!$C$4,'EXPENDITURE LOG'!$A$5:$A$504,"<"&EDATE($C$4,1)) | I80: =C80*MAX(0,$F$4) | J80: =H80-I80 | K80: =SUMIFS('EXPENDITURE LOG'!$D$5:$D$504,'EXPENDITURE LOG'!$J$5:$J$504,$A80)
B81: EDUCATION | C81: =SUM(C82:C87) | D81: =SUM(D82:D87) | E81: =SUM(E82:E87) | F81: =SUM(F82:F87) | G81: =SUM(G82:G87) | H81: =SUM(H82:H87) | I81: =SUM(I82:I87) | J81: =SUM(J82:J87) | K81: =SUM(K82:K87)
A82: =EXPENSES!L80 | B82: =EXPENSES!B80 | C82: =EXPENSES!E80 | D82: =IF(AND($F$4>=1,$F$4<=3),CHOOSE($F$4,'SUPPORT PLAN'!$M82,'SUPPORT PLAN'!$T82,'SUPPORT PLAN'!$AA82),0) | E82: =SUMIFS('EXPENDITURE LOG'!$D$5:$D$504,'EXPENDITURE LOG'!$J$5:$J$504,$A82,'EXPENDITURE LOG'!$A$5:$A$504,">="&$C$4,'EXPENDITURE LOG'!$A$5:$A$504,"<"&EDATE($C$4,1)) | F82: =SUMIFS('EXPENDITURE LOG'!$D$5:$D$504,'EXPENDITURE LOG'!$J$5:$J$504,$A82,'EXPENDITURE LOG'!$A$5:$A$504,">="&$C$4,'EXPENDITURE LOG'!$A$5:$A$504,"<"&EDATE($C$4,1),'EXPENDITURE LOG'!$F$5:$F$504,"Church*") | G82: =E82-C82 | H82: =SUMIFS('EXPENDITURE LOG'!$D$5:$D$504,'EXPENDITURE LOG'!$J$5:$J$504,$A82,'EXPENDITURE LOG'!$A$5:$A$504,">="&'SUPPORT PLAN'!$C$4,'EXPENDITURE LOG'!$A$5:$A$504,"<"&EDATE($C$4,1)) | I82: =C82*MAX(0,$F$4) | J82: =H82-I82 | K82: =SUMIFS('EXPENDITURE LOG'!$D$5:$D$504,'EXPENDITURE LOG'!$J$5:$J$504,$A82)
A83: =EXPENSES!L81 | B83: =EXPENSES!B81 | C83: =EXPENSES!E81 | D83: =IF(AND($F$4>=1,$F$4<=3),CHOOSE($F$4,'SUPPORT PLAN'!$M83,'SUPPORT PLAN'!$T83,'SUPPORT PLAN'!$AA83),0) | E83: =SUMIFS('EXPENDITURE LOG'!$D$5:$D$504,'EXPENDITURE LOG'!$J$5:$J$504,$A83,'EXPENDITURE LOG'!$A$5:$A$504,">="&$C$4,'EXPENDITURE LOG'!$A$5:$A$504,"<"&EDATE($C$4,1)) | F83: =SUMIFS('EXPENDITURE LOG'!$D$5:$D$504,'EXPENDITURE LOG'!$J$5:$J$504,$A83,'EXPENDITURE LOG'!$A$5:$A$504,">="&$C$4,'EXPENDITURE LOG'!$A$5:$A$504,"<"&EDATE($C$4,1),'EXPENDITURE LOG'!$F$5:$F$504,"Church*") | G83: =E83-C83 | H83: =SUMIFS('EXPENDITURE LOG'!$D$5:$D$504,'EXPENDITURE LOG'!$J$5:$J$504,$A83,'EXPENDITURE LOG'!$A$5:$A$504,">="&'SUPPORT PLAN'!$C$4,'EXPENDITURE LOG'!$A$5:$A$504,"<"&EDATE($C$4,1)) | I83: =C83*MAX(0,$F$4) | J83: =H83-I83 | K83: =SUMIFS('EXPENDITURE LOG'!$D$5:$D$504,'EXPENDITURE LOG'!$J$5:$J$504,$A83)
A84: =EXPENSES!L82 | B84: =EXPENSES!B82 | C84: =EXPENSES!E82 | D84: =IF(AND($F$4>=1,$F$4<=3),CHOOSE($F$4,'SUPPORT PLAN'!$M84,'SUPPORT PLAN'!$T84,'SUPPORT PLAN'!$AA84),0) | E84: =SUMIFS('EXPENDITURE LOG'!$D$5:$D$504,'EXPENDITURE LOG'!$J$5:$J$504,$A84,'EXPENDITURE LOG'!$A$5:$A$504,">="&$C$4,'EXPENDITURE LOG'!$A$5:$A$504,"<"&EDATE($C$4,1)) | F84: =SUMIFS('EXPENDITURE LOG'!$D$5:$D$504,'EXPENDITURE LOG'!$J$5:$J$504,$A84,'EXPENDITURE LOG'!$A$5:$A$504,">="&$C$4,'EXPENDITURE LOG'!$A$5:$A$504,"<"&EDATE($C$4,1),'EXPENDITURE LOG'!$F$5:$F$504,"Church*") | G84: =E84-C84 | H84: =SUMIFS('EXPENDITURE LOG'!$D$5:$D$504,'EXPENDITURE LOG'!$J$5:$J$504,$A84,'EXPENDITURE LOG'!$A$5:$A$504,">="&'SUPPORT PLAN'!$C$4,'EXPENDITURE LOG'!$A$5:$A$504,"<"&EDATE($C$4,1)) | I84: =C84*MAX(0,$F$4) | J84: =H84-I84 | K84: =SUMIFS('EXPENDITURE LOG'!$D$5:$D$504,'EXPENDITURE LOG'!$J$5:$J$504,$A84)
A85: =EXPENSES!L83 | B85: =EXPENSES!B83 | C85: =EXPENSES!E83 | D85: =IF(AND($F$4>=1,$F$4<=3),CHOOSE($F$4,'SUPPORT PLAN'!$M85,'SUPPORT PLAN'!$T85,'SUPPORT PLAN'!$AA85),0) | E85: =SUMIFS('EXPENDITURE LOG'!$D$5:$D$504,'EXPENDITURE LOG'!$J$5:$J$504,$A85,'EXPENDITURE LOG'!$A$5:$A$504,">="&$C$4,'EXPENDITURE LOG'!$A$5:$A$504,"<"&EDATE($C$4,1)) | F85: =SUMIFS('EXPENDITURE LOG'!$D$5:$D$504,'EXPENDITURE LOG'!$J$5:$J$504,$A85,'EXPENDITURE LOG'!$A$5:$A$504,">="&$C$4,'EXPENDITURE LOG'!$A$5:$A$504,"<"&EDATE($C$4,1),'EXPENDITURE LOG'!$F$5:$F$504,"Church*") | G85: =E85-C85 | H85: =SUMIFS('EXPENDITURE LOG'!$D$5:$D$504,'EXPENDITURE LOG'!$J$5:$J$504,$A85,'EXPENDITURE LOG'!$A$5:$A$504,">="&'SUPPORT PLAN'!$C$4,'EXPENDITURE LOG'!$A$5:$A$504,"<"&EDATE($C$4,1)) | I85: =C85*MAX(0,$F$4) | J85: =H85-I85 | K85: =SUMIFS('EXPENDITURE LOG'!$D$5:$D$504,'EXPENDITURE LOG'!$J$5:$J$504,$A85)
A86: =EXPENSES!L84 | B86: =EXPENSES!B84 | C86: =EXPENSES!E84 | D86: =IF(AND($F$4>=1,$F$4<=3),CHOOSE($F$4,'SUPPORT PLAN'!$M86,'SUPPORT PLAN'!$T86,'SUPPORT PLAN'!$AA86),0) | E86: =SUMIFS('EXPENDITURE LOG'!$D$5:$D$504,'EXPENDITURE LOG'!$J$5:$J$504,$A86,'EXPENDITURE LOG'!$A$5:$A$504,">="&$C$4,'EXPENDITURE LOG'!$A$5:$A$504,"<"&EDATE($C$4,1)) | F86: =SUMIFS('EXPENDITURE LOG'!$D$5:$D$504,'EXPENDITURE LOG'!$J$5:$J$504,$A86,'EXPENDITURE LOG'!$A$5:$A$504,">="&$C$4,'EXPENDITURE LOG'!$A$5:$A$504,"<"&EDATE($C$4,1),'EXPENDITURE LOG'!$F$5:$F$504,"Church*") | G86: =E86-C86 | H86: =SUMIFS('EXPENDITURE LOG'!$D$5:$D$504,'EXPENDITURE LOG'!$J$5:$J$504,$A86,'EXPENDITURE LOG'!$A$5:$A$504,">="&'SUPPORT PLAN'!$C$4,'EXPENDITURE LOG'!$A$5:$A$504,"<"&EDATE($C$4,1)) | I86: =C86*MAX(0,$F$4) | J86: =H86-I86 | K86: =SUMIFS('EXPENDITURE LOG'!$D$5:$D$504,'EXPENDITURE LOG'!$J$5:$J$504,$A86)
A87: =EXPENSES!L85 | B87: =EXPENSES!B85 | C87: =EXPENSES!E85 | D87: =IF(AND($F$4>=1,$F$4<=3),CHOOSE($F$4,'SUPPORT PLAN'!$M87,'SUPPORT PLAN'!$T87,'SUPPORT PLAN'!$AA87),0) | E87: =SUMIFS('EXPENDITURE LOG'!$D$5:$D$504,'EXPENDITURE LOG'!$J$5:$J$504,$A87,'EXPENDITURE LOG'!$A$5:$A$504,">="&$C$4,'EXPENDITURE LOG'!$A$5:$A$504,"<"&EDATE($C$4,1)) | F87: =SUMIFS('EXPENDITURE LOG'!$D$5:$D$504,'EXPENDITURE LOG'!$J$5:$J$504,$A87,'EXPENDITURE LOG'!$A$5:$A$504,">="&$C$4,'EXPENDITURE LOG'!$A$5:$A$504,"<"&EDATE($C$4,1),'EXPENDITURE LOG'!$F$5:$F$504,"Church*") | G87: =E87-C87 | H87: =SUMIFS('EXPENDITURE LOG'!$D$5:$D$504,'EXPENDITURE LOG'!$J$5:$J$504,$A87,'EXPENDITURE LOG'!$A$5:$A$504,">="&'SUPPORT PLAN'!$C$4,'EXPENDITURE LOG'!$A$5:$A$504,"<"&EDATE($C$4,1)) | I87: =C87*MAX(0,$F$4) | J87: =H87-I87 | K87: =SUMIFS('EXPENDITURE LOG'!$D$5:$D$504,'EXPENDITURE LOG'!$J$5:$J$504,$A87)
B88: DEBT PAYMENTS | C88: =SUM(C89:C89) | D88: =SUM(D89:D89) | E88: =SUM(E89:E89) | F88: =SUM(F89:F89) | G88: =SUM(G89:G89) | H88: =SUM(H89:H89) | I88: =SUM(I89:I89) | J88: =SUM(J89:J89) | K88: =SUM(K89:K89)
A89: =EXPENSES!L87 | B89: =EXPENSES!B87 | C89: =EXPENSES!E87 | D89: =IF(AND($F$4>=1,$F$4<=3),CHOOSE($F$4,'SUPPORT PLAN'!$M89,'SUPPORT PLAN'!$T89,'SUPPORT PLAN'!$AA89),0) | E89: =SUMIFS('EXPENDITURE LOG'!$D$5:$D$504,'EXPENDITURE LOG'!$J$5:$J$504,$A89,'EXPENDITURE LOG'!$A$5:$A$504,">="&$C$4,'EXPENDITURE LOG'!$A$5:$A$504,"<"&EDATE($C$4,1)) | F89: =SUMIFS('EXPENDITURE LOG'!$D$5:$D$504,'EXPENDITURE LOG'!$J$5:$J$504,$A89,'EXPENDITURE LOG'!$A$5:$A$504,">="&$C$4,'EXPENDITURE LOG'!$A$5:$A$504,"<"&EDATE($C$4,1),'EXPENDITURE LOG'!$F$5:$F$504,"Church*") | G89: =E89-C89 | H89: =SUMIFS('EXPENDITURE LOG'!$D$5:$D$504,'EXPENDITURE LOG'!$J$5:$J$504,$A89,'EXPENDITURE LOG'!$A$5:$A$504,">="&'SUPPORT PLAN'!$C$4,'EXPENDITURE LOG'!$A$5:$A$504,"<"&EDATE($C$4,1)) | I89: =C89*MAX(0,$F$4) | J89: =H89-I89 | K89: =SUMIFS('EXPENDITURE LOG'!$D$5:$D$504,'EXPENDITURE LOG'!$J$5:$J$504,$A89)
B90: LEGAL & GOVERNMENT | C90: =SUM(C91:C95) | D90: =SUM(D91:D95) | E90: =SUM(E91:E95) | F90: =SUM(F91:F95) | G90: =SUM(G91:G95) | H90: =SUM(H91:H95) | I90: =SUM(I91:I95) | J90: =SUM(J91:J95) | K90: =SUM(K91:K95)
A91: =EXPENSES!L89 | B91: =EXPENSES!B89 | C91: =EXPENSES!E89 | D91: =IF(AND($F$4>=1,$F$4<=3),CHOOSE($F$4,'SUPPORT PLAN'!$M91,'SUPPORT PLAN'!$T91,'SUPPORT PLAN'!$AA91),0) | E91: =SUMIFS('EXPENDITURE LOG'!$D$5:$D$504,'EXPENDITURE LOG'!$J$5:$J$504,$A91,'EXPENDITURE LOG'!$A$5:$A$504,">="&$C$4,'EXPENDITURE LOG'!$A$5:$A$504,"<"&EDATE($C$4,1)) | F91: =SUMIFS('EXPENDITURE LOG'!$D$5:$D$504,'EXPENDITURE LOG'!$J$5:$J$504,$A91,'EXPENDITURE LOG'!$A$5:$A$504,">="&$C$4,'EXPENDITURE LOG'!$A$5:$A$504,"<"&EDATE($C$4,1),'EXPENDITURE LOG'!$F$5:$F$504,"Church*") | G91: =E91-C91 | H91: =SUMIFS('EXPENDITURE LOG'!$D$5:$D$504,'EXPENDITURE LOG'!$J$5:$J$504,$A91,'EXPENDITURE LOG'!$A$5:$A$504,">="&'SUPPORT PLAN'!$C$4,'EXPENDITURE LOG'!$A$5:$A$504,"<"&EDATE($C$4,1)) | I91: =C91*MAX(0,$F$4) | J91: =H91-I91 | K91: =SUMIFS('EXPENDITURE LOG'!$D$5:$D$504,'EXPENDITURE LOG'!$J$5:$J$504,$A91)
A92: =EXPENSES!L90 | B92: =EXPENSES!B90 | C92: =EXPENSES!E90 | D92: =IF(AND($F$4>=1,$F$4<=3),CHOOSE($F$4,'SUPPORT PLAN'!$M92,'SUPPORT PLAN'!$T92,'SUPPORT PLAN'!$AA92),0) | E92: =SUMIFS('EXPENDITURE LOG'!$D$5:$D$504,'EXPENDITURE LOG'!$J$5:$J$504,$A92,'EXPENDITURE LOG'!$A$5:$A$504,">="&$C$4,'EXPENDITURE LOG'!$A$5:$A$504,"<"&EDATE($C$4,1)) | F92: =SUMIFS('EXPENDITURE LOG'!$D$5:$D$504,'EXPENDITURE LOG'!$J$5:$J$504,$A92,'EXPENDITURE LOG'!$A$5:$A$504,">="&$C$4,'EXPENDITURE LOG'!$A$5:$A$504,"<"&EDATE($C$4,1),'EXPENDITURE LOG'!$F$5:$F$504,"Church*") | G92: =E92-C92 | H92: =SUMIFS('EXPENDITURE LOG'!$D$5:$D$504,'EXPENDITURE LOG'!$J$5:$J$504,$A92,'EXPENDITURE LOG'!$A$5:$A$504,">="&'SUPPORT PLAN'!$C$4,'EXPENDITURE LOG'!$A$5:$A$504,"<"&EDATE($C$4,1)) | I92: =C92*MAX(0,$F$4) | J92: =H92-I92 | K92: =SUMIFS('EXPENDITURE LOG'!$D$5:$D$504,'EXPENDITURE LOG'!$J$5:$J$504,$A92)
A93: =EXPENSES!L91 | B93: =EXPENSES!B91 | C93: =EXPENSES!E91 | D93: =IF(AND($F$4>=1,$F$4<=3),CHOOSE($F$4,'SUPPORT PLAN'!$M93,'SUPPORT PLAN'!$T93,'SUPPORT PLAN'!$AA93),0) | E93: =SUMIFS('EXPENDITURE LOG'!$D$5:$D$504,'EXPENDITURE LOG'!$J$5:$J$504,$A93,'EXPENDITURE LOG'!$A$5:$A$504,">="&$C$4,'EXPENDITURE LOG'!$A$5:$A$504,"<"&EDATE($C$4,1)) | F93: =SUMIFS('EXPENDITURE LOG'!$D$5:$D$504,'EXPENDITURE LOG'!$J$5:$J$504,$A93,'EXPENDITURE LOG'!$A$5:$A$504,">="&$C$4,'EXPENDITURE LOG'!$A$5:$A$504,"<"&EDATE($C$4,1),'EXPENDITURE LOG'!$F$5:$F$504,"Church*") | G93: =E93-C93 | H93: =SUMIFS('EXPENDITURE LOG'!$D$5:$D$504,'EXPENDITURE LOG'!$J$5:$J$504,$A93,'EXPENDITURE LOG'!$A$5:$A$504,">="&'SUPPORT PLAN'!$C$4,'EXPENDITURE LOG'!$A$5:$A$504,"<"&EDATE($C$4,1)) | I93: =C93*MAX(0,$F$4) | J93: =H93-I93 | K93: =SUMIFS('EXPENDITURE LOG'!$D$5:$D$504,'EXPENDITURE LOG'!$J$5:$J$504,$A93)
A94: =EXPENSES!L92 | B94: =EXPENSES!B92 | C94: =EXPENSES!E92 | D94: =IF(AND($F$4>=1,$F$4<=3),CHOOSE($F$4,'SUPPORT PLAN'!$M94,'SUPPORT PLAN'!$T94,'SUPPORT PLAN'!$AA94),0) | E94: =SUMIFS('EXPENDITURE LOG'!$D$5:$D$504,'EXPENDITURE LOG'!$J$5:$J$504,$A94,'EXPENDITURE LOG'!$A$5:$A$504,">="&$C$4,'EXPENDITURE LOG'!$A$5:$A$504,"<"&EDATE($C$4,1)) | F94: =SUMIFS('EXPENDITURE LOG'!$D$5:$D$504,'EXPENDITURE LOG'!$J$5:$J$504,$A94,'EXPENDITURE LOG'!$A$5:$A$504,">="&$C$4,'EXPENDITURE LOG'!$A$5:$A$504,"<"&EDATE($C$4,1),'EXPENDITURE LOG'!$F$5:$F$504,"Church*") | G94: =E94-C94 | H94: =SUMIFS('EXPENDITURE LOG'!$D$5:$D$504,'EXPENDITURE LOG'!$J$5:$J$504,$A94,'EXPENDITURE LOG'!$A$5:$A$504,">="&'SUPPORT PLAN'!$C$4,'EXPENDITURE LOG'!$A$5:$A$504,"<"&EDATE($C$4,1)) | I94: =C94*MAX(0,$F$4) | J94: =H94-I94 | K94: =SUMIFS('EXPENDITURE LOG'!$D$5:$D$504,'EXPENDITURE LOG'!$J$5:$J$504,$A94)
A95: =EXPENSES!L93 | B95: =EXPENSES!B93 | C95: =EXPENSES!E93 | D95: =IF(AND($F$4>=1,$F$4<=3),CHOOSE($F$4,'SUPPORT PLAN'!$M95,'SUPPORT PLAN'!$T95,'SUPPORT PLAN'!$AA95),0) | E95: =SUMIFS('EXPENDITURE LOG'!$D$5:$D$504,'EXPENDITURE LOG'!$J$5:$J$504,$A95,'EXPENDITURE LOG'!$A$5:$A$504,">="&$C$4,'EXPENDITURE LOG'!$A$5:$A$504,"<"&EDATE($C$4,1)) | F95: =SUMIFS('EXPENDITURE LOG'!$D$5:$D$504,'EXPENDITURE LOG'!$J$5:$J$504,$A95,'EXPENDITURE LOG'!$A$5:$A$504,">="&$C$4,'EXPENDITURE LOG'!$A$5:$A$504,"<"&EDATE($C$4,1),'EXPENDITURE LOG'!$F$5:$F$504,"Church*") | G95: =E95-C95 | H95: =SUMIFS('EXPENDITURE LOG'!$D$5:$D$504,'EXPENDITURE LOG'!$J$5:$J$504,$A95,'EXPENDITURE LOG'!$A$5:$A$504,">="&'SUPPORT PLAN'!$C$4,'EXPENDITURE LOG'!$A$5:$A$504,"<"&EDATE($C$4,1)) | I95: =C95*MAX(0,$F$4) | J95: =H95-I95 | K95: =SUMIFS('EXPENDITURE LOG'!$D$5:$D$504,'EXPENDITURE LOG'!$J$5:$J$504,$A95)
B96: PETS | C96: =SUM(C97:C100) | D96: =SUM(D97:D100) | E96: =SUM(E97:E100) | F96: =SUM(F97:F100) | G96: =SUM(G97:G100) | H96: =SUM(H97:H100) | I96: =SUM(I97:I100) | J96: =SUM(J97:J100) | K96: =SUM(K97:K100)
A97: =EXPENSES!L95 | B97: =EXPENSES!B95 | C97: =EXPENSES!E95 | D97: =IF(AND($F$4>=1,$F$4<=3),CHOOSE($F$4,'SUPPORT PLAN'!$M97,'SUPPORT PLAN'!$T97,'SUPPORT PLAN'!$AA97),0) | E97: =SUMIFS('EXPENDITURE LOG'!$D$5:$D$504,'EXPENDITURE LOG'!$J$5:$J$504,$A97,'EXPENDITURE LOG'!$A$5:$A$504,">="&$C$4,'EXPENDITURE LOG'!$A$5:$A$504,"<"&EDATE($C$4,1)) | F97: =SUMIFS('EXPENDITURE LOG'!$D$5:$D$504,'EXPENDITURE LOG'!$J$5:$J$504,$A97,'EXPENDITURE LOG'!$A$5:$A$504,">="&$C$4,'EXPENDITURE LOG'!$A$5:$A$504,"<"&EDATE($C$4,1),'EXPENDITURE LOG'!$F$5:$F$504,"Church*") | G97: =E97-C97 | H97: =SUMIFS('EXPENDITURE LOG'!$D$5:$D$504,'EXPENDITURE LOG'!$J$5:$J$504,$A97,'EXPENDITURE LOG'!$A$5:$A$504,">="&'SUPPORT PLAN'!$C$4,'EXPENDITURE LOG'!$A$5:$A$504,"<"&EDATE($C$4,1)) | I97: =C97*MAX(0,$F$4) | J97: =H97-I97 | K97: =SUMIFS('EXPENDITURE LOG'!$D$5:$D$504,'EXPENDITURE LOG'!$J$5:$J$504,$A97)
A98: =EXPENSES!L96 | B98: =EXPENSES!B96 | C98: =EXPENSES!E96 | D98: =IF(AND($F$4>=1,$F$4<=3),CHOOSE($F$4,'SUPPORT PLAN'!$M98,'SUPPORT PLAN'!$T98,'SUPPORT PLAN'!$AA98),0) | E98: =SUMIFS('EXPENDITURE LOG'!$D$5:$D$504,'EXPENDITURE LOG'!$J$5:$J$504,$A98,'EXPENDITURE LOG'!$A$5:$A$504,">="&$C$4,'EXPENDITURE LOG'!$A$5:$A$504,"<"&EDATE($C$4,1)) | F98: =SUMIFS('EXPENDITURE LOG'!$D$5:$D$504,'EXPENDITURE LOG'!$J$5:$J$504,$A98,'EXPENDITURE LOG'!$A$5:$A$504,">="&$C$4,'EXPENDITURE LOG'!$A$5:$A$504,"<"&EDATE($C$4,1),'EXPENDITURE LOG'!$F$5:$F$504,"Church*") | G98: =E98-C98 | H98: =SUMIFS('EXPENDITURE LOG'!$D$5:$D$504,'EXPENDITURE LOG'!$J$5:$J$504,$A98,'EXPENDITURE LOG'!$A$5:$A$504,">="&'SUPPORT PLAN'!$C$4,'EXPENDITURE LOG'!$A$5:$A$504,"<"&EDATE($C$4,1)) | I98: =C98*MAX(0,$F$4) | J98: =H98-I98 | K98: =SUMIFS('EXPENDITURE LOG'!$D$5:$D$504,'EXPENDITURE LOG'!$J$5:$J$504,$A98)
A99: =EXPENSES!L97 | B99: =EXPENSES!B97 | C99: =EXPENSES!E97 | D99: =IF(AND($F$4>=1,$F$4<=3),CHOOSE($F$4,'SUPPORT PLAN'!$M99,'SUPPORT PLAN'!$T99,'SUPPORT PLAN'!$AA99),0) | E99: =SUMIFS('EXPENDITURE LOG'!$D$5:$D$504,'EXPENDITURE LOG'!$J$5:$J$504,$A99,'EXPENDITURE LOG'!$A$5:$A$504,">="&$C$4,'EXPENDITURE LOG'!$A$5:$A$504,"<"&EDATE($C$4,1)) | F99: =SUMIFS('EXPENDITURE LOG'!$D$5:$D$504,'EXPENDITURE LOG'!$J$5:$J$504,$A99,'EXPENDITURE LOG'!$A$5:$A$504,">="&$C$4,'EXPENDITURE LOG'!$A$5:$A$504,"<"&EDATE($C$4,1),'EXPENDITURE LOG'!$F$5:$F$504,"Church*") | G99: =E99-C99 | H99: =SUMIFS('EXPENDITURE LOG'!$D$5:$D$504,'EXPENDITURE LOG'!$J$5:$J$504,$A99,'EXPENDITURE LOG'!$A$5:$A$504,">="&'SUPPORT PLAN'!$C$4,'EXPENDITURE LOG'!$A$5:$A$504,"<"&EDATE($C$4,1)) | I99: =C99*MAX(0,$F$4) | J99: =H99-I99 | K99: =SUMIFS('EXPENDITURE LOG'!$D$5:$D$504,'EXPENDITURE LOG'!$J$5:$J$504,$A99)
A100: =EXPENSES!L98 | B100: =EXPENSES!B98 | C100: =EXPENSES!E98 | D100: =IF(AND($F$4>=1,$F$4<=3),CHOOSE($F$4,'SUPPORT PLAN'!$M100,'SUPPORT PLAN'!$T100,'SUPPORT PLAN'!$AA100),0) | E100: =SUMIFS('EXPENDITURE LOG'!$D$5:$D$504,'EXPENDITURE LOG'!$J$5:$J$504,$A100,'EXPENDITURE LOG'!$A$5:$A$504,">="&$C$4,'EXPENDITURE LOG'!$A$5:$A$504,"<"&EDATE($C$4,1)) | F100: =SUMIFS('EXPENDITURE LOG'!$D$5:$D$504,'EXPENDITURE LOG'!$J$5:$J$504,$A100,'EXPENDITURE LOG'!$A$5:$A$504,">="&$C$4,'EXPENDITURE LOG'!$A$5:$A$504,"<"&EDATE($C$4,1),'EXPENDITURE LOG'!$F$5:$F$504,"Church*") | G100: =E100-C100 | H100: =SUMIFS('EXPENDITURE LOG'!$D$5:$D$504,'EXPENDITURE LOG'!$J$5:$J$504,$A100,'EXPENDITURE LOG'!$A$5:$A$504,">="&'SUPPORT PLAN'!$C$4,'EXPENDITURE LOG'!$A$5:$A$504,"<"&EDATE($C$4,1)) | I100: =C100*MAX(0,$F$4) | J100: =H100-I100 | K100: =SUMIFS('EXPENDITURE LOG'!$D$5:$D$504,'EXPENDITURE LOG'!$J$5:$J$504,$A100)
B101: SUBSCRIPTIONS & MEMBERSHIPS | C101: =SUM(C102:C107) | D101: =SUM(D102:D107) | E101: =SUM(E102:E107) | F101: =SUM(F102:F107) | G101: =SUM(G102:G107) | H101: =SUM(H102:H107) | I101: =SUM(I102:I107) | J101: =SUM(J102:J107) | K101: =SUM(K102:K107)
A102: =EXPENSES!L100 | B102: =EXPENSES!B100 | C102: =EXPENSES!E100 | D102: =IF(AND($F$4>=1,$F$4<=3),CHOOSE($F$4,'SUPPORT PLAN'!$M102,'SUPPORT PLAN'!$T102,'SUPPORT PLAN'!$AA102),0) | E102: =SUMIFS('EXPENDITURE LOG'!$D$5:$D$504,'EXPENDITURE LOG'!$J$5:$J$504,$A102,'EXPENDITURE LOG'!$A$5:$A$504,">="&$C$4,'EXPENDITURE LOG'!$A$5:$A$504,"<"&EDATE($C$4,1)) | F102: =SUMIFS('EXPENDITURE LOG'!$D$5:$D$504,'EXPENDITURE LOG'!$J$5:$J$504,$A102,'EXPENDITURE LOG'!$A$5:$A$504,">="&$C$4,'EXPENDITURE LOG'!$A$5:$A$504,"<"&EDATE($C$4,1),'EXPENDITURE LOG'!$F$5:$F$504,"Church*") | G102: =E102-C102 | H102: =SUMIFS('EXPENDITURE LOG'!$D$5:$D$504,'EXPENDITURE LOG'!$J$5:$J$504,$A102,'EXPENDITURE LOG'!$A$5:$A$504,">="&'SUPPORT PLAN'!$C$4,'EXPENDITURE LOG'!$A$5:$A$504,"<"&EDATE($C$4,1)) | I102: =C102*MAX(0,$F$4) | J102: =H102-I102 | K102: =SUMIFS('EXPENDITURE LOG'!$D$5:$D$504,'EXPENDITURE LOG'!$J$5:$J$504,$A102)
...

Sheet NOTES
A1: DISCUSSION NOTES
A13: ACTION ITEMS
A24: CASH ON HAND/SAVINGS

Sheet LISTS
A1: Frequency | B1: Monthly factor | D1: Expense type | F1: Form line (expenses) | H1: Form line (income) | J1: Expense line (for log) | L1: Months | N1: Paid by | P1: Payment method | T1: Access (liquid funds)
A2: Weekly | B2: 4.333333 | D2: Essential | F2: Tithes, offerings | H2: Income from all household members | J2: =EXPENSES!L6&" - "&EXPENSES!B6 | L2: =EDATE('SUPPORT PLAN'!$C$4,0) | N2: Member | P2: Cash | T2: Immediate
A3: Biweekly | B3: 2.166667 | D3: Important | F3: Food | H3: Other financial sources (family, others) | J3: =EXPENSES!L7&" - "&EXPENSES!B7 | L3: =EDATE('SUPPORT PLAN'!$C$4,1) | N3: Church assistance (fast offering) | P3: Debit card | T3: Within 30 days
A4: Semi-monthly | B4: 2 | D4: Discretionary | F4: Housing | H4: Government assistance | J4: =EXPENSES!L8&" - "&EXPENSES!B8 | L4: =EDATE('SUPPORT PLAN'!$C$4,2) | N4: Family / friends | P4: Credit card | T4: Penalty / tax to withdraw
A5: Monthly | B5: 1 | F5: Water | J5: =EXPENSES!L9&" - "&EXPENSES!B9 | L5: =EDATE('SUPPORT PLAN'!$C$4,3) | N5: Government program | P5: Check | T5: Not accessible
A6: Quarterly | B6: 0.333333 | F6: Medical | J6: =EXPENSES!L10&" - "&EXPENSES!B10 | L6: =EDATE('SUPPORT PLAN'!$C$4,4) | N6: Other | P6: Bishop's order / direct vendor payment
A7: Semi-annual | B7: 0.166667 | F7: Transportation | J7: =EXPENSES!L12&" - "&EXPENSES!B12 | L7: =EDATE('SUPPORT PLAN'!$C$4,5) | P7: Electronic transfer
A8: Annual | B8: 0.083333 | F8: Education | J8: =EXPENSES!L13&" - "&EXPENSES!B13 | L8: =EDATE('SUPPORT PLAN'!$C$4,6) | P8: Other
F9: Debt payments | J9: =EXPENSES!L14&" - "&EXPENSES!B14 | L9: =EDATE('SUPPORT PLAN'!$C$4,7)
A10: Factors: weekly = 52/12, biweekly = 26/12, annual = 1/12 (standard conversions). | F10: Clothing | J10: =EXPENSES!L15&" - "&EXPENSES!B15 | L10: =EDATE('SUPPORT PLAN'!$C$4,8)
F11: Electricity, fuel | J11: =EXPENSES!L16&" - "&EXPENSES!B16 | L11: =EDATE('SUPPORT PLAN'!$C$4,9)
F12: Other | J12: =EXPENSES!L17&" - "&EXPENSES!B17 | L12: =EDATE('SUPPORT PLAN'!$C$4,10)
J13: =EXPENSES!L18&" - "&EXPENSES!B18 | L13: =EDATE('SUPPORT PLAN'!$C$4,11)
J14: =EXPENSES!L19&" - "&EXPENSES!B19 | L14: =EDATE('SUPPORT PLAN'!$C$4,12)
J15: =EXPENSES!L21&" - "&EXPENSES!B21 | L15: =EDATE('SUPPORT PLAN'!$C$4,13)
J16: =EXPENSES!L22&" - "&EXPENSES!B22 | L16: =EDATE('SUPPORT PLAN'!$C$4,14)
J17: =EXPENSES!L23&" - "&EXPENSES!B23 | L17: =EDATE('SUPPORT PLAN'!$C$4,15)
J18: =EXPENSES!L24&" - "&EXPENSES!B24 | L18: =EDATE('SUPPORT PLAN'!$C$4,16)
J19: =EXPENSES!L25&" - "&EXPENSES!B25 | L19: =EDATE('SUPPORT PLAN'!$C$4,17)
J20: =EXPENSES!L26&" - "&EXPENSES!B26 | L20: =EDATE('SUPPORT PLAN'!$C$4,18)
J21: =EXPENSES!L27&" - "&EXPENSES!B27 | L21: =EDATE('SUPPORT PLAN'!$C$4,19)
J22: =EXPENSES!L28&" - "&EXPENSES!B28 | L22: =EDATE('SUPPORT PLAN'!$C$4,20)
J23: =EXPENSES!L29&" - "&EXPENSES!B29 | L23: =EDATE('SUPPORT PLAN'!$C$4,21)
J24: =EXPENSES!L31&" - "&EXPENSES!B31 | L24: =EDATE('SUPPORT PLAN'!$C$4,22)
J25: =EXPENSES!L32&" - "&EXPENSES!B32 | L25: =EDATE('SUPPORT PLAN'!$C$4,23)
J26: =EXPENSES!L33&" - "&EXPENSES!B33
J27: =EXPENSES!L34&" - "&EXPENSES!B34
J28: =EXPENSES!L35&" - "&EXPENSES!B35
J29: =EXPENSES!L36&" - "&EXPENSES!B36
J30: =EXPENSES!L38&" - "&EXPENSES!B38
J31: =EXPENSES!L39&" - "&EXPENSES!B39
J32: =EXPENSES!L40&" - "&EXPENSES!B40
J33: =EXPENSES!L41&" - "&EXPENSES!B41
J34: =EXPENSES!L42&" - "&EXPENSES!B42
J35: =EXPENSES!L43&" - "&EXPENSES!B43
J36: =EXPENSES!L44&" - "&EXPENSES!B44
J37: =EXPENSES!L46&" - "&EXPENSES!B46
J38: =EXPENSES!L47&" - "&EXPENSES!B47
J39: =EXPENSES!L48&" - "&EXPENSES!B48
J40: =EXPENSES!L49&" - "&EXPENSES!B49
J41: =EXPENSES!L50&" - "&EXPENSES!B50
J42: =EXPENSES!L52&" - "&EXPENSES!B52
J43: =EXPENSES!L53&" - "&EXPENSES!B53
J44: =EXPENSES!L54&" - "&EXPENSES!B54
J45: =EXPENSES!L55&" - "&EXPENSES!B55
J46: =EXPENSES!L56&" - "&EXPENSES!B56
J47: =EXPENSES!L57&" - "&EXPENSES!B57
J48: =EXPENSES!L58&" - "&EXPENSES!B58
J49: =EXPENSES!L59&" - "&EXPENSES!B59
J50: =EXPENSES!L60&" - "&EXPENSES!B60
J51: =EXPENSES!L62&" - "&EXPENSES!B62
J52: =EXPENSES!L63&" - "&EXPENSES!B63
J53: =EXPENSES!L64&" - "&EXPENSES!B64
J54: =EXPENSES!L65&" - "&EXPENSES!B65
J55: =EXPENSES!L66&" - "&EXPENSES!B66
J56: =EXPENSES!L67&" - "&EXPENSES!B67
J57: =EXPENSES!L68&" - "&EXPENSES!B68
J58: =EXPENSES!L69&" - "&EXPENSES!B69
J59: =EXPENSES!L70&" - "&EXPENSES!B70
J60: =EXPENSES!L72&" - "&EXPENSES!B72
J61: =EXPENSES!L73&" - "&EXPENSES!B73
J62: =EXPENSES!L74&" - "&EXPENSES!B74
J63: =EXPENSES!L75&" - "&EXPENSES!B75
J64: =EXPENSES!L76&" - "&EXPENSES!B76
J65: =EXPENSES!L77&" - "&EXPENSES!B77
J66: =EXPENSES!L78&" - "&EXPENSES!B78
J67: =EXPENSES!L80&" - "&EXPENSES!B80
J68: =EXPENSES!L81&" - "&EXPENSES!B81
J69: =EXPENSES!L82&" - "&EXPENSES!B82
J70: =EXPENSES!L83&" - "&EXPENSES!B83
J71: =EXPENSES!L84&" - "&EXPENSES!B84
J72: =EXPENSES!L85&" - "&EXPENSES!B85
J73: =EXPENSES!L87&" - "&EXPENSES!B87
J74: =EXPENSES!L89&" - "&EXPENSES!B89
J75: =EXPENSES!L90&" - "&EXPENSES!B90
J76: =EXPENSES!L91&" - "&EXPENSES!B91
J77: =EXPENSES!L92&" - "&EXPENSES!B92
J78: =EXPENSES!L93&" - "&EXPENSES!B93
J79: =EXPENSES!L95&" - "&EXPENSES!B95
J80: =EXPENSES!L96&" - "&EXPENSES!B96
J81: =EXPENSES!L97&" - "&EXPENSES!B97
J82: =EXPENSES!L98&" - "&EXPENSES!B98
J83: =EXPENSES!L100&" - "&EXPENSES!B100
J84: =EXPENSES!L101&" - "&EXPENSES!B101
J85: =EXPENSES!L102&" - "&EXPENSES!B102
J86: =EXPENSES!L103&" - "&EXPENSES!B103
J87: =EXPENSES!L104&" - "&EXPENSES!B104
J88: =EXPENSES!L105&" - "&EXPENSES!B105
J89: =EXPENSES!L107&" - "&EXPENSES!B107
J90: =EXPENSES!L108&" - "&EXPENSES!B108
J91: =EXPENSES!L109&" - "&EXPENSES!B109
J92: =EXPENSES!L110&" - "&EXPENSES!B110
J93: =EXPENSES!L111&" - "&EXPENSES!B111
J94: =EXPENSES!L112&" - "&EXPENSES!B112
J95: =EXPENSES!L113&" - "&EXPENSES!B113
J96: =EXPENSES!L115&" - "&EXPENSES!B115
J97: =EXPENSES!L116&" - "&EXPENSES!B116
J98: =EXPENSES!L117&" - "&EXPENSES!B117
J99: =EXPENSES!L118&" - "&EXPENSES!B118
J100: =EXPENSES!L119&" - "&EXPENSES!B119
...
